// converted by version 1.3
// on Fri Aug 12 13:03:06 CEST 2011

.package des {
	.aid 0x1:0x2:0x3:0x4:0x5:0x6:0x7:0x8:0x9:0x0:0x1;
	.version 1.0;

	.imports {
		0xA0:0x0:0x0:0x0:0x62:0x0:0x1 1.0;		//java/lang
		0xA0:0x0:0x0:0x0:0x62:0x1:0x1 1.2;		//javacard/framework
		0xA0:0x0:0x0:0x0:0x62:0x1:0x2 1.2;		//javacard/security
		0xA0:0x0:0x0:0x0:0x62:0x2:0x1 1.2;		//javacardx/crypto
		0xA0:0x0:0x0:0x0:0x62:0x1:0x1:0x1 1.0;		//javacard/framework/service
	}

	.applet {
		0x1:0x2:0x3:0x4:0x5:0x6:0x7:0x8:0x9:0x0:0x0 DesfireCard;
	}

	.constantPool {
		// 0
		instanceFieldRef boolean File/active;
		// 1
		instanceFieldRef byte File/fileID;
		// 2
		instanceFieldRef byte File/size;
		// 3
		instanceFieldRef MasterFile DesfireCard/masterFile;
		// 4
		instanceFieldRef DirectoryFile DesfireCard/selectedDF;
		// 5
		instanceFieldRef 2.14 DesfireCard/randomData;
		// 6
		instanceFieldRef 3.1 DesfireCard/cipher;
		// 7
		instanceFieldRef byte DesfireCard/commandToContinue;
		// 8
		instanceFieldRef short DesfireCard/offset;
		// 9
		instanceFieldRef short DesfireCard/bytesLeft;
		// 10
		instanceFieldRef byte DesfireCard/keyNumberToAuthenticate;
		// 11
		instanceFieldRef byte DesfireCard/authenticated;
		// 12
		instanceFieldRef 2.0 DesfireCard/sessionKey;
		// 13
		instanceFieldRef byte DesfireCard/securityLevel;
		// 14
		instanceFieldRef 4.3 DesfireCard/bs;
		// 15
		instanceFieldRef byte[] DesfireCard/randomNumberToAuthenticate;
		// 16
		instanceFieldRef DirectoryFile[] MasterFile/arrayDF;
		// 17
		instanceFieldRef byte MasterFile/numApp;
		// 18
		instanceFieldRef boolean[] DirectoryFile/activatedFiles;
		// 19
		instanceFieldRef File DesfireCard/selectedFile;
		// 20
		instanceFieldRef byte[] DesfireCard/dataBuffer;
		// 21
		instanceFieldRef short DesfireCard/readed;
		// 22
		instanceFieldRef short LinearRecord/recordSize;
		// 23
		instanceFieldRef short CyclicRecord/recordSize;
		// 24
		instanceFieldRef boolean[] DirectoryFile/waitingForTransaction;
		// 25
		instanceFieldRef File[] DirectoryFile/arrayFiles;
		// 26
		instanceFieldRef byte[] DirectoryFile/permissions;
		// 27
		instanceFieldRef byte DirectoryFile/numberFiles;
		// 28
		instanceFieldRef boolean DirectoryFile/configurationChangeable;
		// 29
		instanceFieldRef boolean DirectoryFile/masterNotNeededForManage;
		// 30
		instanceFieldRef boolean DirectoryFile/masterNotNeededForCheck;
		// 31
		instanceFieldRef boolean DirectoryFile/masterChangeable;
		// 32
		instanceFieldRef byte DirectoryFile/keyType;
		// 33
		instanceFieldRef 2.0 DirectoryFile/masterKey;
		// 34
		instanceFieldRef byte DirectoryFile/maxKeyNumber;
		// 35
		instanceFieldRef boolean DirectoryFile/ISOFileIDSupported;
		// 36
		instanceFieldRef 2.0[] DirectoryFile/keyList;
		// 37
		instanceFieldRef byte DirectoryFile/changeKeyAccessRights;
		// 38
		instanceFieldRef DirectoryFile CyclicRecord/parentFile;
		// 39
		instanceFieldRef byte[] CyclicRecord/permissions;
		// 40
		instanceFieldRef byte[] CyclicRecord/data;
		// 41
		instanceFieldRef short CyclicRecord/size;
		// 42
		instanceFieldRef short CyclicRecord/maxSize;
		// 43
		instanceFieldRef byte[] CyclicRecord/uncommitedRecord;
		// 44
		instanceFieldRef boolean CyclicRecord/waitingToDeleteRecord;
		// 45
		instanceFieldRef DirectoryFile IndexFile/parentFile;
		// 46
		instanceFieldRef byte[] IndexFile/permissions;
		// 47
		instanceFieldRef byte[] IndexFile/data;
		// 48
		instanceFieldRef short IndexFile/size;
		// 49
		instanceFieldRef short IndexFile/recordSize;
		// 50
		instanceFieldRef DirectoryFile LinearRecord/parentFile;
		// 51
		instanceFieldRef byte[] LinearRecord/permissions;
		// 52
		instanceFieldRef byte[] LinearRecord/data;
		// 53
		instanceFieldRef short LinearRecord/size;
		// 54
		instanceFieldRef short LinearRecord/maxSize;
		// 55
		instanceFieldRef byte[] LinearRecord/uncommitedRecord;
		// 56
		instanceFieldRef boolean LinearRecord/waitingToDeleteRecord;
		// 57
		instanceFieldRef boolean MasterFile/formatEnabled;
		// 58
		instanceFieldRef boolean MasterFile/randomID;
		// 59
		instanceFieldRef IndexFile MasterFile/indexDF;
		// 60
		instanceFieldRef DirectoryFile StandartFile/parentFile;
		// 61
		instanceFieldRef byte[] StandartFile/permissions;
		// 62
		instanceFieldRef byte[] StandartFile/data;
		// 63
		instanceFieldRef byte[] Value/value;
		// 64
		instanceFieldRef DirectoryFile ValueRecord/parentFile;
		// 65
		instanceFieldRef byte[] ValueRecord/permissions;
		// 66
		instanceFieldRef Value ValueRecord/upperLimit;
		// 67
		instanceFieldRef Value ValueRecord/lowerLimit;
		// 68
		instanceFieldRef Value ValueRecord/value;
		// 69
		instanceFieldRef boolean ValueRecord/limitedCreditEnabled;
		// 70
		instanceFieldRef boolean ValueRecord/freeGetValueEnabled;
		// 71
		instanceFieldRef Value ValueRecord/uncommitedValue;
		// 72
		staticMethodRef Util/rotateLeft([B)[B;
		// 73
		staticMethodRef DesfireCard/sendResponseAndChangeStatus(Ljavacard/framework/APDU;[B[B[B)V;
			.descriptor	Ljavacard/framework/APDU;	1.10;

		// 74
		virtualMethodRef DirectoryFile/hasKeySettingsChangeAllowed(B)Z;
		// 75
		virtualMethodRef File/getFileID()B;
		// 76
		virtualMethodRef DirectoryFile/changeKeySettings(B)V;
		// 77
		staticMethodRef MasterFile/<init>()V;
		// 78
		virtualMethodRef DirectoryFile/hasChangeAccess(BB)Z;
		// 79
		virtualMethodRef DirectoryFile/changeKey(B[B)V;
		// 80
		virtualMethodRef DirectoryFile/hasManageRights(B)Z;
		// 81
		virtualMethodRef MasterFile/getIndexDF()Ldes/IndexFile;;
		// 82
		virtualMethodRef IndexFile/hasWriteAccess(B)Z;
		// 83
		virtualMethodRef MasterFile/addDF([B[B)B;
		// 84
		virtualMethodRef MasterFile/searchAID([B)B;
		// 85
		virtualMethodRef MasterFile/deleteDF([B)V;
		// 86
		staticMethodRef 0.0.0()V;		// java/lang/Object.<init>()V
		// 87
		virtualMethodRef DirectoryFile/hasGetRights(B)Z;
		// 88
		virtualMethodRef MasterFile/getAID(B)[B;
		// 89
		staticMethodRef DesfireCard/sendResponse(Ljavacard/framework/APDU;[B[B)V;
			.descriptor	Ljavacard/framework/APDU;	1.10;

		// 90
		virtualMethodRef DirectoryFile/getKeySettings()B;
		// 91
		virtualMethodRef DirectoryFile/getKeyNumber()B;
		// 92
		virtualMethodRef IndexFile/hasReadAccess(B)Z;
		// 93
		staticFieldRef byte[] Util/masterFileAID;
		// 94
		virtualMethodRef MasterFile/isFormatEnabled()Z;
		// 95
		virtualMethodRef MasterFile/format()V;
		// 96
		virtualMethodRef MasterFile/setConfiguration(B)V;
		// 97
		virtualMethodRef DirectoryFile/getMasterKeyType()B;
		// 98
		virtualMethodRef DirectoryFile/getNumberFiles()B;
		// 99
		classRef DesfireCard;
		// 100
		virtualMethodRef DirectoryFile/getFile(B)Ldes/File;;
		// 101
		staticMethodRef DesfireCard/<init>()V;
		// 102
		staticMethodRef Util/byteArrayToShort([B)S;
		// 103
		staticMethodRef 1.8.16(B)S;		// javacard/framework/JCSystem.getAvailableMemory(B)S
		// 104
		classRef StandartFile;
		// 105
		staticMethodRef StandartFile/<init>(BLdes/DirectoryFile;[BS)V;
		// 106
		classRef Value;
		// 107
		staticMethodRef Value/<init>([B)V;
		// 108
		virtualMethodRef Value/compareTo(Ldes/Value;)B;
		// 109
		classRef ValueRecord;
		// 110
		staticMethodRef ValueRecord/<init>(BLdes/DirectoryFile;[BLdes/Value;Ldes/Value;Ldes/Value;B)V;
		// 111
		classRef LinearRecord;
		// 112
		staticMethodRef LinearRecord/<init>(BLdes/DirectoryFile;[BSS)V;
		// 113
		classRef CyclicRecord;
		// 114
		staticMethodRef CyclicRecord/<init>(BLdes/DirectoryFile;[BSS)V;
		// 115
		virtualMethodRef DirectoryFile/deleteFile(B)V;
		// 116
		virtualMethodRef StandartFile/hasReadAccess(B)Z;
		// 117
		virtualMethodRef File/getSize()B;
		// 118
		virtualMethodRef StandartFile/readArray(SSB)[B;
		// 119
		virtualMethodRef StandartFile/hasWriteAccess(B)Z;
		// 120
		virtualMethodRef StandartFile/writeArray([BSS)V;
		// 121
		virtualMethodRef ValueRecord/hasReadAccess(B)Z;
		// 122
		virtualMethodRef ValueRecord/getValue()Ldes/Value;;
		// 123
		virtualMethodRef Value/getValue()[B;
		// 124
		staticMethodRef Util/switchBytes([B)[B;
		// 125
		virtualMethodRef ValueRecord/hasWriteAccess(B)Z;
		// 126
		virtualMethodRef ValueRecord/addCredit(Ldes/Value;)V;
		// 127
		virtualMethodRef ValueRecord/decDebit(Ldes/Value;)V;
		// 128
		staticMethodRef 2.13.0(BSZ)Ljavacard/security/Key;;		// javacard/security/KeyBuilder.buildKey(BSZ)Ljavacard/security/Key;
			.descriptor	Ljavacard/security/Key;	2.0;

		// 129
		virtualMethodRef LinearRecord/hasWriteAccess(B)Z;
		// 130
		virtualMethodRef CyclicRecord/hasWriteAccess(B)Z;
		// 131
		virtualMethodRef LinearRecord/writeRecord([BS)V;
		// 132
		virtualMethodRef CyclicRecord/writeRecord([BS)V;
		// 133
		classRef 2.10;		// javacard/security/DESKey
		// 134
		virtualMethodRef LinearRecord/hasReadAccess(B)Z;
		// 135
		staticMethodRef 2.14.0(B)Ljavacard/security/RandomData;;		// javacard/security/RandomData.getInstance(B)Ljavacard/security/RandomData;
			.descriptor	Ljavacard/security/RandomData;	2.14;

		// 136
		virtualMethodRef LinearRecord/getCurrentSize()S;
		// 137
		virtualMethodRef LinearRecord/readData(SSB)[B;
		// 138
		virtualMethodRef CyclicRecord/hasReadAccess(B)Z;
		// 139
		classRef 2.0;		// javacard/security/Key
		// 140
		virtualMethodRef CyclicRecord/getCurrentSize()S;
		// 141
		virtualMethodRef CyclicRecord/readData(SSB)[B;
		// 142
		virtualMethodRef LinearRecord/deleteRecords()V;
		// 143
		virtualMethodRef CyclicRecord/deleteRecords()V;
		// 144
		staticMethodRef 1.3.0()V;		// javacard/framework/Applet.<init>()V
		// 145
		virtualMethodRef LinearRecord/commitTransaction()V;
		// 146
		virtualMethodRef CyclicRecord/commitTransaction()V;
		// 147
		virtualMethodRef ValueRecord/commitTransaction()V;
		// 148
		virtualMethodRef LinearRecord/abortTransaction()V;
		// 149
		virtualMethodRef CyclicRecord/abortTransaction()V;
		// 150
		virtualMethodRef ValueRecord/abortTransaction()V;
		// 151
		staticMethodRef Util/crc16([B)[B;
		// 152
		staticMethodRef Util/concatByteArray([B[B)[B;
		// 153
		staticMethodRef Util/preparePaddedByteArray([B)[B;
		// 154
		classRef 2.12;		// javacard/security/CryptoException
		// 155
		staticMethodRef Util/removePadding([B)[B;
		// 156
		staticMethodRef Util/byteArrayCompare([B[B)Z;
		// 157
		staticMethodRef DesfireCard/decrypt16([BLjavacard/security/Key;)[B;
			.descriptor	Ljavacard/security/Key;	2.0;

		// 158
		virtualMethodRef 1.10.6()S;		// javacard/framework/APDU.setIncomingAndReceive()S
		// 159
		virtualMethodRef 1.10.3(S)S;		// javacard/framework/APDU.receiveBytes(S)S
		// 160
		staticMethodRef DesfireCard/getCData([B)[B;
		// 161
		staticMethodRef Util/copyByteArray([BSS[BS)[B;
		// 162
		virtualMethodRef 1.10.7()S;		// javacard/framework/APDU.setOutgoing()S
		// 163
		staticMethodRef DesfireCard/encrypt16([BLjavacard/security/Key;)[B;
			.descriptor	Ljavacard/security/Key;	2.0;

		// 164
		virtualMethodRef 1.10.9(S)V;		// javacard/framework/APDU.setOutgoingLength(S)V
		// 165
		virtualMethodRef 1.10.4(SS)V;		// javacard/framework/APDU.sendBytes(SS)V
		// 166
		classRef 1.12;		// javacard/framework/APDUException
		// 167
		virtualMethodRef 1.5.1()S;		// javacard/framework/CardRuntimeException.getReason()S
		// 168
		staticMethodRef DesfireCard/clear()V;
		// 169
		staticMethodRef File/<init>(B)V;
		// 170
		classRef File;
		// 171
		classRef 4.3;		// javacard/framework/service/BasicService
		// 172
		staticMethodRef 4.3.0()V;		// javacard/framework/service/BasicService.<init>()V
		// 173
		staticMethodRef 3.1.0(BZ)Ljavacardx/crypto/Cipher;;		// javacardx/crypto/Cipher.getInstance(BZ)Ljavacardx/crypto/Cipher;
			.descriptor	Ljavacardx/crypto/Cipher;	3.1;

		// 174
		virtualMethodRef 1.3.1()V;		// javacard/framework/Applet.register()V
		// 175
		virtualMethodRef 1.3.3()Z;		// javacard/framework/Applet.selectingApplet()Z
		// 176
		virtualMethodRef 1.10.1()[B;		// javacard/framework/APDU.getBuffer()[B
		// 177
		staticMethodRef 1.7.1(S)V;		// javacard/framework/ISOException.throwIt(S)V
		// 178
		staticMethodRef DesfireCard/authenticate(Ljavacard/framework/APDU;[B)V;
			.descriptor	Ljavacard/framework/APDU;	1.10;

		// 179
		staticFieldRef byte[] Util/DEFAULT_MASTER_KEY;
		// 180
		staticMethodRef DesfireCard/changeKeySettings(Ljavacard/framework/APDU;[B)V;
			.descriptor	Ljavacard/framework/APDU;	1.10;

		// 181
		staticMethodRef DesfireCard/changeKey(Ljavacard/framework/APDU;[B)V;
			.descriptor	Ljavacard/framework/APDU;	1.10;

		// 182
		staticMethodRef DesfireCard/createApplication(Ljavacard/framework/APDU;[B)V;
			.descriptor	Ljavacard/framework/APDU;	1.10;

		// 183
		staticMethodRef DesfireCard/deleteApplication(Ljavacard/framework/APDU;[B)V;
			.descriptor	Ljavacard/framework/APDU;	1.10;

		// 184
		staticMethodRef DesfireCard/getApplicationIDs(Ljavacard/framework/APDU;[B)V;
			.descriptor	Ljavacard/framework/APDU;	1.10;

		// 185
		staticMethodRef File/<init>(BB)V;
		// 186
		staticMethodRef DesfireCard/getKeySettings(Ljavacard/framework/APDU;[B)V;
			.descriptor	Ljavacard/framework/APDU;	1.10;

		// 187
		staticMethodRef DesfireCard/selectApplication(Ljavacard/framework/APDU;[B)V;
			.descriptor	Ljavacard/framework/APDU;	1.10;

		// 188
		staticMethodRef DesfireCard/formatPICC(Ljavacard/framework/APDU;[B)V;
			.descriptor	Ljavacard/framework/APDU;	1.10;

		// 189
		staticMethodRef DesfireCard/setConfiguration(Ljavacard/framework/APDU;[B)V;
			.descriptor	Ljavacard/framework/APDU;	1.10;

		// 190
		staticMethodRef DesfireCard/getFileIDs(Ljavacard/framework/APDU;[B)V;
			.descriptor	Ljavacard/framework/APDU;	1.10;

		// 191
		staticMethodRef DesfireCard/createStdDataFile(Ljavacard/framework/APDU;[B)V;
			.descriptor	Ljavacard/framework/APDU;	1.10;

		// 192
		staticMethodRef DesfireCard/createValueFile(Ljavacard/framework/APDU;[B)V;
			.descriptor	Ljavacard/framework/APDU;	1.10;

		// 193
		virtualMethodRef DirectoryFile/addFile(Ldes/File;)V;
		// 194
		virtualMethodRef CyclicRecord/eraseData()V;
		// 195
		staticMethodRef DesfireCard/createLinearRecordFile(Ljavacard/framework/APDU;[B)V;
			.descriptor	Ljavacard/framework/APDU;	1.10;

		// 196
		staticMethodRef DesfireCard/createCyclicRecordFile(Ljavacard/framework/APDU;[B)V;
			.descriptor	Ljavacard/framework/APDU;	1.10;

		// 197
		staticMethodRef DesfireCard/deleteFile(Ljavacard/framework/APDU;[B)V;
			.descriptor	Ljavacard/framework/APDU;	1.10;

		// 198
		staticMethodRef DesfireCard/readData(Ljavacard/framework/APDU;[B)V;
			.descriptor	Ljavacard/framework/APDU;	1.10;

		// 199
		staticMethodRef DesfireCard/writeData(Ljavacard/framework/APDU;[B)V;
			.descriptor	Ljavacard/framework/APDU;	1.10;

		// 200
		staticMethodRef DesfireCard/getValue(Ljavacard/framework/APDU;[B)V;
			.descriptor	Ljavacard/framework/APDU;	1.10;

		// 201
		staticMethodRef DesfireCard/credit(Ljavacard/framework/APDU;[B)V;
			.descriptor	Ljavacard/framework/APDU;	1.10;

		// 202
		staticMethodRef DesfireCard/debit(Ljavacard/framework/APDU;[B)V;
			.descriptor	Ljavacard/framework/APDU;	1.10;

		// 203
		staticMethodRef DesfireCard/readRecords(Ljavacard/framework/APDU;[B)V;
			.descriptor	Ljavacard/framework/APDU;	1.10;

		// 204
		staticMethodRef DesfireCard/writeRecord(Ljavacard/framework/APDU;[B)V;
			.descriptor	Ljavacard/framework/APDU;	1.10;

		// 205
		staticMethodRef DesfireCard/clearRecordFile(Ljavacard/framework/APDU;[B)V;
			.descriptor	Ljavacard/framework/APDU;	1.10;

		// 206
		staticMethodRef DesfireCard/commitTransaction(Ljavacard/framework/APDU;[B)V;
			.descriptor	Ljavacard/framework/APDU;	1.10;

		// 207
		virtualMethodRef LinearRecord/eraseData()V;
		// 208
		staticMethodRef DirectoryFile/<init>(B)V;
		// 209
		staticMethodRef DesfireCard/abortTransaction(Ljavacard/framework/APDU;[B)V;
			.descriptor	Ljavacard/framework/APDU;	1.10;

		// 210
		staticMethodRef DesfireCard/receiveAPDU(Ljavacard/framework/APDU;[B)V;
			.descriptor	Ljavacard/framework/APDU;	1.10;

		// 211
		classRef IndexFile;
		// 212
		staticMethodRef IndexFile/<init>(BLdes/DirectoryFile;[BSS)V;
		// 213
		virtualMethodRef DirectoryFile/isValidKeyNumber(B)Z;
		// 214
		virtualMethodRef IndexFile/writeRecord(S[B)V;
		// 215
		classRef DirectoryFile;
		// 216
		staticMethodRef DirectoryFile/<init>(B[B)V;
		// 217
		virtualMethodRef IndexFile/deleteRecord(S)V;
		// 218
		virtualMethodRef IndexFile/readValue(S)[B;
		// 219
		classRef MasterFile;
		// 220
		virtualMethodRef 2.14.1([BSS)V;		// javacard/security/RandomData.generateData([BSS)V
		// 221
		virtualMethodRef DirectoryFile/isMasterFile()Z;
		// 222
		virtualMethodRef File/setSize(B)V;
		// 223
		superMethodRef StandartFile/getFileID()B;
		// 224
		staticMethodRef Util/max(SS)S;
		// 225
		staticMethodRef Util/shortToByteArray(S)[B;
		// 226
		virtualMethodRef DirectoryFile/getMasterKey()Ljavacard/security/Key;;
			.descriptor	Ljavacard/security/Key;	2.0;

		// 227
		staticMethodRef Value/isPositive([B)Z;
		// 228
		virtualMethodRef Value/compareAbsoluteValueTo(Ldes/Value;)B;
		// 229
		virtualMethodRef Value/hasOverflowSum(BBB)Z;
		// 230
		virtualMethodRef Value/addValue(Ldes/Value;)Z;
		// 231
		staticMethodRef Value/isPositive(B)Z;
		// 232
		virtualMethodRef 3.1.3(Ljavacard/security/Key;B)V;		// javacardx/crypto/Cipher.init(Ljavacard/security/Key;B)V
			.descriptor	Ljavacard/security/Key;	2.0;

		// 233
		virtualMethodRef DirectoryFile/getKey(B)Ljavacard/security/Key;;
			.descriptor	Ljavacard/security/Key;	2.0;

		// 234
		virtualMethodRef 3.1.1([BSS[BS)S;		// javacardx/crypto/Cipher.doFinal([BSS[BS)S
		// 235
		staticMethodRef DesfireCard/sendResponse(Ljavacard/framework/APDU;[B[BB)V;
			.descriptor	Ljavacard/framework/APDU;	1.10;

		// 236
		staticMethodRef Util/subByteArray([BBB)[B;
		// 237
		staticMethodRef Util/rotateRight([B)[B;
		// 238
		staticMethodRef 1.16.0([BS[BSS)B;		// javacard/framework/Util.arrayCompare([BS[BSS)B
		// 239
		staticMethodRef Util/create3DESSessionKey([B[B)[B;
		// 240
		virtualMethodRef ValueRecord/valueOutBounds(Ldes/Value;)Z;
		// 241
		virtualMethodRef Value/subtractValue(Ldes/Value;)Z;
	}

	.class public abstract File 0 extends 0.0 {		// extends java/lang/Object

		.fields {
			protected boolean active 0;		// Z
			private byte fileID 1;		// B
			private byte size 2;		// B
		}

		.publicMethodTable 1 {
			equals(Ljava/lang/Object;)Z;
			getFileID()B;
			setActive(Z)V;
			getSize()B;
			setSize(B)V;
		}

		.packageMethodTable 0 {
		}

		.method public <init>(B)V 0 {
			.stack 2;
			.locals 0;

				L0:	aload_0;
					invokespecial 86;		// java/lang/Object.<init>()V
					aload_0;
					sconst_1;
					putfield_b 0;		// boolean des/File.active
					aload_0;
					sload_1;
					putfield_b 1;		// byte des/File.fileID
					return;
		}

		.method public <init>(BB)V 1 {
			.stack 2;
			.locals 0;

				L0:	aload_0;
					invokespecial 86;		// java/lang/Object.<init>()V
					aload_0;
					sconst_1;
					putfield_b 0;		// boolean des/File.active
					aload_0;
					sload_1;
					putfield_b 1;		// byte des/File.fileID
					return;
		}

		.method public getFileID()B 1 {
			.stack 1;
			.locals 0;

				L0:	getfield_b_this 1;		// byte des/File.fileID
					sreturn;
		}

		.method public setActive(Z)V 2 {
			.stack 2;
			.locals 0;

				L0:	aload_0;
					sload_1;
					putfield_b 0;		// boolean des/File.active
					return;
		}

		.method public getSize()B 3 {
			.stack 1;
			.locals 0;

				L0:	getfield_b_this 2;		// byte des/File.size
					sreturn;
		}

		.method public setSize(B)V 4 {
			.stack 2;
			.locals 0;

				L0:	aload_0;
					sload_1;
					putfield_b 2;		// byte des/File.size
					return;
		}

	}

	.class public DesfireCard 1 extends 1.3 {		// extends javacard/framework/Applet

		.fields {
			protected MasterFile masterFile 0;		// Ldes/MasterFile;
			private File selectedFile 1;		// Ldes/File;
			private DirectoryFile selectedDF 2;		// Ldes/DirectoryFile;
			private 2.14 randomData 3;		// Ljavacard/security/RandomData;
			private 3.1 cipher 4;		// Ljavacardx/crypto/Cipher;
			private byte[] dataBuffer 5;		// [B
			 byte[] randomNumberToAuthenticate 6;		// [B
			 4.3 bs 7;		// Ljavacard/framework/service/BasicService;
			 2.0 sessionKey 8;		// Ljavacard/security/Key;
			private byte commandToContinue 9;		// B
			private short readed 10;		// S
			private short offset 11;		// S
			private short bytesLeft 12;		// S
			private byte keyNumberToAuthenticate 13;		// B
			private byte authenticated 14;		// B
			 byte securityLevel 15;		// B
		}

		.publicMethodTable 7 {
			equals(Ljava/lang/Object;)Z;
			register()V;
			register([BSB)V;
			selectingApplet()Z;
			deselect()V;
			getShareableInterfaceObject(Ljavacard/framework/AID;B)Ljavacard/framework/Shareable;;
			select()Z;
			process(Ljavacard/framework/APDU;)V;
			select(Z)Z;
			deselect(Z)V;
		}

		.packageMethodTable 0 {
		}

		.implementedInterfaceInfoTable { 
			.interface 1.17 { 		// javacard/framework/MultiSelectable
				8;		// select(Z)Z
				9;		// deselect(Z)V
			}

		}

		.method public static install([BSB)V 0 {
			.stack 2;
			.locals 0;

				L0:	new 99;		// des/DesfireCard
					dup;
					invokespecial 101;		// des/DesfireCard.<init>()V
					pop;
					return;
		}

		.method protected <init>()V 1 {
			.stack 4;
			.locals 0;

				L0:	aload_0;
					invokespecial 144;		// javacard/framework/Applet.<init>()V
					aload_0;
					new 219;		// des/MasterFile
					dup;
					invokespecial 77;		// des/MasterFile.<init>()V
					putfield_a 3;		// reference des/DesfireCard.masterFile
					aload_0;
					getfield_a_this 3;		// reference des/DesfireCard.masterFile
					putfield_a 4;		// reference des/DesfireCard.selectedDF
					getfield_a_this 5;		// reference des/DesfireCard.randomData
					ifnonnull L2;
				L1:	aload_0;
					sconst_2;
					invokestatic 135;		// javacard/security/RandomData.getInstance(B)Ljavacard/security/RandomData;
					putfield_a 5;		// reference des/DesfireCard.randomData
				L2:	getfield_a_this 6;		// reference des/DesfireCard.cipher
					ifnonnull L4;
				L3:	aload_0;
					sconst_5;
					sconst_0;
					invokestatic 173;		// javacardx/crypto/Cipher.getInstance(BZ)Ljavacardx/crypto/Cipher;
					putfield_a 6;		// reference des/DesfireCard.cipher
				L4:	aload_0;
					sconst_0;
					putfield_b 7;		// byte des/DesfireCard.commandToContinue
					aload_0;
					sconst_0;
					putfield_s 8;		// short des/DesfireCard.offset
					aload_0;
					sconst_0;
					putfield_s 9;		// short des/DesfireCard.bytesLeft
					aload_0;
					sconst_0;
					putfield_b 10;		// byte des/DesfireCard.keyNumberToAuthenticate
					aload_0;
					sconst_m1;
					putfield_b 11;		// byte des/DesfireCard.authenticated
					aload_0;
					sconst_3;
					sspush 128;
					sconst_0;
					invokestatic 128;		// javacard/security/KeyBuilder.buildKey(BSZ)Ljavacard/security/Key;
					checkcast 0 133;		// T_CLASSORINTERFACE javacard/security/DESKey
					putfield_a 12;		// reference des/DesfireCard.sessionKey
					getfield_a_this 12;		// reference des/DesfireCard.sessionKey
					invokeinterface 1 139 0;		// javacard/security/Key
					aload_0;
					sconst_0;
					putfield_b 13;		// byte des/DesfireCard.securityLevel
					aload_0;
					new 171;		// javacard/framework/service/BasicService
					dup;
					invokespecial 172;		// javacard/framework/service/BasicService.<init>()V
					putfield_a 14;		// reference des/DesfireCard.bs
					aload_0;
					invokevirtual 174;		// javacard/framework/Applet.register()V
					return;
		}

		.method public process(Ljavacard/framework/APDU;)V 7 {
			.stack 3;
			.locals 1;

			.descriptor	Ljavacard/framework/APDU;	1.10;

				L0:	aload_0;
					invokevirtual 175;		// javacard/framework/Applet.selectingApplet()Z
					ifeq L2;
				L1:	return;
				L2:	aload_1;
					invokevirtual 176;		// javacard/framework/APDU.getBuffer()[B
					astore_2;
					getfield_b_this 11;		// byte des/DesfireCard.authenticated
					sconst_m1;
					if_scmpne L4;
				L3:	aload_0;
					sconst_0;
					putfield_b 13;		// byte des/DesfireCard.securityLevel
				L4:	getfield_b_this 7;		// byte des/DesfireCard.commandToContinue
					ifeq L7;
				L5:	aload_2;
					sconst_1;
					baload;
					bspush -81;
					if_scmpeq L7;
				L6:	sspush -28214;
					invokestatic 177;		// javacard/framework/ISOException.throwIt(S)V
				L7:	aload_2;
					sconst_1;
					baload;
					slookupswitch L42 27 -115 L24 -89 L33 -81 L34 -69 L29 -64 L22 -63 L21 -60 L10 -57 L32 -54 L11 -52 L20 -51 L19 -38 L12 -36 L28 -33 L23 -21 L31 -4 L16 10 L8 12 L27 59 L30 61 L25 69 L14 84 L9 90 L15 92 L17 106 L13 108 L26 111 L18;
				L8:	aload_0;
					aload_1;
					aload_2;
					invokespecial 178;		// des/DesfireCard.authenticate(Ljavacard/framework/APDU;[B)V
					goto_w L43;
				L9:	aload_0;
					aload_1;
					aload_2;
					invokespecial 180;		// des/DesfireCard.changeKeySettings(Ljavacard/framework/APDU;[B)V
					goto_w L43;
				L10:	aload_0;
					aload_1;
					aload_2;
					invokespecial 181;		// des/DesfireCard.changeKey(Ljavacard/framework/APDU;[B)V
					goto_w L43;
				L11:	aload_0;
					aload_1;
					aload_2;
					invokespecial 182;		// des/DesfireCard.createApplication(Ljavacard/framework/APDU;[B)V
					goto_w L43;
				L12:	aload_0;
					aload_1;
					aload_2;
					invokespecial 183;		// des/DesfireCard.deleteApplication(Ljavacard/framework/APDU;[B)V
					goto_w L43;
				L13:	aload_0;
					aload_1;
					aload_2;
					invokespecial 184;		// des/DesfireCard.getApplicationIDs(Ljavacard/framework/APDU;[B)V
					goto_w L43;
				L14:	aload_0;
					aload_1;
					aload_2;
					invokespecial 186;		// des/DesfireCard.getKeySettings(Ljavacard/framework/APDU;[B)V
					goto_w L43;
				L15:	aload_0;
					aload_1;
					aload_2;
					invokespecial 187;		// des/DesfireCard.selectApplication(Ljavacard/framework/APDU;[B)V
					goto_w L43;
				L16:	aload_0;
					aload_1;
					aload_2;
					invokespecial 188;		// des/DesfireCard.formatPICC(Ljavacard/framework/APDU;[B)V
					goto_w L43;
				L17:	aload_0;
					aload_1;
					aload_2;
					invokespecial 189;		// des/DesfireCard.setConfiguration(Ljavacard/framework/APDU;[B)V
					goto_w L43;
				L18:	aload_0;
					aload_1;
					aload_2;
					invokespecial 190;		// des/DesfireCard.getFileIDs(Ljavacard/framework/APDU;[B)V
					goto_w L43;
				L19:	aload_0;
					aload_1;
					aload_2;
					invokespecial 191;		// des/DesfireCard.createStdDataFile(Ljavacard/framework/APDU;[B)V
					goto_w L43;
				L20:	aload_0;
					aload_1;
					aload_2;
					invokespecial 192;		// des/DesfireCard.createValueFile(Ljavacard/framework/APDU;[B)V
					goto_w L43;
				L21:	aload_0;
					aload_1;
					aload_2;
					invokespecial 195;		// des/DesfireCard.createLinearRecordFile(Ljavacard/framework/APDU;[B)V
					goto_w L43;
				L22:	aload_0;
					aload_1;
					aload_2;
					invokespecial 196;		// des/DesfireCard.createCyclicRecordFile(Ljavacard/framework/APDU;[B)V
					goto_w L43;
				L23:	aload_0;
					aload_1;
					aload_2;
					invokespecial 197;		// des/DesfireCard.deleteFile(Ljavacard/framework/APDU;[B)V
					goto_w L43;
				L24:	aload_0;
					aload_1;
					aload_2;
					invokespecial 198;		// des/DesfireCard.readData(Ljavacard/framework/APDU;[B)V
					goto_w L43;
				L25:	aload_0;
					aload_1;
					aload_2;
					invokespecial 199;		// des/DesfireCard.writeData(Ljavacard/framework/APDU;[B)V
					goto_w L43;
				L26:	aload_0;
					aload_1;
					aload_2;
					invokespecial 200;		// des/DesfireCard.getValue(Ljavacard/framework/APDU;[B)V
					goto_w L43;
				L27:	aload_0;
					aload_1;
					aload_2;
					invokespecial 201;		// des/DesfireCard.credit(Ljavacard/framework/APDU;[B)V
					goto_w L43;
				L28:	aload_0;
					aload_1;
					aload_2;
					invokespecial 202;		// des/DesfireCard.debit(Ljavacard/framework/APDU;[B)V
					goto_w L43;
				L29:	aload_0;
					aload_1;
					aload_2;
					invokespecial 203;		// des/DesfireCard.readRecords(Ljavacard/framework/APDU;[B)V
					goto_w L43;
				L30:	aload_0;
					aload_1;
					aload_2;
					invokespecial 204;		// des/DesfireCard.writeRecord(Ljavacard/framework/APDU;[B)V
					goto L43;
				L31:	aload_0;
					aload_1;
					aload_2;
					invokespecial 205;		// des/DesfireCard.clearRecordFile(Ljavacard/framework/APDU;[B)V
					goto L43;
				L32:	aload_0;
					aload_1;
					aload_2;
					invokespecial 206;		// des/DesfireCard.commitTransaction(Ljavacard/framework/APDU;[B)V
					goto L43;
				L33:	aload_0;
					aload_1;
					aload_2;
					invokespecial 209;		// des/DesfireCard.abortTransaction(Ljavacard/framework/APDU;[B)V
					goto L43;
				L34:	getfield_b_this 7;		// byte des/DesfireCard.commandToContinue
					slookupswitch L41 6 -115 L37 -69 L39 10 L35 59 L40 61 L38 106 L36;
				L35:	aload_0;
					aload_1;
					aload_2;
					invokespecial 178;		// des/DesfireCard.authenticate(Ljavacard/framework/APDU;[B)V
					goto L43;
				L36:	aload_0;
					aload_1;
					aload_2;
					invokespecial 184;		// des/DesfireCard.getApplicationIDs(Ljavacard/framework/APDU;[B)V
					goto L43;
				L37:	aload_0;
					aload_1;
					aload_2;
					invokespecial 198;		// des/DesfireCard.readData(Ljavacard/framework/APDU;[B)V
					goto L43;
				L38:	aload_0;
					aload_1;
					aload_2;
					invokespecial 199;		// des/DesfireCard.writeData(Ljavacard/framework/APDU;[B)V
					goto L43;
				L39:	aload_0;
					aload_1;
					aload_2;
					invokespecial 203;		// des/DesfireCard.readRecords(Ljavacard/framework/APDU;[B)V
					goto L43;
				L40:	aload_0;
					aload_1;
					aload_2;
					invokespecial 204;		// des/DesfireCard.writeRecord(Ljavacard/framework/APDU;[B)V
					goto L43;
				L41:	sspush -28388;
					invokestatic 177;		// javacard/framework/ISOException.throwIt(S)V
					goto L43;
				L42:	sspush -28388;
					invokestatic 177;		// javacard/framework/ISOException.throwIt(S)V
				L43:	return;
		}

		.method private authenticate(Ljavacard/framework/APDU;[B)V {
			.stack 6;
			.locals 6;

			.descriptor	Ljavacard/framework/APDU;	1.10;

				L0:	aload_0;
					aload_1;
					aload_2;
					invokespecial 210;		// des/DesfireCard.receiveAPDU(Ljavacard/framework/APDU;[B)V
					getfield_b_this 7;		// byte des/DesfireCard.commandToContinue
					ifne L7;
				L1:	aload_0;
					aload_2;
					sconst_5;
					baload;
					putfield_b 10;		// byte des/DesfireCard.keyNumberToAuthenticate
					getfield_a_this 4;		// reference des/DesfireCard.selectedDF
					getfield_b_this 10;		// byte des/DesfireCard.keyNumberToAuthenticate
					invokevirtual 213;		// des/DirectoryFile.isValidKeyNumber(B)Z
					ifne L3;
				L2:	sspush -28352;
					invokestatic 177;		// javacard/framework/ISOException.throwIt(S)V
				L3:	aload_0;
					bspush 8;
					newarray 11;
					putfield_a 15;		// reference des/DesfireCard.randomNumberToAuthenticate
					getfield_a_this 5;		// reference des/DesfireCard.randomData
					getfield_a_this 15;		// reference des/DesfireCard.randomNumberToAuthenticate
					sconst_0;
					bspush 8;
					invokevirtual 220;		// javacard/security/RandomData.generateData([BSS)V
					bspush 8;
					newarray 11;
					astore_3;
					getfield_a_this 4;		// reference des/DesfireCard.selectedDF
					invokevirtual 221;		// des/DirectoryFile.isMasterFile()Z
					ifeq L5;
				L4:	getfield_a_this 6;		// reference des/DesfireCard.cipher
					getfield_a_this 4;		// reference des/DesfireCard.selectedDF
					invokevirtual 226;		// des/DirectoryFile.getMasterKey()Ljavacard/security/Key;
					sconst_2;
					invokevirtual 232;		// javacardx/crypto/Cipher.init(Ljavacard/security/Key;B)V
					goto L6;
				L5:	getfield_a_this 6;		// reference des/DesfireCard.cipher
					getfield_a_this 4;		// reference des/DesfireCard.selectedDF
					getfield_b_this 10;		// byte des/DesfireCard.keyNumberToAuthenticate
					invokevirtual 233;		// des/DirectoryFile.getKey(B)Ljavacard/security/Key;
					sconst_2;
					invokevirtual 232;		// javacardx/crypto/Cipher.init(Ljavacard/security/Key;B)V
				L6:	getfield_a_this 6;		// reference des/DesfireCard.cipher
					getfield_a_this 15;		// reference des/DesfireCard.randomNumberToAuthenticate
					sconst_0;
					bspush 8;
					aload_3;
					sconst_0;
					invokevirtual 234;		// javacardx/crypto/Cipher.doFinal([BSS[BS)S
					pop;
					aload_0;
					bspush 10;
					putfield_b 7;		// byte des/DesfireCard.commandToContinue
					aload_0;
					aload_1;
					aload_2;
					aload_3;
					bspush -81;
					invokespecial 235;		// des/DesfireCard.sendResponse(Ljavacard/framework/APDU;[B[BB)V
					goto_w L17;
				L7:	aload_0;
					sconst_0;
					putfield_b 7;		// byte des/DesfireCard.commandToContinue
					bspush 8;
					newarray 11;
					astore_3;
					bspush 16;
					newarray 11;
					astore 4;
					bspush 8;
					newarray 11;
					astore 5;
					bspush 8;
					newarray 11;
					astore 6;
					bspush 16;
					newarray 11;
					astore 7;
					aload_2;
					sconst_5;
					bspush 21;
					invokestatic 236;		// des/Util.subByteArray([BBB)[B
					astore 4;
					getfield_a_this 4;		// reference des/DesfireCard.selectedDF
					invokevirtual 221;		// des/DirectoryFile.isMasterFile()Z
					ifeq L9;
				L8:	getfield_a_this 6;		// reference des/DesfireCard.cipher
					getfield_a_this 4;		// reference des/DesfireCard.selectedDF
					invokevirtual 226;		// des/DirectoryFile.getMasterKey()Ljavacard/security/Key;
					sconst_1;
					invokevirtual 232;		// javacardx/crypto/Cipher.init(Ljavacard/security/Key;B)V
					goto L10;
				L9:	getfield_a_this 6;		// reference des/DesfireCard.cipher
					getfield_a_this 4;		// reference des/DesfireCard.selectedDF
					getfield_b_this 10;		// byte des/DesfireCard.keyNumberToAuthenticate
					invokevirtual 233;		// des/DirectoryFile.getKey(B)Ljavacard/security/Key;
					sconst_1;
					invokevirtual 232;		// javacardx/crypto/Cipher.init(Ljavacard/security/Key;B)V
				L10:	getfield_a_this 6;		// reference des/DesfireCard.cipher
					aload 4;
					sconst_0;
					bspush 16;
					aload 7;
					sconst_0;
					invokevirtual 234;		// javacardx/crypto/Cipher.doFinal([BSS[BS)S
					pop;
					aload 7;
					sconst_0;
					bspush 7;
					invokestatic 236;		// des/Util.subByteArray([BBB)[B
					astore 5;
					aload 7;
					bspush 8;
					bspush 15;
					invokestatic 236;		// des/Util.subByteArray([BBB)[B
					astore 6;
					aload 6;
					invokestatic 237;		// des/Util.rotateRight([B)[B
					astore 6;
					aload 6;
					sconst_0;
					getfield_a_this 15;		// reference des/DesfireCard.randomNumberToAuthenticate
					sconst_0;
					aload 6;
					arraylength;
					invokestatic 238;		// javacard/framework/Util.arrayCompare([BS[BSS)B
					ifeq L12;
				L11:	aload_0;
					sconst_m1;
					putfield_b 11;		// byte des/DesfireCard.authenticated
					sspush -28242;
					invokestatic 177;		// javacard/framework/ISOException.throwIt(S)V
					goto L13;
				L12:	aload_0;
					getfield_b_this 10;		// byte des/DesfireCard.keyNumberToAuthenticate
					putfield_b 11;		// byte des/DesfireCard.authenticated
				L13:	aload 5;
					aload 6;
					invokestatic 239;		// des/Util.create3DESSessionKey([B[B)[B
					astore 8;
					aload 5;
					invokestatic 72;		// des/Util.rotateLeft([B)[B
					astore 5;
					getfield_a_this 4;		// reference des/DesfireCard.selectedDF
					invokevirtual 221;		// des/DirectoryFile.isMasterFile()Z
					ifeq L15;
				L14:	getfield_a_this 6;		// reference des/DesfireCard.cipher
					getfield_a_this 4;		// reference des/DesfireCard.selectedDF
					invokevirtual 226;		// des/DirectoryFile.getMasterKey()Ljavacard/security/Key;
					sconst_2;
					invokevirtual 232;		// javacardx/crypto/Cipher.init(Ljavacard/security/Key;B)V
					goto L16;
				L15:	getfield_a_this 6;		// reference des/DesfireCard.cipher
					getfield_a_this 4;		// reference des/DesfireCard.selectedDF
					getfield_b_this 10;		// byte des/DesfireCard.keyNumberToAuthenticate
					invokevirtual 233;		// des/DirectoryFile.getKey(B)Ljavacard/security/Key;
					sconst_2;
					invokevirtual 232;		// javacardx/crypto/Cipher.init(Ljavacard/security/Key;B)V
				L16:	getfield_a_this 6;		// reference des/DesfireCard.cipher
					aload 5;
					sconst_0;
					bspush 8;
					aload_3;
					sconst_0;
					invokevirtual 234;		// javacardx/crypto/Cipher.doFinal([BSS[BS)S
					pop;
					aload_0;
					aload_1;
					aload_2;
					aload_3;
					aload 8;
					invokespecial 73;		// des/DesfireCard.sendResponseAndChangeStatus(Ljavacard/framework/APDU;[B[B[B)V
				L17:	return;
		}

		.method private changeKeySettings(Ljavacard/framework/APDU;[B)V {
			.stack 3;
			.locals 1;

			.descriptor	Ljavacard/framework/APDU;	1.10;

				L0:	aload_0;
					aload_1;
					aload_2;
					invokespecial 210;		// des/DesfireCard.receiveAPDU(Ljavacard/framework/APDU;[B)V
					aload_2;
					sconst_5;
					baload;
					sstore_3;
					getfield_a_this 4;		// reference des/DesfireCard.selectedDF
					getfield_b_this 11;		// byte des/DesfireCard.authenticated
					invokevirtual 74;		// des/DirectoryFile.hasKeySettingsChangeAllowed(B)Z
					ifne L2;
				L1:	sspush -28259;
					invokestatic 177;		// javacard/framework/ISOException.throwIt(S)V
				L2:	getfield_a_this 4;		// reference des/DesfireCard.selectedDF
					invokevirtual 75;		// des/File.getFileID()B
					ifne L4;
				L3:	getfield_a_this 3;		// reference des/DesfireCard.masterFile
					sload_3;
					invokevirtual 76;		// des/DirectoryFile.changeKeySettings(B)V
					aload_0;
					getfield_a_this 3;		// reference des/DesfireCard.masterFile
					putfield_a 4;		// reference des/DesfireCard.selectedDF
					goto L5;
				L4:	getfield_a_this 4;		// reference des/DesfireCard.selectedDF
					sload_3;
					invokevirtual 76;		// des/DirectoryFile.changeKeySettings(B)V
					getfield_a_this 3;		// reference des/DesfireCard.masterFile
					getfield_a 16;		// reference des/MasterFile.arrayDF
					getfield_a_this 4;		// reference des/DesfireCard.selectedDF
					invokevirtual 75;		// des/File.getFileID()B
					getfield_a_this 4;		// reference des/DesfireCard.selectedDF
					aastore;
				L5:	sspush -28416;
					invokestatic 177;		// javacard/framework/ISOException.throwIt(S)V
					return;
		}

		.method private changeKey(Ljavacard/framework/APDU;[B)V {
			.stack 6;
			.locals 3;

			.descriptor	Ljavacard/framework/APDU;	1.10;

				L0:	aload_0;
					aload_1;
					aload_2;
					invokespecial 210;		// des/DesfireCard.receiveAPDU(Ljavacard/framework/APDU;[B)V
					aload_2;
					sconst_5;
					baload;
					sstore_3;
					getfield_a_this 4;		// reference des/DesfireCard.selectedDF
					getfield_b_this 11;		// byte des/DesfireCard.authenticated
					sload_3;
					invokevirtual 78;		// des/DirectoryFile.hasChangeAccess(BB)Z
					ifne L2;
				L1:	sspush -28259;
					invokestatic 177;		// javacard/framework/ISOException.throwIt(S)V
				L2:	aload_2;
					sconst_4;
					baload;
					sconst_1;
					ssub;
					s2b;
					newarray 11;
					astore 4;
					sconst_0;
					sstore 5;
				L3:	sload 5;
					aload 4;
					arraylength;
					if_scmpge L5;
				L4:	aload 4;
					sload 5;
					aload_2;
					sconst_5;
					sload 5;
					sadd;
					sconst_1;
					sadd;
					s2b;
					baload;
					bastore;
					sload 5;
					sconst_1;
					sadd;
					s2b;
					sstore 5;
					goto L3;
				L5:	getfield_a_this 6;		// reference des/DesfireCard.cipher
					getfield_a_this 4;		// reference des/DesfireCard.selectedDF
					getfield_b_this 10;		// byte des/DesfireCard.keyNumberToAuthenticate
					invokevirtual 233;		// des/DirectoryFile.getKey(B)Ljavacard/security/Key;
					sconst_1;
					invokevirtual 232;		// javacardx/crypto/Cipher.init(Ljavacard/security/Key;B)V
					aload 4;
					arraylength;
					newarray 11;
					astore 5;
					getfield_a_this 6;		// reference des/DesfireCard.cipher
					aload 4;
					sconst_0;
					bspush 16;
					aload 5;
					sconst_0;
					invokevirtual 234;		// javacardx/crypto/Cipher.doFinal([BSS[BS)S
					pop;
					getfield_a_this 4;		// reference des/DesfireCard.selectedDF
					invokevirtual 221;		// des/DirectoryFile.isMasterFile()Z
					ifeq L9;
				L6:	getfield_b_this 11;		// byte des/DesfireCard.authenticated
					sload_3;
					if_scmpne L8;
				L7:	aload_0;
					sconst_m1;
					putfield_b 11;		// byte des/DesfireCard.authenticated
				L8:	getfield_a_this 3;		// reference des/DesfireCard.masterFile
					sload_3;
					aload 5;
					invokevirtual 79;		// des/DirectoryFile.changeKey(B[B)V
					aload_0;
					getfield_a_this 3;		// reference des/DesfireCard.masterFile
					putfield_a 4;		// reference des/DesfireCard.selectedDF
					goto L12;
				L9:	getfield_b_this 11;		// byte des/DesfireCard.authenticated
					sload_3;
					if_scmpne L11;
				L10:	aload_0;
					sconst_m1;
					putfield_b 11;		// byte des/DesfireCard.authenticated
				L11:	getfield_a_this 4;		// reference des/DesfireCard.selectedDF
					sload_3;
					aload 5;
					invokevirtual 79;		// des/DirectoryFile.changeKey(B[B)V
					getfield_a_this 3;		// reference des/DesfireCard.masterFile
					getfield_a 16;		// reference des/MasterFile.arrayDF
					getfield_a_this 4;		// reference des/DesfireCard.selectedDF
					invokevirtual 75;		// des/File.getFileID()B
					getfield_a_this 4;		// reference des/DesfireCard.selectedDF
					aastore;
				L12:	sspush -28416;
					invokestatic 177;		// javacard/framework/ISOException.throwIt(S)V
					return;
		}

		.method private createApplication(Ljavacard/framework/APDU;[B)V {
			.stack 5;
			.locals 2;

			.descriptor	Ljavacard/framework/APDU;	1.10;

				L0:	aload_0;
					aload_1;
					aload_2;
					invokespecial 210;		// des/DesfireCard.receiveAPDU(Ljavacard/framework/APDU;[B)V
					getfield_a_this 3;		// reference des/DesfireCard.masterFile
					getfield_b_this 11;		// byte des/DesfireCard.authenticated
					invokevirtual 80;		// des/DirectoryFile.hasManageRights(B)Z
					ifne L2;
				L1:	sspush -28259;
					invokestatic 177;		// javacard/framework/ISOException.throwIt(S)V
				L2:	getfield_a_this 3;		// reference des/DesfireCard.masterFile
					invokevirtual 81;		// des/MasterFile.getIndexDF()Ldes/IndexFile;
					sconst_0;
					invokevirtual 82;		// des/IndexFile.hasWriteAccess(B)Z
					ifne L4;
				L3:	sspush -28259;
					invokestatic 177;		// javacard/framework/ISOException.throwIt(S)V
				L4:	sconst_3;
					newarray 11;
					dup;
					sconst_0;
					aload_2;
					sconst_5;
					baload;
					bastore;
					dup;
					sconst_1;
					aload_2;
					bspush 6;
					baload;
					bastore;
					dup;
					sconst_2;
					aload_2;
					bspush 7;
					baload;
					bastore;
					astore_3;
					sconst_2;
					newarray 11;
					dup;
					sconst_0;
					aload_2;
					bspush 8;
					baload;
					bastore;
					dup;
					sconst_1;
					aload_2;
					bspush 9;
					baload;
					bastore;
					astore 4;
					getfield_a_this 3;		// reference des/DesfireCard.masterFile
					aload_3;
					aload 4;
					invokevirtual 83;		// des/MasterFile.addDF([B[B)B
					pop;
					sspush -28416;
					invokestatic 177;		// javacard/framework/ISOException.throwIt(S)V
					return;
		}

		.method private deleteApplication(Ljavacard/framework/APDU;[B)V {
			.stack 5;
			.locals 1;

			.descriptor	Ljavacard/framework/APDU;	1.10;

				L0:	aload_0;
					aload_1;
					aload_2;
					invokespecial 210;		// des/DesfireCard.receiveAPDU(Ljavacard/framework/APDU;[B)V
					sconst_3;
					newarray 11;
					dup;
					sconst_0;
					aload_2;
					sconst_5;
					baload;
					bastore;
					dup;
					sconst_1;
					aload_2;
					bspush 6;
					baload;
					bastore;
					dup;
					sconst_2;
					aload_2;
					bspush 7;
					baload;
					bastore;
					astore_3;
					getfield_a_this 3;		// reference des/DesfireCard.masterFile
					getfield_b_this 11;		// byte des/DesfireCard.authenticated
					invokevirtual 80;		// des/DirectoryFile.hasManageRights(B)Z
					ifne L2;
				L1:	sspush -28259;
					invokestatic 177;		// javacard/framework/ISOException.throwIt(S)V
				L2:	getfield_a_this 4;		// reference des/DesfireCard.selectedDF
					invokevirtual 75;		// des/File.getFileID()B
					getfield_a_this 3;		// reference des/DesfireCard.masterFile
					aload_3;
					invokevirtual 84;		// des/MasterFile.searchAID([B)B
					if_scmpne L4;
				L3:	aload_0;
					getfield_a_this 3;		// reference des/DesfireCard.masterFile
					putfield_a 4;		// reference des/DesfireCard.selectedDF
				L4:	getfield_a_this 3;		// reference des/DesfireCard.masterFile
					aload_3;
					invokevirtual 85;		// des/MasterFile.deleteDF([B)V
					getfield_a_this 4;		// reference des/DesfireCard.selectedDF
					invokevirtual 221;		// des/DirectoryFile.isMasterFile()Z
					ifeq L6;
				L5:	aload_0;
					getfield_a_this 3;		// reference des/DesfireCard.masterFile
					putfield_a 4;		// reference des/DesfireCard.selectedDF
				L6:	sspush -28416;
					invokestatic 177;		// javacard/framework/ISOException.throwIt(S)V
					return;
		}

		.method private getApplicationIDs(Ljavacard/framework/APDU;[B)V {
			.stack 4;
			.locals 4;

			.descriptor	Ljavacard/framework/APDU;	1.10;

				L0:	getfield_a_this 3;		// reference des/DesfireCard.masterFile
					getfield_b 17;		// byte des/MasterFile.numApp
					sconst_1;
					ssub;
					s2b;
					sstore 4;
					getfield_b_this 7;		// byte des/DesfireCard.commandToContinue
					ifne L12;
				L1:	getfield_a_this 3;		// reference des/DesfireCard.masterFile
					getfield_b_this 11;		// byte des/DesfireCard.authenticated
					invokevirtual 87;		// des/DirectoryFile.hasGetRights(B)Z
					ifne L3;
				L2:	sspush -28259;
					invokestatic 177;		// javacard/framework/ISOException.throwIt(S)V
				L3:	sload 4;
					ifne L5;
				L4:	sspush -28416;
					invokestatic 177;		// javacard/framework/ISOException.throwIt(S)V
				L5:	sload 4;
					bspush 19;
					if_scmple L7;
				L6:	bspush 57;
					newarray 11;
					astore_3;
					aload_0;
					bspush 106;
					putfield_b 7;		// byte des/DesfireCard.commandToContinue
					goto L8;
				L7:	sload 4;
					sconst_3;
					smul;
					s2b;
					newarray 11;
					astore_3;
				L8:	sconst_0;
					sstore 5;
				L9:	sload 5;
					aload_3;
					arraylength;
					if_scmpge L11;
				L10:	getfield_a_this 3;		// reference des/DesfireCard.masterFile
					sload 5;
					sconst_3;
					sdiv;
					sconst_1;
					sadd;
					s2b;
					invokevirtual 88;		// des/MasterFile.getAID(B)[B
					astore 6;
					aload_3;
					sload 5;
					aload 6;
					sconst_0;
					baload;
					bastore;
					aload_3;
					sload 5;
					sconst_1;
					sadd;
					s2b;
					aload 6;
					sconst_1;
					baload;
					bastore;
					aload_3;
					sload 5;
					sconst_2;
					sadd;
					s2b;
					aload 6;
					sconst_2;
					baload;
					bastore;
					sload 5;
					sconst_3;
					sadd;
					s2b;
					sstore 5;
					goto L9;
				L11:	aload_0;
					aload_1;
					aload_2;
					aload_3;
					invokespecial 89;		// des/DesfireCard.sendResponse(Ljavacard/framework/APDU;[B[B)V
					goto L16;
				L12:	aload_0;
					sconst_0;
					putfield_b 7;		// byte des/DesfireCard.commandToContinue
					sload 4;
					bspush 19;
					ssub;
					sconst_3;
					smul;
					s2b;
					newarray 11;
					astore_3;
					sconst_0;
					sstore 5;
				L13:	sload 5;
					aload_3;
					arraylength;
					if_scmpge L15;
				L14:	getfield_a_this 3;		// reference des/DesfireCard.masterFile
					sload 5;
					sconst_3;
					sdiv;
					bspush 21;
					sadd;
					s2b;
					invokevirtual 88;		// des/MasterFile.getAID(B)[B
					astore 6;
					aload_3;
					sload 5;
					aload 6;
					sconst_0;
					baload;
					bastore;
					aload_3;
					sload 5;
					sconst_1;
					sadd;
					s2b;
					aload 6;
					sconst_1;
					baload;
					bastore;
					aload_3;
					sload 5;
					sconst_2;
					sadd;
					s2b;
					aload 6;
					sconst_2;
					baload;
					bastore;
					sload 5;
					sconst_3;
					sadd;
					s2b;
					sstore 5;
					goto L13;
				L15:	aload_0;
					aload_1;
					aload_2;
					aload_3;
					invokespecial 89;		// des/DesfireCard.sendResponse(Ljavacard/framework/APDU;[B[B)V
				L16:	return;
		}

		.method private getKeySettings(Ljavacard/framework/APDU;[B)V {
			.stack 4;
			.locals 3;

			.descriptor	Ljavacard/framework/APDU;	1.10;

				L0:	getfield_a_this 4;		// reference des/DesfireCard.selectedDF
					getfield_b_this 11;		// byte des/DesfireCard.authenticated
					invokevirtual 87;		// des/DirectoryFile.hasGetRights(B)Z
					ifne L2;
				L1:	sspush -28259;
					invokestatic 177;		// javacard/framework/ISOException.throwIt(S)V
				L2:	getfield_a_this 4;		// reference des/DesfireCard.selectedDF
					invokevirtual 90;		// des/DirectoryFile.getKeySettings()B
					sstore_3;
					getfield_a_this 4;		// reference des/DesfireCard.selectedDF
					invokevirtual 91;		// des/DirectoryFile.getKeyNumber()B
					sstore 4;
					sconst_2;
					newarray 11;
					astore 5;
					aload 5;
					sconst_0;
					sload_3;
					bastore;
					aload 5;
					sconst_1;
					sload 4;
					bastore;
					aload_0;
					aload_1;
					aload_2;
					aload 5;
					invokespecial 89;		// des/DesfireCard.sendResponse(Ljavacard/framework/APDU;[B[B)V
					return;
		}

		.method private selectApplication(Ljavacard/framework/APDU;[B)V {
			.stack 5;
			.locals 2;

			.descriptor	Ljavacard/framework/APDU;	1.10;

				L0:	aload_0;
					aload_1;
					aload_2;
					invokespecial 210;		// des/DesfireCard.receiveAPDU(Ljavacard/framework/APDU;[B)V
					getfield_a_this 3;		// reference des/DesfireCard.masterFile
					invokevirtual 81;		// des/MasterFile.getIndexDF()Ldes/IndexFile;
					sconst_0;
					invokevirtual 92;		// des/IndexFile.hasReadAccess(B)Z
					ifne L2;
				L1:	sspush -28259;
					invokestatic 177;		// javacard/framework/ISOException.throwIt(S)V
				L2:	sconst_3;
					newarray 11;
					dup;
					sconst_0;
					aload_2;
					sconst_5;
					baload;
					bastore;
					dup;
					sconst_1;
					aload_2;
					bspush 6;
					baload;
					bastore;
					dup;
					sconst_2;
					aload_2;
					bspush 7;
					baload;
					bastore;
					astore_3;
					aload_3;
					sconst_0;
					getstatic_a 93;		// reference des/Util.masterFileAID
					sconst_0;
					aload_3;
					arraylength;
					invokestatic 238;		// javacard/framework/Util.arrayCompare([BS[BSS)B
					ifne L4;
				L3:	aload_0;
					getfield_a_this 3;		// reference des/DesfireCard.masterFile
					putfield_a 4;		// reference des/DesfireCard.selectedDF
					goto L7;
				L4:	getfield_a_this 3;		// reference des/DesfireCard.masterFile
					aload_3;
					invokevirtual 84;		// des/MasterFile.searchAID([B)B
					sstore 4;
					sload 4;
					sconst_m1;
					if_scmpeq L6;
				L5:	aload_0;
					getfield_a_this 3;		// reference des/DesfireCard.masterFile
					getfield_a 16;		// reference des/MasterFile.arrayDF
					getfield_a_this 3;		// reference des/DesfireCard.masterFile
					aload_3;
					invokevirtual 84;		// des/MasterFile.searchAID([B)B
					aaload;
					putfield_a 4;		// reference des/DesfireCard.selectedDF
					goto L7;
				L6:	sspush -28256;
					invokestatic 177;		// javacard/framework/ISOException.throwIt(S)V
				L7:	aload_0;
					sconst_m1;
					putfield_b 11;		// byte des/DesfireCard.authenticated
					aload_0;
					sconst_0;
					putfield_b 13;		// byte des/DesfireCard.securityLevel
					sspush -28416;
					invokestatic 177;		// javacard/framework/ISOException.throwIt(S)V
					return;
		}

		.method private formatPICC(Ljavacard/framework/APDU;[B)V {
			.stack 1;
			.locals 0;

			.descriptor	Ljavacard/framework/APDU;	1.10;

				L0:	getfield_a_this 4;		// reference des/DesfireCard.selectedDF
					invokevirtual 221;		// des/DirectoryFile.isMasterFile()Z
					ifne L2;
				L1:	sspush -28259;
					invokestatic 177;		// javacard/framework/ISOException.throwIt(S)V
				L2:	getfield_a_this 3;		// reference des/DesfireCard.masterFile
					invokevirtual 94;		// des/MasterFile.isFormatEnabled()Z
					ifne L4;
				L3:	sspush -28259;
					invokestatic 177;		// javacard/framework/ISOException.throwIt(S)V
				L4:	getfield_b_this 11;		// byte des/DesfireCard.authenticated
					ifeq L6;
				L5:	sspush -28259;
					invokestatic 177;		// javacard/framework/ISOException.throwIt(S)V
				L6:	getfield_a_this 3;		// reference des/DesfireCard.masterFile
					invokevirtual 95;		// des/MasterFile.format()V
					sspush -28416;
					invokestatic 177;		// javacard/framework/ISOException.throwIt(S)V
					return;
		}

		.method private setConfiguration(Ljavacard/framework/APDU;[B)V {
			.stack 5;
			.locals 4;

			.descriptor	Ljavacard/framework/APDU;	1.10;

				L0:	aload_0;
					aload_1;
					aload_2;
					invokespecial 210;		// des/DesfireCard.receiveAPDU(Ljavacard/framework/APDU;[B)V
					aload_2;
					sconst_4;
					baload;
					sconst_1;
					ssub;
					s2b;
					newarray 11;
					astore_3;
					sconst_0;
					sstore 4;
				L1:	sload 4;
					aload_3;
					arraylength;
					if_scmpge L3;
				L2:	aload_3;
					sload 4;
					aload_2;
					sload 4;
					sconst_5;
					sadd;
					sconst_1;
					sadd;
					s2b;
					baload;
					bastore;
					sload 4;
					sconst_1;
					sadd;
					s2b;
					sstore 4;
					goto L1;
				L3:	aload_3;
					arraylength;
					newarray 11;
					astore 4;
					aload_3;
					astore 4;
					aload_2;
					sconst_5;
					baload;
					stableswitch L10 0 2 L4 L5 L9;
				L4:	getfield_a_this 3;		// reference des/DesfireCard.masterFile
					aload 4;
					sconst_0;
					baload;
					invokevirtual 96;		// des/MasterFile.setConfiguration(B)V
					goto L11;
				L5:	aload 4;
					arraylength;
					sconst_1;
					ssub;
					s2b;
					newarray 11;
					astore 5;
					sconst_0;
					sstore 6;
				L6:	sload 6;
					aload 5;
					arraylength;
					if_scmpge L8;
				L7:	aload 5;
					sload 6;
					aload 4;
					sload 6;
					baload;
					bastore;
					sload 6;
					sconst_1;
					sadd;
					s2b;
					sstore 6;
					goto L6;
				L8:	getfield_a_this 3;		// reference des/DesfireCard.masterFile
					getfield_a_this 3;		// reference des/DesfireCard.masterFile
					invokevirtual 97;		// des/DirectoryFile.getMasterKeyType()B
					aload 5;
					invokevirtual 79;		// des/DirectoryFile.changeKey(B[B)V
					goto L11;
				L9:	goto L11;
				L10:	sspush -28258;
					invokestatic 177;		// javacard/framework/ISOException.throwIt(S)V
				L11:	return;
		}

		.method private getFileIDs(Ljavacard/framework/APDU;[B)V {
			.stack 4;
			.locals 4;

			.descriptor	Ljavacard/framework/APDU;	1.10;

				L0:	getfield_a_this 4;		// reference des/DesfireCard.selectedDF
					getfield_b_this 11;		// byte des/DesfireCard.authenticated
					invokevirtual 87;		// des/DirectoryFile.hasGetRights(B)Z
					ifeq L2;
				L1:	sspush -28259;
					invokestatic 177;		// javacard/framework/ISOException.throwIt(S)V
				L2:	getfield_a_this 4;		// reference des/DesfireCard.selectedDF
					invokevirtual 98;		// des/DirectoryFile.getNumberFiles()B
					sconst_1;
					sadd;
					newarray 11;
					astore_3;
					sconst_0;
					sstore 4;
					sconst_0;
					sstore 5;
				L3:	sload 5;
					aload_3;
					arraylength;
					sconst_1;
					ssub;
					s2b;
					if_scmpge L10;
				L4:	sload 4;
					sstore 6;
				L5:	sload 6;
					bspush 32;
					if_scmpge L9;
				L6:	getfield_a_this 4;		// reference des/DesfireCard.selectedDF
					getfield_a 18;		// reference des/DirectoryFile.activatedFiles
					sload 6;
					baload;
					sconst_1;
					if_scmpne L8;
				L7:	aload_0;
					getfield_a_this 4;		// reference des/DesfireCard.selectedDF
					sload 6;
					invokevirtual 100;		// des/DirectoryFile.getFile(B)Ldes/File;
					putfield_a 19;		// reference des/DesfireCard.selectedFile
					getfield_a_this 19;		// reference des/DesfireCard.selectedFile
					invokevirtual 75;		// des/File.getFileID()B
					pop;
					aload_3;
					sload 5;
					getfield_a_this 19;		// reference des/DesfireCard.selectedFile
					invokevirtual 75;		// des/File.getFileID()B
					bastore;
					sload 6;
					sconst_1;
					sadd;
					s2b;
					sstore 4;
					goto L9;
				L8:	sload 6;
					sconst_1;
					sadd;
					s2b;
					sstore 6;
					goto L5;
				L9:	sload 5;
					sconst_1;
					sadd;
					s2b;
					sstore 5;
					goto L3;
				L10:	aload_3;
					aload_3;
					arraylength;
					s2b;
					sconst_1;
					ssub;
					sconst_0;
					bastore;
					aload_0;
					aload_1;
					aload_2;
					aload_3;
					invokespecial 89;		// des/DesfireCard.sendResponse(Ljavacard/framework/APDU;[B[B)V
					return;
		}

		.method private createStdDataFile(Ljavacard/framework/APDU;[B)V {
			.stack 7;
			.locals 4;

			.descriptor	Ljavacard/framework/APDU;	1.10;

				L0:	aload_0;
					aload_1;
					aload_2;
					invokespecial 210;		// des/DesfireCard.receiveAPDU(Ljavacard/framework/APDU;[B)V
					getfield_a_this 4;		// reference des/DesfireCard.selectedDF
					invokevirtual 221;		// des/DirectoryFile.isMasterFile()Z
					ifeq L2;
				L1:	sspush -28259;
					invokestatic 177;		// javacard/framework/ISOException.throwIt(S)V
				L2:	aload_2;
					sconst_5;
					baload;
					sstore_3;
					sconst_2;
					newarray 11;
					dup;
					sconst_0;
					aload_2;
					bspush 8;
					baload;
					bastore;
					dup;
					sconst_1;
					aload_2;
					bspush 7;
					baload;
					bastore;
					astore 4;
					sconst_2;
					newarray 11;
					dup;
					sconst_0;
					aload_2;
					bspush 10;
					baload;
					bastore;
					dup;
					sconst_1;
					aload_2;
					bspush 9;
					baload;
					bastore;
					astore 5;
					aload_2;
					sconst_4;
					baload;
					bspush 9;
					if_scmpne L4;
				L3:	aload 4;
					sconst_0;
					aload_2;
					bspush 10;
					baload;
					bastore;
					aload 4;
					sconst_1;
					aload_2;
					bspush 9;
					baload;
					bastore;
					aload 5;
					sconst_0;
					aload_2;
					bspush 12;
					baload;
					bastore;
					aload 5;
					sconst_1;
					aload_2;
					bspush 11;
					baload;
					bastore;
				L4:	aload 5;
					invokestatic 102;		// des/Util.byteArrayToShort([B)S
					sstore 6;
					sload 6;
					sconst_0;
					invokestatic 103;		// javacard/framework/JCSystem.getAvailableMemory(B)S
					if_scmple L6;
				L5:	sspush -28402;
					invokestatic 177;		// javacard/framework/ISOException.throwIt(S)V
				L6:	getfield_a_this 4;		// reference des/DesfireCard.selectedDF
					getfield_b_this 11;		// byte des/DesfireCard.authenticated
					invokevirtual 80;		// des/DirectoryFile.hasManageRights(B)Z
					ifne L8;
				L7:	sspush -28259;
					invokestatic 177;		// javacard/framework/ISOException.throwIt(S)V
				L8:	aload_0;
					new 104;		// des/StandartFile
					dup;
					sload_3;
					getfield_a_this 3;		// reference des/DesfireCard.masterFile
					getfield_a 16;		// reference des/MasterFile.arrayDF
					getfield_a_this 4;		// reference des/DesfireCard.selectedDF
					invokevirtual 75;		// des/File.getFileID()B
					aaload;
					aload 4;
					sload 6;
					invokespecial 105;		// des/StandartFile.<init>(BLdes/DirectoryFile;[BS)V
					putfield_a 19;		// reference des/DesfireCard.selectedFile
					aload_0;
					getfield_a_this 3;		// reference des/DesfireCard.masterFile
					getfield_a 16;		// reference des/MasterFile.arrayDF
					getfield_a_this 4;		// reference des/DesfireCard.selectedDF
					invokevirtual 75;		// des/File.getFileID()B
					aaload;
					putfield_a 4;		// reference des/DesfireCard.selectedDF
					sspush -28416;
					invokestatic 177;		// javacard/framework/ISOException.throwIt(S)V
					return;
		}

		.method private createValueFile(Ljavacard/framework/APDU;[B)V {
			.stack 10;
			.locals 6;

			.descriptor	Ljavacard/framework/APDU;	1.10;

				L0:	aload_0;
					aload_1;
					aload_2;
					invokespecial 210;		// des/DesfireCard.receiveAPDU(Ljavacard/framework/APDU;[B)V
					getfield_a_this 4;		// reference des/DesfireCard.selectedDF
					invokevirtual 221;		// des/DirectoryFile.isMasterFile()Z
					ifeq L2;
				L1:	sspush -28259;
					invokestatic 177;		// javacard/framework/ISOException.throwIt(S)V
				L2:	aload_2;
					sconst_5;
					baload;
					sstore_3;
					sconst_2;
					newarray 11;
					dup;
					sconst_0;
					aload_2;
					bspush 8;
					baload;
					bastore;
					dup;
					sconst_1;
					aload_2;
					bspush 7;
					baload;
					bastore;
					astore 4;
					new 106;		// des/Value
					dup;
					sconst_4;
					newarray 11;
					dup;
					sconst_0;
					aload_2;
					bspush 12;
					baload;
					bastore;
					dup;
					sconst_1;
					aload_2;
					bspush 11;
					baload;
					bastore;
					dup;
					sconst_2;
					aload_2;
					bspush 10;
					baload;
					bastore;
					dup;
					sconst_3;
					aload_2;
					bspush 9;
					baload;
					bastore;
					invokespecial 107;		// des/Value.<init>([B)V
					astore 5;
					new 106;		// des/Value
					dup;
					sconst_4;
					newarray 11;
					dup;
					sconst_0;
					aload_2;
					bspush 16;
					baload;
					bastore;
					dup;
					sconst_1;
					aload_2;
					bspush 15;
					baload;
					bastore;
					dup;
					sconst_2;
					aload_2;
					bspush 14;
					baload;
					bastore;
					dup;
					sconst_3;
					aload_2;
					bspush 13;
					baload;
					bastore;
					invokespecial 107;		// des/Value.<init>([B)V
					astore 6;
					new 106;		// des/Value
					dup;
					sconst_4;
					newarray 11;
					dup;
					sconst_0;
					aload_2;
					bspush 20;
					baload;
					bastore;
					dup;
					sconst_1;
					aload_2;
					bspush 19;
					baload;
					bastore;
					dup;
					sconst_2;
					aload_2;
					bspush 18;
					baload;
					bastore;
					dup;
					sconst_3;
					aload_2;
					bspush 17;
					baload;
					bastore;
					invokespecial 107;		// des/Value.<init>([B)V
					astore 7;
					aload 6;
					aload 5;
					invokevirtual 108;		// des/Value.compareTo(Ldes/Value;)B
					sconst_1;
					if_scmpeq L4;
				L3:	sspush -28226;
					invokestatic 177;		// javacard/framework/ISOException.throwIt(S)V
				L4:	aload 6;
					aload 7;
					invokevirtual 108;		// des/Value.compareTo(Ldes/Value;)B
					sconst_1;
					if_scmpeq L6;
				L5:	sspush -28226;
					invokestatic 177;		// javacard/framework/ISOException.throwIt(S)V
				L6:	aload 7;
					aload 5;
					invokevirtual 108;		// des/Value.compareTo(Ldes/Value;)B
					sconst_1;
					if_scmpeq L8;
				L7:	sspush -28226;
					invokestatic 177;		// javacard/framework/ISOException.throwIt(S)V
				L8:	aload_2;
					bspush 21;
					baload;
					sstore 8;
					bspush 30;
					sconst_0;
					invokestatic 103;		// javacard/framework/JCSystem.getAvailableMemory(B)S
					if_scmple L10;
				L9:	sspush -28402;
					invokestatic 177;		// javacard/framework/ISOException.throwIt(S)V
				L10:	getfield_a_this 4;		// reference des/DesfireCard.selectedDF
					getfield_b_this 11;		// byte des/DesfireCard.authenticated
					invokevirtual 80;		// des/DirectoryFile.hasManageRights(B)Z
					ifne L12;
				L11:	sspush -28259;
					invokestatic 177;		// javacard/framework/ISOException.throwIt(S)V
				L12:	aload_0;
					new 109;		// des/ValueRecord
					dup;
					sload_3;
					getfield_a_this 3;		// reference des/DesfireCard.masterFile
					getfield_a 16;		// reference des/MasterFile.arrayDF
					getfield_a_this 4;		// reference des/DesfireCard.selectedDF
					invokevirtual 75;		// des/File.getFileID()B
					aaload;
					aload 4;
					aload 5;
					aload 6;
					aload 7;
					sload 8;
					invokespecial 110;		// des/ValueRecord.<init>(BLdes/DirectoryFile;[BLdes/Value;Ldes/Value;Ldes/Value;B)V
					putfield_a 19;		// reference des/DesfireCard.selectedFile
					aload_0;
					getfield_a_this 3;		// reference des/DesfireCard.masterFile
					getfield_a 16;		// reference des/MasterFile.arrayDF
					getfield_a_this 4;		// reference des/DesfireCard.selectedDF
					invokevirtual 75;		// des/File.getFileID()B
					aaload;
					putfield_a 4;		// reference des/DesfireCard.selectedDF
					sspush -28416;
					invokestatic 177;		// javacard/framework/ISOException.throwIt(S)V
					return;
		}

		.method private createLinearRecordFile(Ljavacard/framework/APDU;[B)V {
			.stack 8;
			.locals 4;

			.descriptor	Ljavacard/framework/APDU;	1.10;

				L0:	aload_0;
					aload_1;
					aload_2;
					invokespecial 210;		// des/DesfireCard.receiveAPDU(Ljavacard/framework/APDU;[B)V
					getfield_a_this 4;		// reference des/DesfireCard.selectedDF
					invokevirtual 221;		// des/DirectoryFile.isMasterFile()Z
					ifeq L2;
				L1:	sspush -28259;
					invokestatic 177;		// javacard/framework/ISOException.throwIt(S)V
				L2:	aload_2;
					sconst_5;
					baload;
					sstore_3;
					sconst_2;
					newarray 11;
					dup;
					sconst_0;
					aload_2;
					bspush 8;
					baload;
					bastore;
					dup;
					sconst_1;
					aload_2;
					bspush 7;
					baload;
					bastore;
					astore 4;
					sconst_2;
					newarray 11;
					dup;
					sconst_0;
					aload_2;
					bspush 10;
					baload;
					bastore;
					dup;
					sconst_1;
					aload_2;
					bspush 9;
					baload;
					bastore;
					invokestatic 102;		// des/Util.byteArrayToShort([B)S
					sstore 5;
					sconst_2;
					newarray 11;
					dup;
					sconst_0;
					aload_2;
					bspush 13;
					baload;
					bastore;
					dup;
					sconst_1;
					aload_2;
					bspush 12;
					baload;
					bastore;
					invokestatic 102;		// des/Util.byteArrayToShort([B)S
					sstore 6;
					aload_2;
					sconst_4;
					baload;
					bspush 12;
					if_scmpne L4;
				L3:	aload 4;
					sconst_0;
					aload_2;
					bspush 10;
					baload;
					bastore;
					aload 4;
					sconst_1;
					aload_2;
					bspush 9;
					baload;
					bastore;
					sconst_2;
					newarray 11;
					dup;
					sconst_0;
					aload_2;
					bspush 12;
					baload;
					bastore;
					dup;
					sconst_1;
					aload_2;
					bspush 11;
					baload;
					bastore;
					invokestatic 102;		// des/Util.byteArrayToShort([B)S
					sstore 5;
					sconst_2;
					newarray 11;
					dup;
					sconst_0;
					aload_2;
					bspush 15;
					baload;
					bastore;
					dup;
					sconst_1;
					aload_2;
					bspush 14;
					baload;
					bastore;
					invokestatic 102;		// des/Util.byteArrayToShort([B)S
					sstore 6;
				L4:	sload 5;
					sload 6;
					smul;
					sconst_0;
					invokestatic 103;		// javacard/framework/JCSystem.getAvailableMemory(B)S
					if_scmple L6;
				L5:	sspush -28402;
					invokestatic 177;		// javacard/framework/ISOException.throwIt(S)V
				L6:	getfield_a_this 4;		// reference des/DesfireCard.selectedDF
					getfield_b_this 11;		// byte des/DesfireCard.authenticated
					invokevirtual 80;		// des/DirectoryFile.hasManageRights(B)Z
					ifne L8;
				L7:	sspush -28259;
					invokestatic 177;		// javacard/framework/ISOException.throwIt(S)V
				L8:	aload_0;
					new 111;		// des/LinearRecord
					dup;
					sload_3;
					getfield_a_this 3;		// reference des/DesfireCard.masterFile
					getfield_a 16;		// reference des/MasterFile.arrayDF
					getfield_a_this 4;		// reference des/DesfireCard.selectedDF
					invokevirtual 75;		// des/File.getFileID()B
					aaload;
					aload 4;
					sload 5;
					sload 6;
					invokespecial 112;		// des/LinearRecord.<init>(BLdes/DirectoryFile;[BSS)V
					putfield_a 19;		// reference des/DesfireCard.selectedFile
					aload_0;
					getfield_a_this 3;		// reference des/DesfireCard.masterFile
					getfield_a 16;		// reference des/MasterFile.arrayDF
					getfield_a_this 4;		// reference des/DesfireCard.selectedDF
					invokevirtual 75;		// des/File.getFileID()B
					aaload;
					putfield_a 4;		// reference des/DesfireCard.selectedDF
					sspush -28416;
					invokestatic 177;		// javacard/framework/ISOException.throwIt(S)V
					return;
		}

		.method private createCyclicRecordFile(Ljavacard/framework/APDU;[B)V {
			.stack 8;
			.locals 4;

			.descriptor	Ljavacard/framework/APDU;	1.10;

				L0:	aload_0;
					aload_1;
					aload_2;
					invokespecial 210;		// des/DesfireCard.receiveAPDU(Ljavacard/framework/APDU;[B)V
					getfield_a_this 4;		// reference des/DesfireCard.selectedDF
					invokevirtual 221;		// des/DirectoryFile.isMasterFile()Z
					ifeq L2;
				L1:	sspush -28259;
					invokestatic 177;		// javacard/framework/ISOException.throwIt(S)V
				L2:	aload_2;
					sconst_5;
					baload;
					sstore_3;
					sconst_2;
					newarray 11;
					dup;
					sconst_0;
					aload_2;
					bspush 8;
					baload;
					bastore;
					dup;
					sconst_1;
					aload_2;
					bspush 7;
					baload;
					bastore;
					astore 4;
					sconst_2;
					newarray 11;
					dup;
					sconst_0;
					aload_2;
					bspush 10;
					baload;
					bastore;
					dup;
					sconst_1;
					aload_2;
					bspush 9;
					baload;
					bastore;
					invokestatic 102;		// des/Util.byteArrayToShort([B)S
					sstore 5;
					sconst_2;
					newarray 11;
					dup;
					sconst_0;
					aload_2;
					bspush 13;
					baload;
					bastore;
					dup;
					sconst_1;
					aload_2;
					bspush 12;
					baload;
					bastore;
					invokestatic 102;		// des/Util.byteArrayToShort([B)S
					sstore 6;
					aload_2;
					sconst_4;
					baload;
					bspush 12;
					if_scmpne L4;
				L3:	aload 4;
					sconst_0;
					aload_2;
					bspush 10;
					baload;
					bastore;
					aload 4;
					sconst_1;
					aload_2;
					bspush 9;
					baload;
					bastore;
					sconst_2;
					newarray 11;
					dup;
					sconst_0;
					aload_2;
					bspush 12;
					baload;
					bastore;
					dup;
					sconst_1;
					aload_2;
					bspush 11;
					baload;
					bastore;
					invokestatic 102;		// des/Util.byteArrayToShort([B)S
					sstore 5;
					sconst_2;
					newarray 11;
					dup;
					sconst_0;
					aload_2;
					bspush 15;
					baload;
					bastore;
					dup;
					sconst_1;
					aload_2;
					bspush 14;
					baload;
					bastore;
					invokestatic 102;		// des/Util.byteArrayToShort([B)S
					sstore 6;
				L4:	sload 5;
					sload 6;
					smul;
					sconst_0;
					invokestatic 103;		// javacard/framework/JCSystem.getAvailableMemory(B)S
					if_scmple L6;
				L5:	sspush -28402;
					invokestatic 177;		// javacard/framework/ISOException.throwIt(S)V
				L6:	getfield_a_this 4;		// reference des/DesfireCard.selectedDF
					getfield_b_this 11;		// byte des/DesfireCard.authenticated
					invokevirtual 80;		// des/DirectoryFile.hasManageRights(B)Z
					ifne L8;
				L7:	sspush -28259;
					invokestatic 177;		// javacard/framework/ISOException.throwIt(S)V
				L8:	aload_0;
					new 113;		// des/CyclicRecord
					dup;
					sload_3;
					getfield_a_this 3;		// reference des/DesfireCard.masterFile
					getfield_a 16;		// reference des/MasterFile.arrayDF
					getfield_a_this 4;		// reference des/DesfireCard.selectedDF
					invokevirtual 75;		// des/File.getFileID()B
					aaload;
					aload 4;
					sload 5;
					sload 6;
					invokespecial 114;		// des/CyclicRecord.<init>(BLdes/DirectoryFile;[BSS)V
					putfield_a 19;		// reference des/DesfireCard.selectedFile
					aload_0;
					getfield_a_this 3;		// reference des/DesfireCard.masterFile
					getfield_a 16;		// reference des/MasterFile.arrayDF
					getfield_a_this 4;		// reference des/DesfireCard.selectedDF
					invokevirtual 75;		// des/File.getFileID()B
					aaload;
					putfield_a 4;		// reference des/DesfireCard.selectedDF
					sspush -28416;
					invokestatic 177;		// javacard/framework/ISOException.throwIt(S)V
					return;
		}

		.method private deleteFile(Ljavacard/framework/APDU;[B)V {
			.stack 3;
			.locals 1;

			.descriptor	Ljavacard/framework/APDU;	1.10;

				L0:	aload_0;
					aload_1;
					aload_2;
					invokespecial 210;		// des/DesfireCard.receiveAPDU(Ljavacard/framework/APDU;[B)V
					aload_2;
					sconst_5;
					baload;
					sstore_3;
					getfield_a_this 4;		// reference des/DesfireCard.selectedDF
					getfield_b_this 11;		// byte des/DesfireCard.authenticated
					invokevirtual 80;		// des/DirectoryFile.hasManageRights(B)Z
					ifne L2;
				L1:	sspush -28259;
					invokestatic 177;		// javacard/framework/ISOException.throwIt(S)V
				L2:	getfield_a_this 4;		// reference des/DesfireCard.selectedDF
					sload_3;
					invokevirtual 115;		// des/DirectoryFile.deleteFile(B)V
					getfield_a_this 3;		// reference des/DesfireCard.masterFile
					getfield_a 16;		// reference des/MasterFile.arrayDF
					getfield_a_this 4;		// reference des/DesfireCard.selectedDF
					invokevirtual 75;		// des/File.getFileID()B
					getfield_a_this 4;		// reference des/DesfireCard.selectedDF
					aastore;
					sspush -28416;
					invokestatic 177;		// javacard/framework/ISOException.throwIt(S)V
					return;
		}

		.method private readData(Ljavacard/framework/APDU;[B)V {
			.stack 6;
			.locals 1;

			.descriptor	Ljavacard/framework/APDU;	1.10;

				L0:	aload_0;
					aload_1;
					aload_2;
					invokespecial 210;		// des/DesfireCard.receiveAPDU(Ljavacard/framework/APDU;[B)V
					getfield_b_this 7;		// byte des/DesfireCard.commandToContinue
					ifne L5;
				L1:	aload_0;
					getfield_a_this 4;		// reference des/DesfireCard.selectedDF
					aload_2;
					sconst_5;
					baload;
					invokevirtual 100;		// des/DirectoryFile.getFile(B)Ldes/File;
					checkcast 0 104;		// T_CLASSORINTERFACE des/StandartFile
					putfield_a 19;		// reference des/DesfireCard.selectedFile
					getfield_a_this 19;		// reference des/DesfireCard.selectedFile
					checkcast 0 104;		// T_CLASSORINTERFACE des/StandartFile
					getfield_b_this 11;		// byte des/DesfireCard.authenticated
					invokevirtual 116;		// des/StandartFile.hasReadAccess(B)Z
					ifne L3;
				L2:	sspush -28259;
					invokestatic 177;		// javacard/framework/ISOException.throwIt(S)V
				L3:	aload_0;
					sconst_2;
					newarray 11;
					dup;
					sconst_0;
					aload_2;
					bspush 7;
					baload;
					bastore;
					dup;
					sconst_1;
					aload_2;
					bspush 6;
					baload;
					bastore;
					invokestatic 102;		// des/Util.byteArrayToShort([B)S
					putfield_s 8;		// short des/DesfireCard.offset
					aload_0;
					sconst_2;
					newarray 11;
					dup;
					sconst_0;
					aload_2;
					bspush 10;
					baload;
					bastore;
					dup;
					sconst_1;
					aload_2;
					bspush 9;
					baload;
					bastore;
					invokestatic 102;		// des/Util.byteArrayToShort([B)S
					putfield_s 9;		// short des/DesfireCard.bytesLeft
					getfield_s_this 9;		// short des/DesfireCard.bytesLeft
					ifne L5;
				L4:	aload_0;
					getfield_a_this 19;		// reference des/DesfireCard.selectedFile
					invokevirtual 117;		// des/File.getSize()B
					putfield_s 9;		// short des/DesfireCard.bytesLeft
				L5:	getfield_s_this 9;		// short des/DesfireCard.bytesLeft
					bspush 59;
					if_scmplt L7;
				L6:	bspush 59;
					newarray 11;
					astore_3;
					getfield_a_this 19;		// reference des/DesfireCard.selectedFile
					checkcast 0 104;		// T_CLASSORINTERFACE des/StandartFile
					getfield_s_this 8;		// short des/DesfireCard.offset
					bspush 59;
					sconst_0;
					invokevirtual 118;		// des/StandartFile.readArray(SSB)[B
					astore_3;
					aload_0;
					getfield_s_this 9;		// short des/DesfireCard.bytesLeft
					bspush 59;
					ssub;
					putfield_s 9;		// short des/DesfireCard.bytesLeft
					aload_0;
					getfield_s_this 8;		// short des/DesfireCard.offset
					bspush 59;
					sadd;
					putfield_s 8;		// short des/DesfireCard.offset
					aload_0;
					bspush -115;
					putfield_b 7;		// byte des/DesfireCard.commandToContinue
					aload_0;
					aload_1;
					aload_2;
					aload_3;
					bspush -81;
					invokespecial 235;		// des/DesfireCard.sendResponse(Ljavacard/framework/APDU;[B[BB)V
					goto L8;
				L7:	getfield_s_this 9;		// short des/DesfireCard.bytesLeft
					newarray 11;
					astore_3;
					getfield_a_this 19;		// reference des/DesfireCard.selectedFile
					checkcast 0 104;		// T_CLASSORINTERFACE des/StandartFile
					getfield_s_this 8;		// short des/DesfireCard.offset
					getfield_s_this 9;		// short des/DesfireCard.bytesLeft
					sconst_0;
					invokevirtual 118;		// des/StandartFile.readArray(SSB)[B
					astore_3;
					aload_0;
					sconst_0;
					putfield_s 9;		// short des/DesfireCard.bytesLeft
					aload_0;
					sconst_0;
					putfield_s 8;		// short des/DesfireCard.offset
					aload_0;
					sconst_0;
					putfield_b 7;		// byte des/DesfireCard.commandToContinue
					aload_0;
					aload_1;
					aload_2;
					aload_3;
					invokespecial 89;		// des/DesfireCard.sendResponse(Ljavacard/framework/APDU;[B[B)V
				L8:	return;
		}

		.method private writeData(Ljavacard/framework/APDU;[B)V {
			.stack 6;
			.locals 3;

			.descriptor	Ljavacard/framework/APDU;	1.10;

				L0:	aload_0;
					aload_1;
					aload_2;
					invokespecial 210;		// des/DesfireCard.receiveAPDU(Ljavacard/framework/APDU;[B)V
					getfield_b_this 7;		// byte des/DesfireCard.commandToContinue
					ifne_w L7;
				L1:	aload_0;
					getfield_a_this 4;		// reference des/DesfireCard.selectedDF
					aload_2;
					sconst_5;
					baload;
					invokevirtual 100;		// des/DirectoryFile.getFile(B)Ldes/File;
					checkcast 0 104;		// T_CLASSORINTERFACE des/StandartFile
					putfield_a 19;		// reference des/DesfireCard.selectedFile
					getfield_a_this 19;		// reference des/DesfireCard.selectedFile
					checkcast 0 104;		// T_CLASSORINTERFACE des/StandartFile
					getfield_b_this 11;		// byte des/DesfireCard.authenticated
					invokevirtual 119;		// des/StandartFile.hasWriteAccess(B)Z
					ifne L3;
				L2:	sspush -28259;
					invokestatic 177;		// javacard/framework/ISOException.throwIt(S)V
				L3:	aload_0;
					sconst_2;
					newarray 11;
					dup;
					sconst_0;
					aload_2;
					bspush 7;
					baload;
					bastore;
					dup;
					sconst_1;
					aload_2;
					bspush 6;
					baload;
					bastore;
					invokestatic 102;		// des/Util.byteArrayToShort([B)S
					putfield_s 8;		// short des/DesfireCard.offset
					aload_0;
					sconst_2;
					newarray 11;
					dup;
					sconst_0;
					aload_2;
					bspush 10;
					baload;
					bastore;
					dup;
					sconst_1;
					aload_2;
					bspush 9;
					baload;
					bastore;
					invokestatic 102;		// des/Util.byteArrayToShort([B)S
					putfield_s 9;		// short des/DesfireCard.bytesLeft
					bspush 52;
					newarray 11;
					astore 4;
					aload_2;
					sconst_4;
					baload;
					bspush 7;
					ssub;
					s2b;
					sstore_3;
					aload_0;
					getfield_s_this 9;		// short des/DesfireCard.bytesLeft
					sload_3;
					ssub;
					putfield_s 9;		// short des/DesfireCard.bytesLeft
					sconst_0;
					sstore 5;
				L4:	sload 5;
					sload_3;
					if_scmpge L6;
				L5:	aload 4;
					sload 5;
					aload_2;
					sconst_5;
					sload 5;
					sadd;
					bspush 7;
					sadd;
					s2b;
					baload;
					bastore;
					sload 5;
					sconst_1;
					sadd;
					s2b;
					sstore 5;
					goto L4;
				L6:	goto L10;
				L7:	bspush 59;
					newarray 11;
					astore 4;
					aload_2;
					sconst_4;
					baload;
					sstore_3;
					aload_0;
					getfield_s_this 9;		// short des/DesfireCard.bytesLeft
					sload_3;
					ssub;
					putfield_s 9;		// short des/DesfireCard.bytesLeft
					sconst_0;
					sstore 5;
				L8:	sload 5;
					sload_3;
					if_scmpge L10;
				L9:	aload 4;
					sload 5;
					aload_2;
					sconst_5;
					sload 5;
					sadd;
					s2b;
					baload;
					bastore;
					sload 5;
					sconst_1;
					sadd;
					s2b;
					sstore 5;
					goto L8;
				L10:	getfield_a_this 19;		// reference des/DesfireCard.selectedFile
					checkcast 0 104;		// T_CLASSORINTERFACE des/StandartFile
					aload 4;
					getfield_s_this 8;		// short des/DesfireCard.offset
					sload_3;
					invokevirtual 120;		// des/StandartFile.writeArray([BSS)V
					getfield_s_this 9;		// short des/DesfireCard.bytesLeft
					ifle L12;
				L11:	aload_0;
					bspush 61;
					putfield_b 7;		// byte des/DesfireCard.commandToContinue
					aload_0;
					getfield_s_this 8;		// short des/DesfireCard.offset
					sload_3;
					sadd;
					putfield_s 8;		// short des/DesfireCard.offset
					bspush -81;
					invokestatic 177;		// javacard/framework/ISOException.throwIt(S)V
					goto L13;
				L12:	aload_0;
					sconst_0;
					putfield_b 7;		// byte des/DesfireCard.commandToContinue
					aload_0;
					sconst_0;
					putfield_s 8;		// short des/DesfireCard.offset
					aload_0;
					sconst_0;
					putfield_s 9;		// short des/DesfireCard.bytesLeft
					sspush -28416;
					invokestatic 177;		// javacard/framework/ISOException.throwIt(S)V
				L13:	return;
		}

		.method private getValue(Ljavacard/framework/APDU;[B)V {
			.stack 4;
			.locals 2;

			.descriptor	Ljavacard/framework/APDU;	1.10;

				L0:	aload_0;
					aload_1;
					aload_2;
					invokespecial 210;		// des/DesfireCard.receiveAPDU(Ljavacard/framework/APDU;[B)V
					aload_2;
					sconst_5;
					baload;
					sstore_3;
					aload_0;
					getfield_a_this 4;		// reference des/DesfireCard.selectedDF
					sload_3;
					invokevirtual 100;		// des/DirectoryFile.getFile(B)Ldes/File;
					checkcast 0 109;		// T_CLASSORINTERFACE des/ValueRecord
					putfield_a 19;		// reference des/DesfireCard.selectedFile
					getfield_a_this 19;		// reference des/DesfireCard.selectedFile
					checkcast 0 109;		// T_CLASSORINTERFACE des/ValueRecord
					getfield_b_this 11;		// byte des/DesfireCard.authenticated
					invokevirtual 121;		// des/ValueRecord.hasReadAccess(B)Z
					sconst_1;
					if_scmpeq L2;
				L1:	sspush -28259;
					invokestatic 177;		// javacard/framework/ISOException.throwIt(S)V
				L2:	getfield_a_this 19;		// reference des/DesfireCard.selectedFile
					checkcast 0 109;		// T_CLASSORINTERFACE des/ValueRecord
					invokevirtual 122;		// des/ValueRecord.getValue()Ldes/Value;
					invokevirtual 123;		// des/Value.getValue()[B
					invokestatic 124;		// des/Util.switchBytes([B)[B
					astore 4;
					aload_0;
					aload_1;
					aload_2;
					aload 4;
					invokespecial 89;		// des/DesfireCard.sendResponse(Ljavacard/framework/APDU;[B[B)V
					return;
		}

		.method private credit(Ljavacard/framework/APDU;[B)V {
			.stack 8;
			.locals 1;

			.descriptor	Ljavacard/framework/APDU;	1.10;

				L0:	aload_0;
					aload_1;
					aload_2;
					invokespecial 210;		// des/DesfireCard.receiveAPDU(Ljavacard/framework/APDU;[B)V
					aload_2;
					sconst_5;
					baload;
					sstore_3;
					aload_0;
					getfield_a_this 4;		// reference des/DesfireCard.selectedDF
					sload_3;
					invokevirtual 100;		// des/DirectoryFile.getFile(B)Ldes/File;
					checkcast 0 109;		// T_CLASSORINTERFACE des/ValueRecord
					putfield_a 19;		// reference des/DesfireCard.selectedFile
					getfield_a_this 19;		// reference des/DesfireCard.selectedFile
					checkcast 0 109;		// T_CLASSORINTERFACE des/ValueRecord
					getfield_b_this 11;		// byte des/DesfireCard.authenticated
					invokevirtual 125;		// des/ValueRecord.hasWriteAccess(B)Z
					ifne L2;
				L1:	sspush -28259;
					invokestatic 177;		// javacard/framework/ISOException.throwIt(S)V
				L2:	getfield_a_this 19;		// reference des/DesfireCard.selectedFile
					checkcast 0 109;		// T_CLASSORINTERFACE des/ValueRecord
					new 106;		// des/Value
					dup;
					sconst_4;
					newarray 11;
					dup;
					sconst_0;
					aload_2;
					bspush 9;
					baload;
					bastore;
					dup;
					sconst_1;
					aload_2;
					bspush 8;
					baload;
					bastore;
					dup;
					sconst_2;
					aload_2;
					bspush 7;
					baload;
					bastore;
					dup;
					sconst_3;
					aload_2;
					bspush 6;
					baload;
					bastore;
					invokespecial 107;		// des/Value.<init>([B)V
					invokevirtual 126;		// des/ValueRecord.addCredit(Ldes/Value;)V
					sspush -28416;
					invokestatic 177;		// javacard/framework/ISOException.throwIt(S)V
					return;
		}

		.method private debit(Ljavacard/framework/APDU;[B)V {
			.stack 8;
			.locals 1;

			.descriptor	Ljavacard/framework/APDU;	1.10;

				L0:	aload_0;
					aload_1;
					aload_2;
					invokespecial 210;		// des/DesfireCard.receiveAPDU(Ljavacard/framework/APDU;[B)V
					aload_2;
					sconst_5;
					baload;
					sstore_3;
					aload_0;
					getfield_a_this 4;		// reference des/DesfireCard.selectedDF
					sload_3;
					invokevirtual 100;		// des/DirectoryFile.getFile(B)Ldes/File;
					checkcast 0 109;		// T_CLASSORINTERFACE des/ValueRecord
					putfield_a 19;		// reference des/DesfireCard.selectedFile
					getfield_a_this 19;		// reference des/DesfireCard.selectedFile
					checkcast 0 109;		// T_CLASSORINTERFACE des/ValueRecord
					getfield_b_this 11;		// byte des/DesfireCard.authenticated
					invokevirtual 125;		// des/ValueRecord.hasWriteAccess(B)Z
					ifne L2;
				L1:	sspush -28259;
					invokestatic 177;		// javacard/framework/ISOException.throwIt(S)V
				L2:	getfield_a_this 19;		// reference des/DesfireCard.selectedFile
					checkcast 0 109;		// T_CLASSORINTERFACE des/ValueRecord
					new 106;		// des/Value
					dup;
					sconst_4;
					newarray 11;
					dup;
					sconst_0;
					aload_2;
					bspush 9;
					baload;
					bastore;
					dup;
					sconst_1;
					aload_2;
					bspush 8;
					baload;
					bastore;
					dup;
					sconst_2;
					aload_2;
					bspush 7;
					baload;
					bastore;
					dup;
					sconst_3;
					aload_2;
					bspush 6;
					baload;
					bastore;
					invokespecial 107;		// des/Value.<init>([B)V
					invokevirtual 127;		// des/ValueRecord.decDebit(Ldes/Value;)V
					sspush -28416;
					invokestatic 177;		// javacard/framework/ISOException.throwIt(S)V
					return;
		}

		.method private writeRecord(Ljavacard/framework/APDU;[B)V {
			.stack 6;
			.locals 3;

			.descriptor	Ljavacard/framework/APDU;	1.10;

				L0:	aload_0;
					aload_1;
					aload_2;
					invokespecial 210;		// des/DesfireCard.receiveAPDU(Ljavacard/framework/APDU;[B)V
					getfield_b_this 7;		// byte des/DesfireCard.commandToContinue
					ifne_w L18;
				L1:	getfield_a_this 4;		// reference des/DesfireCard.selectedDF
					aload_2;
					sconst_5;
					baload;
					invokevirtual 100;		// des/DirectoryFile.getFile(B)Ldes/File;
					astore_3;
					aload_0;
					sconst_2;
					newarray 11;
					dup;
					sconst_0;
					aload_2;
					bspush 7;
					baload;
					bastore;
					dup;
					sconst_1;
					aload_2;
					bspush 6;
					baload;
					bastore;
					invokestatic 102;		// des/Util.byteArrayToShort([B)S
					putfield_s 8;		// short des/DesfireCard.offset
					aload_0;
					sconst_2;
					newarray 11;
					dup;
					sconst_0;
					aload_2;
					bspush 10;
					baload;
					bastore;
					dup;
					sconst_1;
					aload_2;
					bspush 9;
					baload;
					bastore;
					invokestatic 102;		// des/Util.byteArrayToShort([B)S
					putfield_s 9;		// short des/DesfireCard.bytesLeft
					aload_2;
					sconst_4;
					baload;
					bspush 7;
					ssub;
					s2b;
					sstore 4;
					aload_0;
					getfield_s_this 9;		// short des/DesfireCard.bytesLeft
					newarray 11;
					putfield_a 20;		// reference des/DesfireCard.dataBuffer
					sconst_0;
					sstore 5;
				L2:	sload 5;
					sload 4;
					if_scmpge L4;
				L3:	getfield_a_this 20;		// reference des/DesfireCard.dataBuffer
					sload 5;
					aload_2;
					sconst_5;
					sload 5;
					sadd;
					bspush 7;
					sadd;
					s2b;
					baload;
					bastore;
					sload 5;
					sconst_1;
					sadd;
					s2b;
					sstore 5;
					goto L2;
				L4:	aload_3;
					instanceof 0 111;		// T_CLASSORINTERFACE des/LinearRecord
					ifeq L7;
				L5:	getfield_a_this 4;		// reference des/DesfireCard.selectedDF
					aload_2;
					sconst_5;
					baload;
					invokevirtual 100;		// des/DirectoryFile.getFile(B)Ldes/File;
					checkcast 0 111;		// T_CLASSORINTERFACE des/LinearRecord
					astore_3;
					aload_3;
					checkcast 0 111;		// T_CLASSORINTERFACE des/LinearRecord
					getfield_b_this 11;		// byte des/DesfireCard.authenticated
					invokevirtual 129;		// des/LinearRecord.hasWriteAccess(B)Z
					ifne L10;
				L6:	sspush -28259;
					invokestatic 177;		// javacard/framework/ISOException.throwIt(S)V
					goto L10;
				L7:	aload_3;
					instanceof 0 113;		// T_CLASSORINTERFACE des/CyclicRecord
					ifeq L10;
				L8:	getfield_a_this 4;		// reference des/DesfireCard.selectedDF
					aload_2;
					sconst_5;
					baload;
					invokevirtual 100;		// des/DirectoryFile.getFile(B)Ldes/File;
					checkcast 0 113;		// T_CLASSORINTERFACE des/CyclicRecord
					astore_3;
					aload_3;
					checkcast 0 113;		// T_CLASSORINTERFACE des/CyclicRecord
					getfield_b_this 11;		// byte des/DesfireCard.authenticated
					invokevirtual 130;		// des/CyclicRecord.hasWriteAccess(B)Z
					ifne L10;
				L9:	sspush -28259;
					invokestatic 177;		// javacard/framework/ISOException.throwIt(S)V
				L10:	getfield_s_this 9;		// short des/DesfireCard.bytesLeft
					bspush 52;
					if_scmpgt L16;
				L11:	aload_3;
					instanceof 0 111;		// T_CLASSORINTERFACE des/LinearRecord
					ifeq L13;
				L12:	aload_3;
					checkcast 0 111;		// T_CLASSORINTERFACE des/LinearRecord
					getfield_a_this 20;		// reference des/DesfireCard.dataBuffer
					getfield_s_this 8;		// short des/DesfireCard.offset
					invokevirtual 131;		// des/LinearRecord.writeRecord([BS)V
				L13:	aload_3;
					instanceof 0 113;		// T_CLASSORINTERFACE des/CyclicRecord
					ifeq L15;
				L14:	aload_3;
					checkcast 0 113;		// T_CLASSORINTERFACE des/CyclicRecord
					getfield_a_this 20;		// reference des/DesfireCard.dataBuffer
					getfield_s_this 8;		// short des/DesfireCard.offset
					invokevirtual 132;		// des/CyclicRecord.writeRecord([BS)V
				L15:	aload_0;
					aconst_null;
					putfield_a 20;		// reference des/DesfireCard.dataBuffer
					aload_0;
					sconst_0;
					putfield_s 8;		// short des/DesfireCard.offset
					aload_0;
					sconst_0;
					putfield_s 9;		// short des/DesfireCard.bytesLeft
					sspush -28416;
					invokestatic 177;		// javacard/framework/ISOException.throwIt(S)V
					goto L17;
				L16:	aload_0;
					bspush 52;
					putfield_s 21;		// short des/DesfireCard.readed
					aload_0;
					getfield_s_this 9;		// short des/DesfireCard.bytesLeft
					bspush 52;
					ssub;
					putfield_s 9;		// short des/DesfireCard.bytesLeft
					aload_0;
					bspush 59;
					putfield_b 7;		// byte des/DesfireCard.commandToContinue
					bspush -81;
					invokestatic 177;		// javacard/framework/ISOException.throwIt(S)V
				L17:	goto_w L28;
				L18:	aload_2;
					sconst_4;
					baload;
					sstore_3;
					sconst_0;
					sstore 4;
				L19:	sload 4;
					sload_3;
					if_scmpge L21;
				L20:	getfield_a_this 20;		// reference des/DesfireCard.dataBuffer
					sload 4;
					getfield_s_this 21;		// short des/DesfireCard.readed
					sadd;
					aload_2;
					sconst_5;
					sload 4;
					sadd;
					s2b;
					baload;
					bastore;
					sload 4;
					sconst_1;
					sadd;
					s2b;
					sstore 4;
					goto L19;
				L21:	getfield_s_this 9;		// short des/DesfireCard.bytesLeft
					bspush 59;
					if_scmpgt L27;
				L22:	getfield_a_this 19;		// reference des/DesfireCard.selectedFile
					instanceof 0 111;		// T_CLASSORINTERFACE des/LinearRecord
					ifeq L24;
				L23:	getfield_a_this 19;		// reference des/DesfireCard.selectedFile
					checkcast 0 111;		// T_CLASSORINTERFACE des/LinearRecord
					getfield_a_this 20;		// reference des/DesfireCard.dataBuffer
					getfield_s_this 8;		// short des/DesfireCard.offset
					invokevirtual 131;		// des/LinearRecord.writeRecord([BS)V
				L24:	getfield_a_this 19;		// reference des/DesfireCard.selectedFile
					instanceof 0 113;		// T_CLASSORINTERFACE des/CyclicRecord
					ifeq L26;
				L25:	getfield_a_this 19;		// reference des/DesfireCard.selectedFile
					checkcast 0 113;		// T_CLASSORINTERFACE des/CyclicRecord
					getfield_a_this 20;		// reference des/DesfireCard.dataBuffer
					getfield_s_this 8;		// short des/DesfireCard.offset
					invokevirtual 132;		// des/CyclicRecord.writeRecord([BS)V
				L26:	aload_0;
					aconst_null;
					putfield_a 20;		// reference des/DesfireCard.dataBuffer
					aload_0;
					sconst_0;
					putfield_s 8;		// short des/DesfireCard.offset
					aload_0;
					sconst_0;
					putfield_s 9;		// short des/DesfireCard.bytesLeft
					sspush -28416;
					invokestatic 177;		// javacard/framework/ISOException.throwIt(S)V
					goto L28;
				L27:	aload_0;
					getfield_s_this 21;		// short des/DesfireCard.readed
					bspush 59;
					sadd;
					putfield_s 21;		// short des/DesfireCard.readed
					aload_0;
					getfield_s_this 9;		// short des/DesfireCard.bytesLeft
					bspush 59;
					ssub;
					putfield_s 9;		// short des/DesfireCard.bytesLeft
					aload_0;
					bspush 59;
					putfield_b 7;		// byte des/DesfireCard.commandToContinue
					bspush -81;
					invokestatic 177;		// javacard/framework/ISOException.throwIt(S)V
				L28:	return;
		}

		.method private readRecords(Ljavacard/framework/APDU;[B)V {
			.stack 6;
			.locals 3;

			.descriptor	Ljavacard/framework/APDU;	1.10;

				L0:	aload_0;
					aload_1;
					aload_2;
					invokespecial 210;		// des/DesfireCard.receiveAPDU(Ljavacard/framework/APDU;[B)V
					aconst_null;
					astore_3;
					getfield_b_this 7;		// byte des/DesfireCard.commandToContinue
					ifne_w L14;
				L1:	getfield_a_this 4;		// reference des/DesfireCard.selectedDF
					aload_2;
					sconst_5;
					baload;
					invokevirtual 100;		// des/DirectoryFile.getFile(B)Ldes/File;
					astore 4;
					aload_0;
					sconst_2;
					newarray 11;
					dup;
					sconst_0;
					aload_2;
					bspush 7;
					baload;
					bastore;
					dup;
					sconst_1;
					aload_2;
					bspush 6;
					baload;
					bastore;
					invokestatic 102;		// des/Util.byteArrayToShort([B)S
					putfield_s 8;		// short des/DesfireCard.offset
					sconst_2;
					newarray 11;
					dup;
					sconst_0;
					aload_2;
					bspush 10;
					baload;
					bastore;
					dup;
					sconst_1;
					aload_2;
					bspush 9;
					baload;
					bastore;
					invokestatic 102;		// des/Util.byteArrayToShort([B)S
					sstore 5;
					aload 4;
					instanceof 0 111;		// T_CLASSORINTERFACE des/LinearRecord
					ifeq_w L7;
				L2:	getfield_a_this 4;		// reference des/DesfireCard.selectedDF
					aload_2;
					sconst_5;
					baload;
					invokevirtual 100;		// des/DirectoryFile.getFile(B)Ldes/File;
					checkcast 0 111;		// T_CLASSORINTERFACE des/LinearRecord
					astore 4;
					aload 4;
					checkcast 0 111;		// T_CLASSORINTERFACE des/LinearRecord
					getfield_b_this 11;		// byte des/DesfireCard.authenticated
					invokevirtual 134;		// des/LinearRecord.hasReadAccess(B)Z
					ifne L4;
				L3:	sspush -28259;
					invokestatic 177;		// javacard/framework/ISOException.throwIt(S)V
				L4:	aload_0;
					sload 5;
					aload 4;
					checkcast 0 111;		// T_CLASSORINTERFACE des/LinearRecord
					getfield_s 22;		// short des/LinearRecord.recordSize
					smul;
					putfield_s 9;		// short des/DesfireCard.bytesLeft
					aload_0;
					aload 4;
					checkcast 0 111;		// T_CLASSORINTERFACE des/LinearRecord
					invokevirtual 136;		// des/LinearRecord.getCurrentSize()S
					getfield_s_this 8;		// short des/DesfireCard.offset
					aload 4;
					checkcast 0 111;		// T_CLASSORINTERFACE des/LinearRecord
					getfield_s 22;		// short des/LinearRecord.recordSize
					smul;
					ssub;
					getfield_s_this 9;		// short des/DesfireCard.bytesLeft
					ssub;
					putfield_s 8;		// short des/DesfireCard.offset
					getfield_s_this 9;		// short des/DesfireCard.bytesLeft
					bspush 59;
					if_scmpgt L6;
				L5:	aload 4;
					checkcast 0 111;		// T_CLASSORINTERFACE des/LinearRecord
					getfield_s_this 8;		// short des/DesfireCard.offset
					getfield_s_this 9;		// short des/DesfireCard.bytesLeft
					sconst_0;
					invokevirtual 137;		// des/LinearRecord.readData(SSB)[B
					astore_3;
					aload_0;
					sconst_0;
					putfield_s 8;		// short des/DesfireCard.offset
					aload_0;
					sconst_0;
					putfield_s 9;		// short des/DesfireCard.bytesLeft
					aload_0;
					aload_1;
					aload_2;
					aload_3;
					invokespecial 89;		// des/DesfireCard.sendResponse(Ljavacard/framework/APDU;[B[B)V
					goto L7;
				L6:	aload 4;
					checkcast 0 111;		// T_CLASSORINTERFACE des/LinearRecord
					getfield_s_this 8;		// short des/DesfireCard.offset
					bspush 59;
					sconst_0;
					invokevirtual 137;		// des/LinearRecord.readData(SSB)[B
					astore_3;
					aload_0;
					bspush -69;
					putfield_b 7;		// byte des/DesfireCard.commandToContinue
					aload_0;
					getfield_s_this 8;		// short des/DesfireCard.offset
					bspush 59;
					sadd;
					putfield_s 8;		// short des/DesfireCard.offset
					aload_0;
					getfield_s_this 9;		// short des/DesfireCard.bytesLeft
					bspush 59;
					ssub;
					putfield_s 9;		// short des/DesfireCard.bytesLeft
					aload_0;
					aload_1;
					aload_2;
					aload_3;
					bspush -81;
					invokespecial 235;		// des/DesfireCard.sendResponse(Ljavacard/framework/APDU;[B[BB)V
				L7:	aload 4;
					instanceof 0 113;		// T_CLASSORINTERFACE des/CyclicRecord
					ifeq_w L13;
				L8:	getfield_a_this 4;		// reference des/DesfireCard.selectedDF
					aload_2;
					sconst_5;
					baload;
					invokevirtual 100;		// des/DirectoryFile.getFile(B)Ldes/File;
					checkcast 0 113;		// T_CLASSORINTERFACE des/CyclicRecord
					astore 4;
					aload 4;
					checkcast 0 113;		// T_CLASSORINTERFACE des/CyclicRecord
					getfield_b_this 11;		// byte des/DesfireCard.authenticated
					invokevirtual 138;		// des/CyclicRecord.hasReadAccess(B)Z
					ifne L10;
				L9:	sspush -28259;
					invokestatic 177;		// javacard/framework/ISOException.throwIt(S)V
				L10:	aload_0;
					sload 5;
					aload 4;
					checkcast 0 113;		// T_CLASSORINTERFACE des/CyclicRecord
					getfield_s 23;		// short des/CyclicRecord.recordSize
					smul;
					putfield_s 9;		// short des/DesfireCard.bytesLeft
					aload_0;
					aload 4;
					checkcast 0 113;		// T_CLASSORINTERFACE des/CyclicRecord
					invokevirtual 140;		// des/CyclicRecord.getCurrentSize()S
					getfield_s_this 8;		// short des/DesfireCard.offset
					aload 4;
					checkcast 0 113;		// T_CLASSORINTERFACE des/CyclicRecord
					getfield_s 23;		// short des/CyclicRecord.recordSize
					smul;
					ssub;
					getfield_s_this 9;		// short des/DesfireCard.bytesLeft
					ssub;
					putfield_s 8;		// short des/DesfireCard.offset
					getfield_s_this 9;		// short des/DesfireCard.bytesLeft
					bspush 59;
					if_scmpgt L12;
				L11:	aload 4;
					checkcast 0 113;		// T_CLASSORINTERFACE des/CyclicRecord
					getfield_s_this 8;		// short des/DesfireCard.offset
					getfield_s_this 9;		// short des/DesfireCard.bytesLeft
					sconst_0;
					invokevirtual 141;		// des/CyclicRecord.readData(SSB)[B
					astore_3;
					aload_0;
					sconst_0;
					putfield_s 8;		// short des/DesfireCard.offset
					aload_0;
					sconst_0;
					putfield_s 9;		// short des/DesfireCard.bytesLeft
					aload_0;
					aload_1;
					aload_2;
					aload_3;
					invokespecial 89;		// des/DesfireCard.sendResponse(Ljavacard/framework/APDU;[B[B)V
					goto L13;
				L12:	aload 4;
					checkcast 0 113;		// T_CLASSORINTERFACE des/CyclicRecord
					getfield_s_this 8;		// short des/DesfireCard.offset
					bspush 59;
					sconst_0;
					invokevirtual 141;		// des/CyclicRecord.readData(SSB)[B
					astore_3;
					aload_0;
					bspush -69;
					putfield_b 7;		// byte des/DesfireCard.commandToContinue
					aload_0;
					getfield_s_this 8;		// short des/DesfireCard.offset
					bspush 59;
					sadd;
					putfield_s 8;		// short des/DesfireCard.offset
					aload_0;
					getfield_s_this 9;		// short des/DesfireCard.bytesLeft
					bspush 59;
					ssub;
					putfield_s 9;		// short des/DesfireCard.bytesLeft
					aload_0;
					aload_1;
					aload_2;
					aload_3;
					bspush -81;
					invokespecial 235;		// des/DesfireCard.sendResponse(Ljavacard/framework/APDU;[B[BB)V
				L13:	goto_w L22;
				L14:	getfield_a_this 19;		// reference des/DesfireCard.selectedFile
					instanceof 0 111;		// T_CLASSORINTERFACE des/LinearRecord
					ifeq L18;
				L15:	getfield_s_this 9;		// short des/DesfireCard.bytesLeft
					bspush 59;
					if_scmpgt L17;
				L16:	getfield_a_this 19;		// reference des/DesfireCard.selectedFile
					checkcast 0 111;		// T_CLASSORINTERFACE des/LinearRecord
					getfield_s_this 8;		// short des/DesfireCard.offset
					getfield_s_this 9;		// short des/DesfireCard.bytesLeft
					sconst_0;
					invokevirtual 137;		// des/LinearRecord.readData(SSB)[B
					astore_3;
					aload_0;
					sconst_0;
					putfield_s 8;		// short des/DesfireCard.offset
					aload_0;
					sconst_0;
					putfield_s 9;		// short des/DesfireCard.bytesLeft
					aload_0;
					sconst_0;
					putfield_b 7;		// byte des/DesfireCard.commandToContinue
					aload_0;
					aload_1;
					aload_2;
					aload_3;
					invokespecial 89;		// des/DesfireCard.sendResponse(Ljavacard/framework/APDU;[B[B)V
					goto L18;
				L17:	getfield_a_this 19;		// reference des/DesfireCard.selectedFile
					checkcast 0 111;		// T_CLASSORINTERFACE des/LinearRecord
					getfield_s_this 8;		// short des/DesfireCard.offset
					bspush 59;
					sconst_0;
					invokevirtual 137;		// des/LinearRecord.readData(SSB)[B
					astore_3;
					aload_0;
					bspush -69;
					putfield_b 7;		// byte des/DesfireCard.commandToContinue
					aload_0;
					getfield_s_this 8;		// short des/DesfireCard.offset
					bspush 59;
					sadd;
					putfield_s 8;		// short des/DesfireCard.offset
					aload_0;
					getfield_s_this 9;		// short des/DesfireCard.bytesLeft
					bspush 59;
					ssub;
					putfield_s 9;		// short des/DesfireCard.bytesLeft
					aload_0;
					aload_1;
					aload_2;
					aload_3;
					bspush -81;
					invokespecial 235;		// des/DesfireCard.sendResponse(Ljavacard/framework/APDU;[B[BB)V
				L18:	getfield_a_this 19;		// reference des/DesfireCard.selectedFile
					instanceof 0 113;		// T_CLASSORINTERFACE des/CyclicRecord
					ifeq L22;
				L19:	getfield_s_this 9;		// short des/DesfireCard.bytesLeft
					bspush 59;
					if_scmpgt L21;
				L20:	getfield_a_this 19;		// reference des/DesfireCard.selectedFile
					checkcast 0 113;		// T_CLASSORINTERFACE des/CyclicRecord
					getfield_s_this 8;		// short des/DesfireCard.offset
					getfield_s_this 9;		// short des/DesfireCard.bytesLeft
					sconst_0;
					invokevirtual 141;		// des/CyclicRecord.readData(SSB)[B
					astore_3;
					aload_0;
					sconst_0;
					putfield_s 8;		// short des/DesfireCard.offset
					aload_0;
					sconst_0;
					putfield_s 9;		// short des/DesfireCard.bytesLeft
					aload_0;
					sconst_0;
					putfield_b 7;		// byte des/DesfireCard.commandToContinue
					aload_0;
					aload_1;
					aload_2;
					aload_3;
					invokespecial 89;		// des/DesfireCard.sendResponse(Ljavacard/framework/APDU;[B[B)V
					goto L22;
				L21:	getfield_a_this 19;		// reference des/DesfireCard.selectedFile
					checkcast 0 113;		// T_CLASSORINTERFACE des/CyclicRecord
					getfield_s_this 8;		// short des/DesfireCard.offset
					bspush 59;
					sconst_0;
					invokevirtual 141;		// des/CyclicRecord.readData(SSB)[B
					astore_3;
					aload_0;
					bspush -69;
					putfield_b 7;		// byte des/DesfireCard.commandToContinue
					aload_0;
					getfield_s_this 8;		// short des/DesfireCard.offset
					bspush 59;
					sadd;
					putfield_s 8;		// short des/DesfireCard.offset
					aload_0;
					getfield_s_this 9;		// short des/DesfireCard.bytesLeft
					bspush 59;
					ssub;
					putfield_s 9;		// short des/DesfireCard.bytesLeft
					aload_0;
					aload_1;
					aload_2;
					aload_3;
					bspush -81;
					invokespecial 235;		// des/DesfireCard.sendResponse(Ljavacard/framework/APDU;[B[BB)V
				L22:	return;
		}

		.method private clearRecordFile(Ljavacard/framework/APDU;[B)V {
			.stack 3;
			.locals 1;

			.descriptor	Ljavacard/framework/APDU;	1.10;

				L0:	aload_0;
					aload_1;
					aload_2;
					invokespecial 210;		// des/DesfireCard.receiveAPDU(Ljavacard/framework/APDU;[B)V
					getfield_a_this 4;		// reference des/DesfireCard.selectedDF
					aload_2;
					sconst_5;
					baload;
					invokevirtual 100;		// des/DirectoryFile.getFile(B)Ldes/File;
					astore_3;
					aload_3;
					instanceof 0 111;		// T_CLASSORINTERFACE des/LinearRecord
					ifeq L4;
				L1:	getfield_a_this 4;		// reference des/DesfireCard.selectedDF
					aload_2;
					sconst_5;
					baload;
					invokevirtual 100;		// des/DirectoryFile.getFile(B)Ldes/File;
					checkcast 0 111;		// T_CLASSORINTERFACE des/LinearRecord
					astore_3;
					aload_3;
					checkcast 0 111;		// T_CLASSORINTERFACE des/LinearRecord
					getfield_b_this 11;		// byte des/DesfireCard.authenticated
					invokevirtual 129;		// des/LinearRecord.hasWriteAccess(B)Z
					ifne L3;
				L2:	sspush -28259;
					invokestatic 177;		// javacard/framework/ISOException.throwIt(S)V
				L3:	aload_3;
					checkcast 0 111;		// T_CLASSORINTERFACE des/LinearRecord
					invokevirtual 142;		// des/LinearRecord.deleteRecords()V
					sspush -28416;
					invokestatic 177;		// javacard/framework/ISOException.throwIt(S)V
				L4:	aload_3;
					instanceof 0 113;		// T_CLASSORINTERFACE des/CyclicRecord
					ifeq L8;
				L5:	getfield_a_this 4;		// reference des/DesfireCard.selectedDF
					aload_2;
					sconst_5;
					baload;
					invokevirtual 100;		// des/DirectoryFile.getFile(B)Ldes/File;
					checkcast 0 113;		// T_CLASSORINTERFACE des/CyclicRecord
					astore_3;
					aload_3;
					checkcast 0 113;		// T_CLASSORINTERFACE des/CyclicRecord
					getfield_b_this 11;		// byte des/DesfireCard.authenticated
					invokevirtual 130;		// des/CyclicRecord.hasWriteAccess(B)Z
					ifne L7;
				L6:	sspush -28259;
					invokestatic 177;		// javacard/framework/ISOException.throwIt(S)V
				L7:	aload_3;
					checkcast 0 113;		// T_CLASSORINTERFACE des/CyclicRecord
					invokevirtual 143;		// des/CyclicRecord.deleteRecords()V
					sspush -28416;
					invokestatic 177;		// javacard/framework/ISOException.throwIt(S)V
				L8:	return;
		}

		.method private commitTransaction(Ljavacard/framework/APDU;[B)V {
			.stack 3;
			.locals 1;

			.descriptor	Ljavacard/framework/APDU;	1.10;

				L0:	sconst_0;
					sstore_3;
				L1:	sload_3;
					bspush 32;
					if_scmpge_w L16;
				L2:	getfield_a_this 4;		// reference des/DesfireCard.selectedDF
					getfield_a 24;		// reference des/DirectoryFile.waitingForTransaction
					sload_3;
					baload;
					sconst_1;
					if_scmpne_w L15;
				L3:	getfield_a_this 4;		// reference des/DesfireCard.selectedDF
					sload_3;
					invokevirtual 100;		// des/DirectoryFile.getFile(B)Ldes/File;
					instanceof 0 111;		// T_CLASSORINTERFACE des/LinearRecord
					ifeq L7;
				L4:	aload_0;
					getfield_a_this 4;		// reference des/DesfireCard.selectedDF
					sload_3;
					invokevirtual 100;		// des/DirectoryFile.getFile(B)Ldes/File;
					checkcast 0 111;		// T_CLASSORINTERFACE des/LinearRecord
					putfield_a 19;		// reference des/DesfireCard.selectedFile
					getfield_a_this 19;		// reference des/DesfireCard.selectedFile
					checkcast 0 111;		// T_CLASSORINTERFACE des/LinearRecord
					getfield_b_this 11;		// byte des/DesfireCard.authenticated
					invokevirtual 129;		// des/LinearRecord.hasWriteAccess(B)Z
					ifne L6;
				L5:	sspush -28259;
					invokestatic 177;		// javacard/framework/ISOException.throwIt(S)V
				L6:	getfield_a_this 19;		// reference des/DesfireCard.selectedFile
					checkcast 0 111;		// T_CLASSORINTERFACE des/LinearRecord
					invokevirtual 145;		// des/LinearRecord.commitTransaction()V
				L7:	getfield_a_this 4;		// reference des/DesfireCard.selectedDF
					sload_3;
					invokevirtual 100;		// des/DirectoryFile.getFile(B)Ldes/File;
					instanceof 0 113;		// T_CLASSORINTERFACE des/CyclicRecord
					ifeq L11;
				L8:	aload_0;
					getfield_a_this 4;		// reference des/DesfireCard.selectedDF
					sload_3;
					invokevirtual 100;		// des/DirectoryFile.getFile(B)Ldes/File;
					checkcast 0 113;		// T_CLASSORINTERFACE des/CyclicRecord
					putfield_a 19;		// reference des/DesfireCard.selectedFile
					getfield_a_this 19;		// reference des/DesfireCard.selectedFile
					checkcast 0 113;		// T_CLASSORINTERFACE des/CyclicRecord
					getfield_b_this 11;		// byte des/DesfireCard.authenticated
					invokevirtual 130;		// des/CyclicRecord.hasWriteAccess(B)Z
					ifne L10;
				L9:	sspush -28259;
					invokestatic 177;		// javacard/framework/ISOException.throwIt(S)V
				L10:	getfield_a_this 19;		// reference des/DesfireCard.selectedFile
					checkcast 0 113;		// T_CLASSORINTERFACE des/CyclicRecord
					invokevirtual 146;		// des/CyclicRecord.commitTransaction()V
				L11:	getfield_a_this 4;		// reference des/DesfireCard.selectedDF
					sload_3;
					invokevirtual 100;		// des/DirectoryFile.getFile(B)Ldes/File;
					instanceof 0 109;		// T_CLASSORINTERFACE des/ValueRecord
					ifeq L15;
				L12:	aload_0;
					getfield_a_this 4;		// reference des/DesfireCard.selectedDF
					sload_3;
					invokevirtual 100;		// des/DirectoryFile.getFile(B)Ldes/File;
					checkcast 0 109;		// T_CLASSORINTERFACE des/ValueRecord
					putfield_a 19;		// reference des/DesfireCard.selectedFile
					getfield_a_this 19;		// reference des/DesfireCard.selectedFile
					checkcast 0 109;		// T_CLASSORINTERFACE des/ValueRecord
					getfield_b_this 11;		// byte des/DesfireCard.authenticated
					invokevirtual 125;		// des/ValueRecord.hasWriteAccess(B)Z
					ifne L14;
				L13:	sspush -28259;
					invokestatic 177;		// javacard/framework/ISOException.throwIt(S)V
				L14:	getfield_a_this 19;		// reference des/DesfireCard.selectedFile
					checkcast 0 109;		// T_CLASSORINTERFACE des/ValueRecord
					invokevirtual 147;		// des/ValueRecord.commitTransaction()V
				L15:	sload_3;
					sconst_1;
					sadd;
					s2b;
					sstore_3;
					goto_w L1;
				L16:	sspush -28416;
					invokestatic 177;		// javacard/framework/ISOException.throwIt(S)V
					return;
		}

		.method private abortTransaction(Ljavacard/framework/APDU;[B)V {
			.stack 3;
			.locals 1;

			.descriptor	Ljavacard/framework/APDU;	1.10;

				L0:	sconst_0;
					sstore_3;
				L1:	sload_3;
					bspush 32;
					if_scmpge_w L16;
				L2:	getfield_a_this 4;		// reference des/DesfireCard.selectedDF
					getfield_a 24;		// reference des/DirectoryFile.waitingForTransaction
					sload_3;
					baload;
					sconst_1;
					if_scmpne_w L15;
				L3:	getfield_a_this 4;		// reference des/DesfireCard.selectedDF
					sload_3;
					invokevirtual 100;		// des/DirectoryFile.getFile(B)Ldes/File;
					instanceof 0 111;		// T_CLASSORINTERFACE des/LinearRecord
					ifeq L7;
				L4:	aload_0;
					getfield_a_this 4;		// reference des/DesfireCard.selectedDF
					sload_3;
					invokevirtual 100;		// des/DirectoryFile.getFile(B)Ldes/File;
					checkcast 0 111;		// T_CLASSORINTERFACE des/LinearRecord
					putfield_a 19;		// reference des/DesfireCard.selectedFile
					getfield_a_this 19;		// reference des/DesfireCard.selectedFile
					checkcast 0 111;		// T_CLASSORINTERFACE des/LinearRecord
					getfield_b_this 11;		// byte des/DesfireCard.authenticated
					invokevirtual 129;		// des/LinearRecord.hasWriteAccess(B)Z
					ifne L6;
				L5:	sspush -28259;
					invokestatic 177;		// javacard/framework/ISOException.throwIt(S)V
				L6:	getfield_a_this 19;		// reference des/DesfireCard.selectedFile
					checkcast 0 111;		// T_CLASSORINTERFACE des/LinearRecord
					invokevirtual 148;		// des/LinearRecord.abortTransaction()V
				L7:	getfield_a_this 4;		// reference des/DesfireCard.selectedDF
					sload_3;
					invokevirtual 100;		// des/DirectoryFile.getFile(B)Ldes/File;
					instanceof 0 113;		// T_CLASSORINTERFACE des/CyclicRecord
					ifeq L11;
				L8:	aload_0;
					getfield_a_this 4;		// reference des/DesfireCard.selectedDF
					sload_3;
					invokevirtual 100;		// des/DirectoryFile.getFile(B)Ldes/File;
					checkcast 0 113;		// T_CLASSORINTERFACE des/CyclicRecord
					putfield_a 19;		// reference des/DesfireCard.selectedFile
					getfield_a_this 19;		// reference des/DesfireCard.selectedFile
					checkcast 0 113;		// T_CLASSORINTERFACE des/CyclicRecord
					getfield_b_this 11;		// byte des/DesfireCard.authenticated
					invokevirtual 130;		// des/CyclicRecord.hasWriteAccess(B)Z
					ifne L10;
				L9:	sspush -28259;
					invokestatic 177;		// javacard/framework/ISOException.throwIt(S)V
				L10:	getfield_a_this 19;		// reference des/DesfireCard.selectedFile
					checkcast 0 113;		// T_CLASSORINTERFACE des/CyclicRecord
					invokevirtual 149;		// des/CyclicRecord.abortTransaction()V
				L11:	getfield_a_this 4;		// reference des/DesfireCard.selectedDF
					sload_3;
					invokevirtual 100;		// des/DirectoryFile.getFile(B)Ldes/File;
					instanceof 0 109;		// T_CLASSORINTERFACE des/ValueRecord
					ifeq L15;
				L12:	aload_0;
					getfield_a_this 4;		// reference des/DesfireCard.selectedDF
					sload_3;
					invokevirtual 100;		// des/DirectoryFile.getFile(B)Ldes/File;
					checkcast 0 109;		// T_CLASSORINTERFACE des/ValueRecord
					putfield_a 19;		// reference des/DesfireCard.selectedFile
					getfield_a_this 19;		// reference des/DesfireCard.selectedFile
					checkcast 0 109;		// T_CLASSORINTERFACE des/ValueRecord
					getfield_b_this 11;		// byte des/DesfireCard.authenticated
					invokevirtual 125;		// des/ValueRecord.hasWriteAccess(B)Z
					ifne L14;
				L13:	sspush -28259;
					invokestatic 177;		// javacard/framework/ISOException.throwIt(S)V
				L14:	getfield_a_this 19;		// reference des/DesfireCard.selectedFile
					checkcast 0 109;		// T_CLASSORINTERFACE des/ValueRecord
					invokevirtual 150;		// des/ValueRecord.abortTransaction()V
				L15:	sload_3;
					sconst_1;
					sadd;
					s2b;
					sstore_3;
					goto_w L1;
				L16:	return;
		}

		.method private encrypt16([BLjavacard/security/Key;)[B {
			.stack 6;
			.locals 1;

			.descriptor	Ljavacard/security/Key;	2.0;

				L0:	aload_1;
					invokestatic 151;		// des/Util.crc16([B)[B
					astore_3;
					aload_1;
					aload_3;
					invokestatic 152;		// des/Util.concatByteArray([B[B)[B
					astore_1;
					aload_1;
					invokestatic 153;		// des/Util.preparePaddedByteArray([B)[B
					astore_1;
					getfield_a_this 6;		// reference des/DesfireCard.cipher
					aload_2;
					sconst_2;
					invokevirtual 232;		// javacardx/crypto/Cipher.init(Ljavacard/security/Key;B)V
					getfield_a_this 6;		// reference des/DesfireCard.cipher
					aload_1;
					sconst_0;
					aload_1;
					arraylength;
					aload_1;
					sconst_0;
					invokevirtual 234;		// javacardx/crypto/Cipher.doFinal([BSS[BS)S
					pop;
					aload_1;
					areturn;
		}

		.method private decrypt16([BLjavacard/security/Key;)[B {
			.stack 6;
			.locals 4;

			.descriptor	Ljavacard/security/Key;	2.0;

				L0:	aload_1;
					arraylength;
					newarray 11;
					astore_3;
				L1:	getfield_a_this 6;		// reference des/DesfireCard.cipher
					aload_2;
					sconst_1;
					invokevirtual 232;		// javacardx/crypto/Cipher.init(Ljavacard/security/Key;B)V
					getfield_a_this 6;		// reference des/DesfireCard.cipher
					aload_1;
					sconst_0;
					aload_1;
					arraylength;
					aload_3;
					sconst_0;
					invokevirtual 234;		// javacardx/crypto/Cipher.doFinal([BSS[BS)S
					pop;
					aload_3;
					invokestatic 155;		// des/Util.removePadding([B)[B
					astore 4;
					aload 4;
					aload 4;
					arraylength;
					sconst_2;
					ssub;
					s2b;
					aload 4;
					arraylength;
					sconst_1;
					ssub;
					s2b;
					invokestatic 236;		// des/Util.subByteArray([BBB)[B
					astore 5;
					aload 4;
					sconst_0;
					aload 4;
					arraylength;
					sconst_3;
					ssub;
					s2b;
					invokestatic 236;		// des/Util.subByteArray([BBB)[B
					astore 4;
					aload 4;
					invokestatic 151;		// des/Util.crc16([B)[B
					astore 6;
					aload 6;
					aload 5;
					invokestatic 156;		// des/Util.byteArrayCompare([B[B)Z
					ifne L6;
				L2:	aload_3;
					aload_3;
					arraylength;
					sconst_2;
					ssub;
					s2b;
					aload_3;
					arraylength;
					sconst_1;
					ssub;
					s2b;
					invokestatic 236;		// des/Util.subByteArray([BBB)[B
					astore 5;
					aload_3;
					sconst_0;
					aload_3;
					arraylength;
					sconst_3;
					ssub;
					s2b;
					invokestatic 236;		// des/Util.subByteArray([BBB)[B
					astore_3;
					aload_3;
					invokestatic 151;		// des/Util.crc16([B)[B
					astore 6;
					aload 6;
					aload 5;
					invokestatic 156;		// des/Util.byteArrayCompare([B[B)Z
					ifne L4;
				L3:	aload_0;
					sconst_0;
					putfield_b 13;		// byte des/DesfireCard.securityLevel
					sspush -28386;
					invokestatic 177;		// javacard/framework/ISOException.throwIt(S)V
				L4:	aload_3;
				L5:	areturn;
				L6:	aload 4;
				L7:	areturn;
				L8:	astore 4;
					aload_0;
					sconst_0;
					putfield_b 13;		// byte des/DesfireCard.securityLevel
					sspush -28259;
					invokestatic 177;		// javacard/framework/ISOException.throwIt(S)V
					aconst_null;
					areturn;
			.exceptionTable {
				// start_block end_block handler_block catch_type_index
				L1 L5 L8 154;
				L6 L7 L8 154;
			}
		}

		.method private getCData([B)[B {
			.stack 3;
			.locals 0;

				L0:	getfield_b_this 13;		// byte des/DesfireCard.securityLevel
					slookupswitch L3 2 0 L1 2 L2;
				L1:	aload_1;
					areturn;
				L2:	aload_0;
					aload_1;
					getfield_a_this 12;		// reference des/DesfireCard.sessionKey
					invokespecial 157;		// des/DesfireCard.decrypt16([BLjavacard/security/Key;)[B
					astore_1;
					aload_1;
					areturn;
				L3:	aconst_null;
					areturn;
		}

		.method private receiveAPDU(Ljavacard/framework/APDU;[B)V {
			.stack 6;
			.locals 3;

			.descriptor	Ljavacard/framework/APDU;	1.10;

				L0:	aload_2;
					sconst_4;
					baload;
					sspush 255;
					sand;
					sstore_3;
					aload_1;
					invokevirtual 158;		// javacard/framework/APDU.setIncomingAndReceive()S
					sstore 4;
				L1:	sload_3;
					ifle L3;
				L2:	sload_3;
					sload 4;
					ssub;
					sstore_3;
					aload_1;
					sconst_5;
					invokevirtual 159;		// javacard/framework/APDU.receiveBytes(S)S
					sstore 4;
					goto L1;
				L3:	aload_0;
					aload_2;
					sconst_5;
					sconst_5;
					aload_2;
					sconst_4;
					baload;
					sadd;
					sconst_1;
					ssub;
					s2b;
					invokestatic 236;		// des/Util.subByteArray([BBB)[B
					invokespecial 160;		// des/DesfireCard.getCData([B)[B
					astore 5;
					aload 5;
					sconst_0;
					aload 5;
					arraylength;
					aload_2;
					sconst_5;
					invokestatic 161;		// des/Util.copyByteArray([BSS[BS)[B
					astore_2;
					aload_2;
					sconst_4;
					aload 5;
					arraylength;
					s2b;
					bastore;
					return;
		}

		.method private sendResponse(Ljavacard/framework/APDU;[B[B)V {
			.stack 5;
			.locals 0;

			.descriptor	Ljavacard/framework/APDU;	1.10;

				L0:	aload_0;
					aload_1;
					aload_2;
					aload_3;
					sconst_0;
					invokespecial 235;		// des/DesfireCard.sendResponse(Ljavacard/framework/APDU;[B[BB)V
					return;
		}

		.method private sendResponseAndChangeStatus(Ljavacard/framework/APDU;[B[B[B)V {
			.stack 4;
			.locals 2;

			.descriptor	Ljavacard/framework/APDU;	1.10;

				L0:	aload_1;
					invokevirtual 162;		// javacard/framework/APDU.setOutgoing()S
					sstore 5;
					aload_3;
					arraylength;
					ifne L2;
				L1:	sspush -28290;
					invokestatic 177;		// javacard/framework/ISOException.throwIt(S)V
				L2:	getfield_b_this 13;		// byte des/DesfireCard.securityLevel
					stableswitch L6 0 2 L3 L4 L5;
				L3:	goto L6;
				L4:	goto L6;
				L5:	aload_0;
					aload_3;
					getfield_a_this 12;		// reference des/DesfireCard.sessionKey
					invokespecial 163;		// des/DesfireCard.encrypt16([BLjavacard/security/Key;)[B
					astore_3;
					goto L6;
				L6:	getfield_a_this 12;		// reference des/DesfireCard.sessionKey
					invokeinterface 1 139 0;		// javacard/security/Key
					getfield_a_this 12;		// reference des/DesfireCard.sessionKey
					checkcast 0 133;		// T_CLASSORINTERFACE javacard/security/DESKey
					aload 4;
					sconst_0;
					invokeinterface 3 133 5;		// javacard/security/DESKey
					aload_0;
					sconst_2;
					putfield_b 13;		// byte des/DesfireCard.securityLevel
					aload_1;
					aload_3;
					arraylength;
					invokevirtual 164;		// javacard/framework/APDU.setOutgoingLength(S)V
					sconst_0;
					sstore 6;
				L7:	sload 6;
					aload_3;
					arraylength;
					if_scmpge L9;
				L8:	aload_2;
					sload 6;
					aload_3;
					sload 6;
					baload;
					bastore;
					sload 6;
					sconst_1;
					sadd;
					s2b;
					sstore 6;
					goto L7;
				L9:	aload_1;
					sconst_0;
					aload_3;
					arraylength;
					invokevirtual 165;		// javacard/framework/APDU.sendBytes(SS)V
					return;
		}

		.method private sendResponse(Ljavacard/framework/APDU;[B[BB)V {
			.stack 4;
			.locals 2;

			.descriptor	Ljavacard/framework/APDU;	1.10;

				L0:	aload_1;
					invokevirtual 162;		// javacard/framework/APDU.setOutgoing()S
					sstore 5;
					aload_3;
					arraylength;
					ifne L2;
				L1:	sspush -28290;
					invokestatic 177;		// javacard/framework/ISOException.throwIt(S)V
				L2:	getfield_b_this 13;		// byte des/DesfireCard.securityLevel
					stableswitch L6 0 2 L3 L4 L5;
				L3:	goto L6;
				L4:	goto L6;
				L5:	aload_0;
					aload_3;
					getfield_a_this 12;		// reference des/DesfireCard.sessionKey
					invokespecial 163;		// des/DesfireCard.encrypt16([BLjavacard/security/Key;)[B
					astore_3;
					goto L6;
				L6:	aload_1;
					aload_3;
					arraylength;
					invokevirtual 164;		// javacard/framework/APDU.setOutgoingLength(S)V
					sconst_0;
					sstore 6;
				L7:	sload 6;
					aload_3;
					arraylength;
					if_scmpge L9;
				L8:	aload_2;
					sload 6;
					aload_3;
					sload 6;
					baload;
					bastore;
					sload 6;
					sconst_1;
					sadd;
					s2b;
					sstore 6;
					goto L7;
				L9:	aload_1;
					sconst_0;
					aload_3;
					arraylength;
					invokevirtual 165;		// javacard/framework/APDU.sendBytes(SS)V
				L10:	goto L12;
				L11:	astore 5;
					aload 5;
					invokevirtual 167;		// javacard/framework/CardRuntimeException.getReason()S
					invokestatic 177;		// javacard/framework/ISOException.throwIt(S)V
				L12:	return;
			.exceptionTable {
				// start_block end_block handler_block catch_type_index
				L0 L10 L11 166;
			}
		}

		.method public select(Z)Z 8 {
			.stack 1;
			.locals 0;

				L0:	aload_0;
					invokespecial 168;		// des/DesfireCard.clear()V
					sconst_1;
					sreturn;
		}

		.method public deselect(Z)V 9 {
			.stack 1;
			.locals 0;

				L0:	aload_0;
					invokespecial 168;		// des/DesfireCard.clear()V
					return;
		}

		.method private clear()V {
			.stack 2;
			.locals 0;

				L0:	aload_0;
					aconst_null;
					putfield_a 19;		// reference des/DesfireCard.selectedFile
					aload_0;
					getfield_a_this 3;		// reference des/DesfireCard.masterFile
					putfield_a 4;		// reference des/DesfireCard.selectedDF
					aload_0;
					sconst_0;
					putfield_b 7;		// byte des/DesfireCard.commandToContinue
					aload_0;
					sconst_m1;
					putfield_b 11;		// byte des/DesfireCard.authenticated
					aload_0;
					aconst_null;
					putfield_a 20;		// reference des/DesfireCard.dataBuffer
					aload_0;
					sconst_0;
					putfield_b 13;		// byte des/DesfireCard.securityLevel
					getfield_a_this 12;		// reference des/DesfireCard.sessionKey
					invokeinterface 1 139 0;		// javacard/security/Key
					return;
		}

	}

	.class public DirectoryFile 2 extends File {

		.fields {
			public boolean configurationChangeable 0;		// Z
			public boolean[] activatedFiles 1;		// [Z
			public boolean[] waitingForTransaction 2;		// [Z
			protected byte[] permissions 3;		// [B
			private byte[] AID 4;		// [B
			private File[] arrayFiles 5;		// [Ldes/File;
			private 2.0[] keyList 6;		// [Ljavacard/security/Key;
			private 2.0 masterKey 7;		// Ljavacard/security/Key;
			private byte numberFiles 8;		// B
			private byte keyType 9;		// B
			private byte changeKeyAccessRights 10;		// B
			private boolean masterNotNeededForManage 11;		// Z
			private boolean masterNotNeededForCheck 12;		// Z
			private boolean masterChangeable 13;		// Z
			private byte maxKeyNumber 14;		// B
			private boolean ISOFileIDSupported 15;		// Z
			private static final byte MAX_FILES = 32;		// B
		}

		.publicMethodTable 5 {
			equals(Ljava/lang/Object;)Z;
			getFileID()B;
			setActive(Z)V;
			getSize()B;
			setSize(B)V;
			setAID([B)V;
			getNumberFiles()B;
			getFile(B)Ldes/File;;
			updateFile(Ldes/File;B)V;
			addFile(Ldes/File;)V;
			deleteFile(B)V;
			getKey(B)Ljavacard/security/Key;;
			getMasterKey()Ljavacard/security/Key;;
			changeKey(B[B)V;
			getMasterKeyType()B;
			hasChangeAccess(BB)Z;
			hasKeySettingsChangeAllowed(B)Z;
			changeKeySettings(B)V;
			hasGetRights(B)Z;
			hasManageRights(B)Z;
			getKeySettings()B;
			getKeyNumber()B;
			isMasterFile()Z;
			isValidKeyNumber(B)Z;
		}

		.packageMethodTable 0 {
		}

		.method protected <init>(B)V 0 {
			.stack 5;
			.locals 1;

				L0:	aload_0;
					sload_1;
					invokespecial 169;		// des/File.<init>(B)V
					aload_0;
					bspush 32;
					newarray 10;
					putfield_a 18;		// reference des/DirectoryFile.activatedFiles
					aload_0;
					bspush 32;
					newarray 10;
					putfield_a 24;		// reference des/DirectoryFile.waitingForTransaction
					aload_0;
					bspush 32;
					anewarray 170;		// des/File
					putfield_a 25;		// reference des/DirectoryFile.arrayFiles
					aload_0;
					sconst_2;
					newarray 11;
					dup;
					sconst_0;
					sconst_0;
					bastore;
					dup;
					sconst_1;
					sconst_0;
					bastore;
					putfield_a 26;		// reference des/DirectoryFile.permissions
					aload_0;
					sconst_0;
					putfield_b 27;		// byte des/DirectoryFile.numberFiles
					sconst_0;
					sstore_2;
				L1:	sload_2;
					getfield_a_this 18;		// reference des/DirectoryFile.activatedFiles
					arraylength;
					if_scmpge L3;
				L2:	getfield_a_this 18;		// reference des/DirectoryFile.activatedFiles
					sload_2;
					sconst_0;
					bastore;
					sload_2;
					sconst_1;
					sadd;
					s2b;
					sstore_2;
					goto L1;
				L3:	aload_0;
					sconst_1;
					putfield_b 28;		// boolean des/DirectoryFile.configurationChangeable
					aload_0;
					sconst_1;
					putfield_b 29;		// boolean des/DirectoryFile.masterNotNeededForManage
					aload_0;
					sconst_1;
					putfield_b 30;		// boolean des/DirectoryFile.masterNotNeededForCheck
					aload_0;
					sconst_1;
					putfield_b 31;		// boolean des/DirectoryFile.masterChangeable
					aload_0;
					sconst_0;
					putfield_b 32;		// byte des/DirectoryFile.keyType
					sconst_3;
					sspush 128;
					sconst_0;
					invokestatic 128;		// javacard/security/KeyBuilder.buildKey(BSZ)Ljavacard/security/Key;
					checkcast 0 133;		// T_CLASSORINTERFACE javacard/security/DESKey
					astore_2;
					aload_2;
					invokeinterface 1 139 0;		// javacard/security/Key
					aload_2;
					getstatic_a 179;		// reference des/Util.DEFAULT_MASTER_KEY
					sconst_0;
					invokeinterface 3 133 5;		// javacard/security/DESKey
					aload_0;
					aload_2;
					putfield_a 33;		// reference des/DirectoryFile.masterKey
					aload_0;
					sconst_m1;
					putfield_b 34;		// byte des/DirectoryFile.maxKeyNumber
					return;
		}

		.method protected <init>(B[B)V 1 {
			.stack 5;
			.locals 1;

				L0:	aload_0;
					sload_1;
					invokespecial 169;		// des/File.<init>(B)V
					aload_0;
					bspush 32;
					newarray 10;
					putfield_a 18;		// reference des/DirectoryFile.activatedFiles
					aload_0;
					bspush 32;
					newarray 10;
					putfield_a 24;		// reference des/DirectoryFile.waitingForTransaction
					aload_0;
					bspush 32;
					anewarray 170;		// des/File
					putfield_a 25;		// reference des/DirectoryFile.arrayFiles
					aload_0;
					sconst_2;
					newarray 11;
					dup;
					sconst_0;
					sconst_0;
					bastore;
					dup;
					sconst_1;
					sconst_0;
					bastore;
					putfield_a 26;		// reference des/DirectoryFile.permissions
					aload_0;
					sconst_0;
					putfield_b 27;		// byte des/DirectoryFile.numberFiles
					aload_0;
					aload_2;
					sconst_0;
					baload;
					invokevirtual 76;		// des/DirectoryFile.changeKeySettings(B)V
					aload_0;
					aload_2;
					sconst_1;
					baload;
					bspush 6;
					sshr;
					putfield_b 32;		// byte des/DirectoryFile.keyType
					aload_0;
					aload_2;
					sconst_1;
					baload;
					bspush 15;
					sand;
					putfield_b 34;		// byte des/DirectoryFile.maxKeyNumber
					aload_2;
					sconst_1;
					baload;
					bspush 16;
					sand;
					bspush 16;
					if_scmpne L2;
				L1:	aload_0;
					sconst_1;
					putfield_b 35;		// boolean des/DirectoryFile.ISOFileIDSupported
					goto L3;
				L2:	aload_0;
					sconst_0;
					putfield_b 35;		// boolean des/DirectoryFile.ISOFileIDSupported
				L3:	sconst_0;
					sstore_3;
				L4:	sload_3;
					getfield_a_this 18;		// reference des/DirectoryFile.activatedFiles
					arraylength;
					if_scmpge L6;
				L5:	getfield_a_this 18;		// reference des/DirectoryFile.activatedFiles
					sload_3;
					sconst_0;
					bastore;
					sload_3;
					sconst_1;
					sadd;
					s2b;
					sstore_3;
					goto L4;
				L6:	sconst_0;
					sstore_3;
				L7:	sload_3;
					getfield_a_this 24;		// reference des/DirectoryFile.waitingForTransaction
					arraylength;
					if_scmpge L9;
				L8:	getfield_a_this 24;		// reference des/DirectoryFile.waitingForTransaction
					sload_3;
					sconst_0;
					bastore;
					sload_3;
					sconst_1;
					sadd;
					s2b;
					sstore_3;
					goto L7;
				L9:	aload_0;
					getfield_b_this 34;		// byte des/DirectoryFile.maxKeyNumber
					anewarray 139;		// javacard/security/Key
					putfield_a 36;		// reference des/DirectoryFile.keyList
					aload_0;
					sconst_0;
					putfield_b 32;		// byte des/DirectoryFile.keyType
					sconst_3;
					sspush 128;
					sconst_0;
					invokestatic 128;		// javacard/security/KeyBuilder.buildKey(BSZ)Ljavacard/security/Key;
					checkcast 0 133;		// T_CLASSORINTERFACE javacard/security/DESKey
					astore_3;
					aload_3;
					invokeinterface 1 139 0;		// javacard/security/Key
					aload_3;
					getstatic_a 179;		// reference des/Util.DEFAULT_MASTER_KEY
					sconst_0;
					invokeinterface 3 133 5;		// javacard/security/DESKey
					getfield_a_this 36;		// reference des/DirectoryFile.keyList
					sconst_0;
					aload_3;
					aastore;
					return;
		}

		.method public setAID([B)V 5 {
			.stack 0;
			.locals 0;

				L0:	return;
		}

		.method public getNumberFiles()B 6 {
			.stack 1;
			.locals 0;

				L0:	getfield_b_this 27;		// byte des/DirectoryFile.numberFiles
					sreturn;
		}

		.method public getFile(B)Ldes/File; 7 {
			.stack 2;
			.locals 0;

				L0:	getfield_a_this 18;		// reference des/DirectoryFile.activatedFiles
					sload_1;
					baload;
					sconst_1;
					if_scmpne L2;
				L1:	getfield_a_this 25;		// reference des/DirectoryFile.arrayFiles
					sload_1;
					aaload;
					areturn;
				L2:	sspush -28176;
					invokestatic 177;		// javacard/framework/ISOException.throwIt(S)V
					aconst_null;
					areturn;
		}

		.method public updateFile(Ldes/File;B)V 8 {
			.stack 3;
			.locals 0;

				L0:	getfield_a_this 25;		// reference des/DirectoryFile.arrayFiles
					sload_2;
					aload_1;
					aastore;
					return;
		}

		.method public addFile(Ldes/File;)V 9 {
			.stack 3;
			.locals 0;

				L0:	getfield_a_this 18;		// reference des/DirectoryFile.activatedFiles
					aload_1;
					invokevirtual 75;		// des/File.getFileID()B
					baload;
					sconst_1;
					if_scmpne L2;
				L1:	sspush -28194;
					invokestatic 177;		// javacard/framework/ISOException.throwIt(S)V
				L2:	getfield_a_this 25;		// reference des/DirectoryFile.arrayFiles
					aload_1;
					invokevirtual 75;		// des/File.getFileID()B
					aload_1;
					aastore;
					aload_0;
					dup;
					getfield_b 27;		// byte des/DirectoryFile.numberFiles
					sconst_1;
					sadd;
					s2b;
					putfield_b 27;		// byte des/DirectoryFile.numberFiles
					getfield_a_this 18;		// reference des/DirectoryFile.activatedFiles
					aload_1;
					invokevirtual 75;		// des/File.getFileID()B
					sconst_1;
					bastore;
					return;
		}

		.method public deleteFile(B)V 10 {
			.stack 3;
			.locals 0;

				L0:	getfield_a_this 18;		// reference des/DirectoryFile.activatedFiles
					sload_1;
					sconst_0;
					bastore;
					getfield_a_this 25;		// reference des/DirectoryFile.arrayFiles
					sload_1;
					aconst_null;
					aastore;
					aload_0;
					dup;
					getfield_b 27;		// byte des/DirectoryFile.numberFiles
					sconst_1;
					ssub;
					s2b;
					putfield_b 27;		// byte des/DirectoryFile.numberFiles
					return;
		}

		.method public getKey(B)Ljavacard/security/Key; 11 {
			.stack 2;
			.locals 0;

			.descriptor	Ljavacard/security/Key;	2.0;

				L0:	sload_1;
					getfield_b_this 34;		// byte des/DirectoryFile.maxKeyNumber
					if_scmplt L2;
				L1:	sspush -28352;
					invokestatic 177;		// javacard/framework/ISOException.throwIt(S)V
					goto L4;
				L2:	getfield_a_this 36;		// reference des/DirectoryFile.keyList
					sload_1;
					aaload;
					ifnonnull L4;
				L3:	sspush -28352;
					invokestatic 177;		// javacard/framework/ISOException.throwIt(S)V
				L4:	getfield_a_this 36;		// reference des/DirectoryFile.keyList
					sload_1;
					aaload;
					areturn;
		}

		.method public getMasterKey()Ljavacard/security/Key; 12 {
			.stack 1;
			.locals 0;

			.descriptor	Ljavacard/security/Key;	2.0;

				L0:	getfield_a_this 33;		// reference des/DirectoryFile.masterKey
					areturn;
		}

		.method public changeKey(B[B)V 13 {
			.stack 3;
			.locals 1;

				L0:	sload_1;
					getfield_b_this 34;		// byte des/DirectoryFile.maxKeyNumber
					if_scmplt L2;
				L1:	sspush -28352;
					invokestatic 177;		// javacard/framework/ISOException.throwIt(S)V
				L2:	aload_0;
					invokevirtual 75;		// des/File.getFileID()B
					ifne L4;
				L3:	sconst_3;
					sspush 128;
					sconst_0;
					invokestatic 128;		// javacard/security/KeyBuilder.buildKey(BSZ)Ljavacard/security/Key;
					checkcast 0 133;		// T_CLASSORINTERFACE javacard/security/DESKey
					astore_3;
					aload_3;
					invokeinterface 1 139 0;		// javacard/security/Key
					aload_3;
					aload_2;
					sconst_0;
					invokeinterface 3 133 5;		// javacard/security/DESKey
					aload_0;
					aload_3;
					putfield_a 33;		// reference des/DirectoryFile.masterKey
					goto L5;
				L4:	sconst_3;
					sspush 128;
					sconst_0;
					invokestatic 128;		// javacard/security/KeyBuilder.buildKey(BSZ)Ljavacard/security/Key;
					checkcast 0 133;		// T_CLASSORINTERFACE javacard/security/DESKey
					astore_3;
					aload_3;
					invokeinterface 1 139 0;		// javacard/security/Key
					aload_3;
					aload_2;
					sconst_0;
					invokeinterface 3 133 5;		// javacard/security/DESKey
					getfield_a_this 36;		// reference des/DirectoryFile.keyList
					sload_1;
					aload_3;
					aastore;
				L5:	return;
		}

		.method public getMasterKeyType()B 14 {
			.stack 1;
			.locals 0;

				L0:	getfield_b_this 32;		// byte des/DirectoryFile.keyType
					sreturn;
		}

		.method public hasChangeAccess(BB)Z 15 {
			.stack 3;
			.locals 0;

				L0:	sload_2;
					getfield_b_this 34;		// byte des/DirectoryFile.maxKeyNumber
					if_scmplt L2;
				L1:	sspush -28352;
					invokestatic 177;		// javacard/framework/ISOException.throwIt(S)V
				L2:	aload_0;
					invokevirtual 75;		// des/File.getFileID()B
					ifne L12;
				L3:	sload_1;
					ifne L5;
				L4:	sconst_1;
					goto L6;
				L5:	sconst_0;
				L6:	getfield_b_this 31;		// boolean des/DirectoryFile.masterChangeable
					sconst_1;
					if_scmpne L8;
				L7:	sconst_1;
					goto L9;
				L8:	sconst_0;
				L9:	sand;
					ifeq L11;
				L10:	sconst_1;
					sreturn;
				L11:	sconst_0;
					sreturn;
				L12:	getfield_b_this 37;		// byte des/DirectoryFile.changeKeyAccessRights
					ifne L16;
				L13:	sload_1;
					ifne L15;
				L14:	sconst_1;
					sreturn;
				L15:	sconst_0;
					sreturn;
				L16:	getfield_b_this 37;		// byte des/DirectoryFile.changeKeyAccessRights
					bspush 15;
					if_scmpne L29;
				L17:	sload_2;
					ifne L19;
				L18:	sconst_1;
					goto L20;
				L19:	sconst_0;
				L20:	sload_1;
					ifne L22;
				L21:	sconst_1;
					goto L23;
				L22:	sconst_0;
				L23:	sand;
					getfield_b_this 31;		// boolean des/DirectoryFile.masterChangeable
					sconst_1;
					if_scmpne L25;
				L24:	sconst_1;
					goto L26;
				L25:	sconst_0;
				L26:	sand;
					ifeq L28;
				L27:	sconst_1;
					sreturn;
				L28:	sconst_0;
					sreturn;
				L29:	getfield_b_this 37;		// byte des/DirectoryFile.changeKeyAccessRights
					bspush 14;
					if_scmpne L41;
				L30:	sload_2;
					ifne L32;
				L31:	sconst_1;
					goto L33;
				L32:	sconst_0;
				L33:	getfield_b_this 31;		// boolean des/DirectoryFile.masterChangeable
					ifne L35;
				L34:	sconst_1;
					goto L36;
				L35:	sconst_0;
				L36:	sand;
					ifeq L38;
				L37:	sconst_0;
					sreturn;
				L38:	sload_2;
					sload_1;
					if_scmpne L40;
				L39:	sconst_1;
					sreturn;
				L40:	sconst_0;
					sreturn;
				L41:	sload_2;
					getfield_b_this 37;		// byte des/DirectoryFile.changeKeyAccessRights
					if_scmpne L45;
				L42:	sload_1;
					ifne L44;
				L43:	sconst_1;
					sreturn;
				L44:	sconst_0;
					sreturn;
				L45:	sload_2;
					ifne L51;
				L46:	getfield_b_this 31;		// boolean des/DirectoryFile.masterChangeable
					ifne L48;
				L47:	sconst_0;
					sreturn;
				L48:	sload_1;
					ifne L50;
				L49:	sconst_1;
					sreturn;
				L50:	sconst_0;
					sreturn;
				L51:	getfield_b_this 37;		// byte des/DirectoryFile.changeKeyAccessRights
					sload_1;
					if_scmpne L53;
				L52:	sconst_1;
					sreturn;
				L53:	sconst_0;
					sreturn;
		}

		.method public hasKeySettingsChangeAllowed(B)Z 16 {
			.stack 1;
			.locals 0;

				L0:	getfield_b_this 28;		// boolean des/DirectoryFile.configurationChangeable
					ifne L2;
				L1:	sconst_0;
					sreturn;
				L2:	sload_1;
					ifne L4;
				L3:	sconst_1;
					sreturn;
				L4:	sconst_0;
					sreturn;
		}

		.method public changeKeySettings(B)V 17 {
			.stack 3;
			.locals 0;

				L0:	aload_0;
					invokevirtual 75;		// des/File.getFileID()B
					ifeq L2;
				L1:	aload_0;
					sload_1;
					sconst_4;
					sshr;
					bspush 15;
					sand;
					putfield_b 37;		// byte des/DirectoryFile.changeKeyAccessRights
				L2:	sload_1;
					bspush -9;
					sor;
					sspush 247;
					if_scmpne L4;
				L3:	aload_0;
					sconst_0;
					putfield_b 28;		// boolean des/DirectoryFile.configurationChangeable
					goto L5;
				L4:	aload_0;
					sconst_1;
					putfield_b 28;		// boolean des/DirectoryFile.configurationChangeable
				L5:	sload_1;
					bspush -5;
					sor;
					sspush 251;
					if_scmpne L7;
				L6:	aload_0;
					sconst_0;
					putfield_b 29;		// boolean des/DirectoryFile.masterNotNeededForManage
					goto L8;
				L7:	aload_0;
					sconst_1;
					putfield_b 29;		// boolean des/DirectoryFile.masterNotNeededForManage
				L8:	sload_1;
					bspush -3;
					sor;
					sspush 253;
					if_scmpne L10;
				L9:	aload_0;
					sconst_0;
					putfield_b 30;		// boolean des/DirectoryFile.masterNotNeededForCheck
					goto L11;
				L10:	aload_0;
					sconst_1;
					putfield_b 30;		// boolean des/DirectoryFile.masterNotNeededForCheck
				L11:	sload_1;
					bspush -2;
					sor;
					sspush 254;
					if_scmpne L13;
				L12:	aload_0;
					sconst_0;
					putfield_b 31;		// boolean des/DirectoryFile.masterChangeable
					goto L14;
				L13:	aload_0;
					sconst_1;
					putfield_b 31;		// boolean des/DirectoryFile.masterChangeable
				L14:	return;
		}

		.method public hasGetRights(B)Z 18 {
			.stack 1;
			.locals 0;

				L0:	getfield_b_this 30;		// boolean des/DirectoryFile.masterNotNeededForCheck
					ifeq L2;
				L1:	sconst_1;
					sreturn;
				L2:	sload_1;
					ifne L4;
				L3:	sconst_1;
					sreturn;
				L4:	sconst_0;
					sreturn;
		}

		.method public hasManageRights(B)Z 19 {
			.stack 1;
			.locals 0;

				L0:	getfield_b_this 29;		// boolean des/DirectoryFile.masterNotNeededForManage
					ifeq L2;
				L1:	sconst_1;
					sreturn;
				L2:	sload_1;
					ifne L4;
				L3:	sconst_1;
					sreturn;
				L4:	sconst_0;
					sreturn;
		}

		.method public getKeySettings()B 20 {
			.stack 2;
			.locals 1;

				L0:	sconst_0;
					sstore_1;
					aload_0;
					invokevirtual 75;		// des/File.getFileID()B
					ifeq L2;
				L1:	getfield_b_this 37;		// byte des/DirectoryFile.changeKeyAccessRights
					sconst_4;
					sshl;
					s2b;
					sstore_1;
				L2:	getfield_b_this 28;		// boolean des/DirectoryFile.configurationChangeable
					sconst_1;
					if_scmpne L4;
				L3:	sload_1;
					bspush 8;
					sor;
					sstore_1;
				L4:	getfield_b_this 29;		// boolean des/DirectoryFile.masterNotNeededForManage
					sconst_1;
					if_scmpne L6;
				L5:	sload_1;
					sconst_4;
					sor;
					sstore_1;
				L6:	getfield_b_this 30;		// boolean des/DirectoryFile.masterNotNeededForCheck
					sconst_1;
					if_scmpne L8;
				L7:	sload_1;
					sconst_2;
					sor;
					sstore_1;
				L8:	getfield_b_this 31;		// boolean des/DirectoryFile.masterChangeable
					sconst_1;
					if_scmpne L10;
				L9:	sload_1;
					sconst_1;
					sor;
					sstore_1;
				L10:	sload_1;
					sreturn;
		}

		.method public getKeyNumber()B 21 {
			.stack 2;
			.locals 1;

				L0:	sconst_0;
					sstore_1;
					aload_0;
					invokevirtual 75;		// des/File.getFileID()B
					ifne L2;
				L1:	sconst_1;
					sreturn;
				L2:	getfield_b_this 32;		// byte des/DirectoryFile.keyType
					bspush 6;
					sshl;
					s2b;
					sstore_1;
					sload_1;
					getfield_b_this 34;		// byte des/DirectoryFile.maxKeyNumber
					sor;
					sstore_1;
					sload_1;
					sreturn;
		}

		.method public isMasterFile()Z 22 {
			.stack 1;
			.locals 0;

				L0:	sconst_0;
					sreturn;
		}

		.method public isValidKeyNumber(B)Z 23 {
			.stack 2;
			.locals 0;

				L0:	sload_1;
					getfield_b_this 34;		// byte des/DirectoryFile.maxKeyNumber
					if_scmplt L2;
				L1:	sconst_0;
					sreturn;
				L2:	getfield_a_this 36;		// reference des/DirectoryFile.keyList
					sload_1;
					aaload;
					ifnonnull L4;
				L3:	sconst_0;
					sreturn;
				L4:	sconst_1;
					sreturn;
		}

	}

	.class public CyclicRecord 3 extends File {

		.fields {
			private DirectoryFile parentFile 0;		// Ldes/DirectoryFile;
			private byte[] data 1;		// [B
			private byte[] uncommitedRecord 2;		// [B
			private byte[] permissions 3;		// [B
			private boolean waitingToDeleteRecord 4;		// Z
			 short size 5;		// S
			 short maxSize 6;		// S
			 short recordSize 7;		// S
		}

		.publicMethodTable 5 {
			equals(Ljava/lang/Object;)Z;
			getFileID()B;
			setActive(Z)V;
			getSize()B;
			setSize(B)V;
			getParent()Ldes/DirectoryFile;;
			getData()[B;
			getCurrentSize()S;
			getMaxSize()S;
			eraseData()V;
			deleteRecord()V;
			deleteRecords()V;
			writeRecord([B)V;
			writeRecord([BS)V;
			commitTransaction()V;
			abortTransaction()V;
			readValue()[B;
			readData(SSB)[B;
			getPermissions()[B;
			getAccessRight(B)B;
			hasWriteAccess(B)Z;
			hasReadAccess(B)Z;
		}

		.packageMethodTable 0 {
		}

		.method public <init>(BLdes/DirectoryFile;[BSS)V 0 {
			.stack 3;
			.locals 0;

				L0:	aload_0;
					sload_1;
					sconst_4;
					invokespecial 185;		// des/File.<init>(BB)V
					aload_0;
					aload_2;
					putfield_a 38;		// reference des/CyclicRecord.parentFile
					aload_0;
					aload_3;
					putfield_a 39;		// reference des/CyclicRecord.permissions
					aload_0;
					sload 5;
					sload 4;
					smul;
					newarray 11;
					putfield_a 40;		// reference des/CyclicRecord.data
					aload_0;
					sconst_0;
					putfield_s 41;		// short des/CyclicRecord.size
					aload_0;
					sload 4;
					putfield_s 23;		// short des/CyclicRecord.recordSize
					aload_0;
					sload 5;
					putfield_s 42;		// short des/CyclicRecord.maxSize
					aload_0;
					sload 4;
					newarray 11;
					putfield_a 43;		// reference des/CyclicRecord.uncommitedRecord
					aload_0;
					sconst_0;
					putfield_b 44;		// boolean des/CyclicRecord.waitingToDeleteRecord
					aload_2;
					aload_0;
					invokevirtual 193;		// des/DirectoryFile.addFile(Ldes/File;)V
					return;
		}

		.method public getParent()Ldes/DirectoryFile; 5 {
			.stack 1;
			.locals 0;

				L0:	getfield_a_this 38;		// reference des/CyclicRecord.parentFile
					areturn;
		}

		.method public getData()[B 6 {
			.stack 2;
			.locals 0;

				L0:	getfield_b_this 0;		// boolean des/File.active
					sconst_1;
					if_scmpne L2;
				L1:	getfield_a_this 40;		// reference des/CyclicRecord.data
					areturn;
				L2:	sspush 27010;
					invokestatic 177;		// javacard/framework/ISOException.throwIt(S)V
					aconst_null;
					areturn;
		}

		.method public getCurrentSize()S 7 {
			.stack 2;
			.locals 0;

				L0:	getfield_b_this 0;		// boolean des/File.active
					sconst_1;
					if_scmpne L2;
				L1:	getfield_s_this 41;		// short des/CyclicRecord.size
					sreturn;
				L2:	sspush 27010;
					invokestatic 177;		// javacard/framework/ISOException.throwIt(S)V
					sconst_0;
					sreturn;
		}

		.method public getMaxSize()S 8 {
			.stack 1;
			.locals 0;

				L0:	getfield_a_this 40;		// reference des/CyclicRecord.data
					arraylength;
					sreturn;
		}

		.method public eraseData()V 9 {
			.stack 3;
			.locals 1;

				L0:	sconst_0;
					sstore_1;
				L1:	sload_1;
					getfield_a_this 40;		// reference des/CyclicRecord.data
					arraylength;
					if_scmpge L3;
				L2:	getfield_a_this 40;		// reference des/CyclicRecord.data
					sload_1;
					sconst_0;
					bastore;
					sinc 1 1;
					goto L1;
				L3:	return;
		}

		.method public deleteRecord()V 10 {
			.stack 3;
			.locals 0;

				L0:	getfield_a_this 38;		// reference des/CyclicRecord.parentFile
					getfield_a 24;		// reference des/DirectoryFile.waitingForTransaction
					aload_0;
					invokevirtual 75;		// des/File.getFileID()B
					sconst_1;
					bastore;
					aload_0;
					sconst_1;
					putfield_b 44;		// boolean des/CyclicRecord.waitingToDeleteRecord
					return;
		}

		.method public deleteRecords()V 11 {
			.stack 2;
			.locals 0;

				L0:	aload_0;
					invokevirtual 194;		// des/CyclicRecord.eraseData()V
					aload_0;
					sconst_0;
					putfield_s 41;		// short des/CyclicRecord.size
					return;
		}

		.method public writeRecord([B)V 12 {
			.stack 4;
			.locals 1;

				L0:	aload_1;
					arraylength;
					getfield_s_this 23;		// short des/CyclicRecord.recordSize
					if_scmplt L2;
				L1:	sspush -28226;
					invokestatic 177;		// javacard/framework/ISOException.throwIt(S)V
				L2:	getfield_a_this 38;		// reference des/CyclicRecord.parentFile
					getfield_a 24;		// reference des/DirectoryFile.waitingForTransaction
					aload_0;
					invokevirtual 75;		// des/File.getFileID()B
					sconst_1;
					bastore;
					sconst_0;
					sstore_2;
				L3:	sload_2;
					getfield_s_this 23;		// short des/CyclicRecord.recordSize
					if_scmpge L7;
				L4:	getfield_a_this 43;		// reference des/CyclicRecord.uncommitedRecord
					sload_2;
					aload_1;
					sload_2;
					baload;
					bastore;
					sload_2;
					aload_1;
					arraylength;
					if_scmplt L6;
				L5:	getfield_a_this 43;		// reference des/CyclicRecord.uncommitedRecord
					sload_2;
					sconst_0;
					bastore;
				L6:	sinc 2 1;
					goto L3;
				L7:	return;
		}

		.method public writeRecord([BS)V 13 {
			.stack 4;
			.locals 1;

				L0:	aload_1;
					arraylength;
					sload_2;
					sadd;
					getfield_s_this 23;		// short des/CyclicRecord.recordSize
					if_scmplt L2;
				L1:	sspush -28226;
					invokestatic 177;		// javacard/framework/ISOException.throwIt(S)V
				L2:	getfield_a_this 38;		// reference des/CyclicRecord.parentFile
					getfield_a 24;		// reference des/DirectoryFile.waitingForTransaction
					aload_0;
					invokevirtual 75;		// des/File.getFileID()B
					sconst_1;
					bastore;
					sconst_0;
					sstore_3;
				L3:	sload_3;
					getfield_s_this 23;		// short des/CyclicRecord.recordSize
					if_scmpge L9;
				L4:	sload_3;
					sload_2;
					if_scmpge L6;
				L5:	getfield_a_this 43;		// reference des/CyclicRecord.uncommitedRecord
					sload_3;
					sconst_0;
					bastore;
				L6:	getfield_a_this 43;		// reference des/CyclicRecord.uncommitedRecord
					sload_3;
					aload_1;
					sload_3;
					baload;
					bastore;
					sload_3;
					aload_1;
					arraylength;
					if_scmplt L8;
				L7:	getfield_a_this 43;		// reference des/CyclicRecord.uncommitedRecord
					sload_3;
					sconst_0;
					bastore;
				L8:	sinc 3 1;
					goto L3;
				L9:	return;
		}

		.method public commitTransaction()V 14 {
			.stack 4;
			.locals 1;

				L0:	getfield_a_this 38;		// reference des/CyclicRecord.parentFile
					getfield_a 24;		// reference des/DirectoryFile.waitingForTransaction
					aload_0;
					invokevirtual 75;		// des/File.getFileID()B
					sconst_0;
					bastore;
					getfield_b_this 44;		// boolean des/CyclicRecord.waitingToDeleteRecord
					sconst_1;
					if_scmpne L5;
				L1:	aload_0;
					sconst_0;
					putfield_b 44;		// boolean des/CyclicRecord.waitingToDeleteRecord
					getfield_s_this 41;		// short des/CyclicRecord.size
					getfield_s_this 23;		// short des/CyclicRecord.recordSize
					smul;
					sstore_1;
				L2:	sload_1;
					getfield_s_this 41;		// short des/CyclicRecord.size
					sconst_1;
					sadd;
					getfield_s_this 23;		// short des/CyclicRecord.recordSize
					smul;
					if_scmpge L4;
				L3:	getfield_a_this 40;		// reference des/CyclicRecord.data
					sload_1;
					sconst_0;
					bastore;
					sinc 1 1;
					goto L2;
				L4:	aload_0;
					dup;
					getfield_s 41;		// short des/CyclicRecord.size
					sconst_1;
					ssub;
					putfield_s 41;		// short des/CyclicRecord.size
					goto L11;
				L5:	getfield_s_this 41;		// short des/CyclicRecord.size
					getfield_s_this 42;		// short des/CyclicRecord.maxSize
					if_scmpne L7;
				L6:	aload_0;
					sconst_0;
					putfield_s 41;		// short des/CyclicRecord.size
				L7:	getfield_s_this 41;		// short des/CyclicRecord.size
					getfield_s_this 23;		// short des/CyclicRecord.recordSize
					smul;
					sstore_1;
				L8:	sload_1;
					getfield_s_this 41;		// short des/CyclicRecord.size
					sconst_1;
					sadd;
					getfield_s_this 23;		// short des/CyclicRecord.recordSize
					smul;
					if_scmpge L10;
				L9:	getfield_a_this 40;		// reference des/CyclicRecord.data
					sload_1;
					getfield_a_this 43;		// reference des/CyclicRecord.uncommitedRecord
					sload_1;
					baload;
					bastore;
					sinc 1 1;
					goto L8;
				L10:	aload_0;
					dup;
					getfield_s 41;		// short des/CyclicRecord.size
					sconst_1;
					sadd;
					putfield_s 41;		// short des/CyclicRecord.size
				L11:	return;
		}

		.method public abortTransaction()V 15 {
			.stack 3;
			.locals 0;

				L0:	getfield_a_this 38;		// reference des/CyclicRecord.parentFile
					getfield_a 24;		// reference des/DirectoryFile.waitingForTransaction
					aload_0;
					invokevirtual 75;		// des/File.getFileID()B
					sconst_0;
					bastore;
					aload_0;
					sconst_0;
					putfield_b 44;		// boolean des/CyclicRecord.waitingToDeleteRecord
					return;
		}

		.method public readValue()[B 16 {
			.stack 6;
			.locals 2;

				L0:	getfield_s_this 23;		// short des/CyclicRecord.recordSize
					newarray 11;
					astore_1;
					sconst_0;
					sstore_2;
				L1:	sload_2;
					getfield_s_this 23;		// short des/CyclicRecord.recordSize
					if_scmpge L3;
				L2:	aload_1;
					sload_2;
					getfield_a_this 40;		// reference des/CyclicRecord.data
					sload_2;
					getfield_s_this 41;		// short des/CyclicRecord.size
					sconst_1;
					ssub;
					getfield_s_this 23;		// short des/CyclicRecord.recordSize
					smul;
					sadd;
					baload;
					bastore;
					sinc 2 1;
					goto L1;
				L3:	aload_1;
					areturn;
		}

		.method public readData(SSB)[B 17 {
			.stack 5;
			.locals 2;

				L0:	sload_2;
					newarray 11;
					astore 4;
					sconst_0;
					sstore 5;
				L1:	sload 5;
					sload_2;
					if_scmpge L3;
				L2:	aload 4;
					sload_3;
					sload 5;
					sadd;
					getfield_a_this 40;		// reference des/CyclicRecord.data
					sload_1;
					sload 5;
					sadd;
					baload;
					bastore;
					sinc 5 1;
					goto L1;
				L3:	aload 4;
					areturn;
		}

		.method public getPermissions()[B 18 {
			.stack 1;
			.locals 0;

				L0:	getfield_a_this 39;		// reference des/CyclicRecord.permissions
					areturn;
		}

		.method public getAccessRight(B)B 19 {
			.stack 3;
			.locals 0;

				L0:	getfield_a_this 39;		// reference des/CyclicRecord.permissions
					sconst_1;
					baload;
					bspush 15;
					sand;
					sload_1;
					if_scmpne L2;
				L1:	sconst_4;
					sreturn;
				L2:	getfield_a_this 39;		// reference des/CyclicRecord.permissions
					sconst_1;
					baload;
					bspush 15;
					sand;
					bspush 14;
					if_scmpne L4;
				L3:	sconst_4;
					sreturn;
				L4:	getfield_a_this 39;		// reference des/CyclicRecord.permissions
					sconst_1;
					baload;
					bspush -16;
					sand;
					sload_1;
					sconst_4;
					sshl;
					s2b;
					if_scmpne L6;
				L5:	sconst_3;
					sreturn;
				L6:	getfield_a_this 39;		// reference des/CyclicRecord.permissions
					sconst_1;
					baload;
					bspush -16;
					sand;
					bspush -32;
					if_scmpne L8;
				L7:	sconst_3;
					sreturn;
				L8:	getfield_a_this 39;		// reference des/CyclicRecord.permissions
					sconst_0;
					baload;
					bspush 15;
					sand;
					sload_1;
					if_scmpne L10;
				L9:	sconst_2;
					sreturn;
				L10:	getfield_a_this 39;		// reference des/CyclicRecord.permissions
					sconst_0;
					baload;
					bspush 15;
					sand;
					bspush 14;
					if_scmpne L12;
				L11:	sconst_2;
					sreturn;
				L12:	getfield_a_this 39;		// reference des/CyclicRecord.permissions
					sconst_0;
					baload;
					bspush -16;
					sand;
					sload_1;
					sconst_4;
					sshl;
					s2b;
					if_scmpne L14;
				L13:	sconst_1;
					sreturn;
				L14:	getfield_a_this 39;		// reference des/CyclicRecord.permissions
					sconst_0;
					baload;
					bspush -16;
					sand;
					bspush -32;
					if_scmpne L16;
				L15:	sconst_1;
					sreturn;
				L16:	sconst_0;
					sreturn;
		}

		.method public hasWriteAccess(B)Z 20 {
			.stack 3;
			.locals 0;

				L0:	getfield_a_this 39;		// reference des/CyclicRecord.permissions
					sconst_0;
					baload;
					bspush 15;
					sand;
					sload_1;
					if_scmpne L2;
				L1:	sconst_1;
					sreturn;
				L2:	getfield_a_this 39;		// reference des/CyclicRecord.permissions
					sconst_0;
					baload;
					bspush 15;
					sand;
					bspush 14;
					if_scmpne L4;
				L3:	sconst_1;
					sreturn;
				L4:	getfield_a_this 39;		// reference des/CyclicRecord.permissions
					sconst_1;
					baload;
					bspush -16;
					sand;
					sload_1;
					sconst_4;
					sshl;
					s2b;
					if_scmpne L6;
				L5:	sconst_1;
					sreturn;
				L6:	getfield_a_this 39;		// reference des/CyclicRecord.permissions
					sconst_1;
					baload;
					bspush -16;
					sand;
					bspush -32;
					if_scmpne L8;
				L7:	sconst_1;
					sreturn;
				L8:	sconst_0;
					sreturn;
		}

		.method public hasReadAccess(B)Z 21 {
			.stack 3;
			.locals 0;

				L0:	getfield_a_this 39;		// reference des/CyclicRecord.permissions
					sconst_0;
					baload;
					bspush -16;
					sand;
					sload_1;
					sconst_4;
					sshl;
					s2b;
					if_scmpne L2;
				L1:	sconst_1;
					sreturn;
				L2:	getfield_a_this 39;		// reference des/CyclicRecord.permissions
					sconst_0;
					baload;
					bspush -16;
					sand;
					bspush -32;
					if_scmpne L4;
				L3:	sconst_1;
					sreturn;
				L4:	getfield_a_this 39;		// reference des/CyclicRecord.permissions
					sconst_1;
					baload;
					bspush -16;
					sand;
					sload_1;
					sconst_4;
					sshl;
					s2b;
					if_scmpne L6;
				L5:	sconst_1;
					sreturn;
				L6:	getfield_a_this 39;		// reference des/CyclicRecord.permissions
					sconst_1;
					baload;
					bspush -16;
					sand;
					bspush -32;
					if_scmpne L8;
				L7:	sconst_1;
					sreturn;
				L8:	sconst_0;
					sreturn;
		}

	}

	.class public IndexFile 4 extends File {

		.fields {
			private DirectoryFile parentFile 0;		// Ldes/DirectoryFile;
			private byte[] data 1;		// [B
			private byte[] permissions 2;		// [B
			 short size 3;		// S
			 short recordSize 4;		// S
		}

		.publicMethodTable 5 {
			equals(Ljava/lang/Object;)Z;
			getFileID()B;
			setActive(Z)V;
			getSize()B;
			setSize(B)V;
			getParent()Ldes/DirectoryFile;;
			getData()[B;
			getCurrentSize()S;
			getMaxSize()S;
			eraseData(S)V;
			deleteRecord(S)V;
			writeRecord(S[B)V;
			readValue(S)[B;
			getPermissions()[B;
			getAccessRight(B)B;
			hasWriteAccess(B)Z;
			hasReadAccess(B)Z;
		}

		.packageMethodTable 0 {
		}

		.method public <init>(BLdes/DirectoryFile;[B[B)V 0 {
			.stack 2;
			.locals 0;

				L0:	aload_0;
					sload_1;
					invokespecial 169;		// des/File.<init>(B)V
					aload_0;
					aload_2;
					putfield_a 45;		// reference des/IndexFile.parentFile
					aload_2;
					aload_0;
					invokevirtual 193;		// des/DirectoryFile.addFile(Ldes/File;)V
					aload_0;
					aload_3;
					putfield_a 46;		// reference des/IndexFile.permissions
					aload_0;
					aload 4;
					putfield_a 47;		// reference des/IndexFile.data
					aload_0;
					aload 4;
					arraylength;
					putfield_s 48;		// short des/IndexFile.size
					return;
		}

		.method public <init>(BLdes/DirectoryFile;[BSS)V 1 {
			.stack 3;
			.locals 0;

				L0:	aload_0;
					sload_1;
					invokespecial 169;		// des/File.<init>(B)V
					aload_0;
					aload_2;
					putfield_a 45;		// reference des/IndexFile.parentFile
					getfield_a_this 45;		// reference des/IndexFile.parentFile
					aload_0;
					invokevirtual 193;		// des/DirectoryFile.addFile(Ldes/File;)V
					aload_0;
					aload_3;
					putfield_a 46;		// reference des/IndexFile.permissions
					aload_0;
					sload 5;
					sload 4;
					smul;
					newarray 11;
					putfield_a 47;		// reference des/IndexFile.data
					aload_0;
					sconst_0;
					putfield_s 48;		// short des/IndexFile.size
					aload_0;
					sload 4;
					putfield_s 49;		// short des/IndexFile.recordSize
					return;
		}

		.method public getParent()Ldes/DirectoryFile; 5 {
			.stack 1;
			.locals 0;

				L0:	getfield_a_this 45;		// reference des/IndexFile.parentFile
					areturn;
		}

		.method public getData()[B 6 {
			.stack 2;
			.locals 0;

				L0:	getfield_b_this 0;		// boolean des/File.active
					sconst_1;
					if_scmpne L2;
				L1:	getfield_a_this 47;		// reference des/IndexFile.data
					areturn;
				L2:	sspush 27010;
					invokestatic 177;		// javacard/framework/ISOException.throwIt(S)V
					aconst_null;
					areturn;
		}

		.method public getCurrentSize()S 7 {
			.stack 2;
			.locals 0;

				L0:	getfield_b_this 0;		// boolean des/File.active
					sconst_1;
					if_scmpne L2;
				L1:	getfield_s_this 48;		// short des/IndexFile.size
					sreturn;
				L2:	sspush 27010;
					invokestatic 177;		// javacard/framework/ISOException.throwIt(S)V
					sconst_0;
					sreturn;
		}

		.method public getMaxSize()S 8 {
			.stack 1;
			.locals 0;

				L0:	getfield_a_this 47;		// reference des/IndexFile.data
					arraylength;
					sreturn;
		}

		.method public eraseData(S)V 9 {
			.stack 3;
			.locals 1;

				L0:	sconst_0;
					sstore_2;
				L1:	sload_2;
					getfield_a_this 47;		// reference des/IndexFile.data
					arraylength;
					if_scmpge L3;
				L2:	getfield_a_this 47;		// reference des/IndexFile.data
					sload_2;
					sconst_0;
					bastore;
					sinc 2 1;
					goto L1;
				L3:	return;
		}

		.method public deleteRecord(S)V 10 {
			.stack 3;
			.locals 1;

				L0:	sload_1;
					getfield_s_this 49;		// short des/IndexFile.recordSize
					smul;
					sstore_2;
				L1:	sload_2;
					sload_1;
					sconst_1;
					sadd;
					getfield_s_this 49;		// short des/IndexFile.recordSize
					smul;
					if_scmpge L3;
				L2:	getfield_a_this 47;		// reference des/IndexFile.data
					sload_2;
					sconst_0;
					bastore;
					sinc 2 1;
					goto L1;
				L3:	aload_0;
					dup;
					getfield_s 48;		// short des/IndexFile.size
					sconst_1;
					ssub;
					putfield_s 48;		// short des/IndexFile.size
					return;
		}

		.method public writeRecord(S[B)V 11 {
			.stack 6;
			.locals 1;

				L0:	aload_2;
					arraylength;
					getfield_s_this 49;		// short des/IndexFile.recordSize
					if_scmpeq L2;
				L1:	sspush -17663;
					invokestatic 177;		// javacard/framework/ISOException.throwIt(S)V
				L2:	aload_0;
					dup;
					getfield_s 48;		// short des/IndexFile.size
					sconst_1;
					sadd;
					putfield_s 48;		// short des/IndexFile.size
					sload_1;
					getfield_s_this 49;		// short des/IndexFile.recordSize
					smul;
					sstore_3;
				L3:	sload_3;
					sload_1;
					sconst_1;
					sadd;
					getfield_s_this 49;		// short des/IndexFile.recordSize
					smul;
					if_scmpge L5;
				L4:	getfield_a_this 47;		// reference des/IndexFile.data
					sload_3;
					aload_2;
					sload_3;
					sload_1;
					getfield_s_this 49;		// short des/IndexFile.recordSize
					smul;
					ssub;
					baload;
					bastore;
					sinc 3 1;
					goto L3;
				L5:	return;
		}

		.method public readValue(S)[B 12 {
			.stack 6;
			.locals 2;

				L0:	getfield_s_this 49;		// short des/IndexFile.recordSize
					newarray 11;
					astore_2;
					sconst_0;
					sstore_3;
				L1:	sload_3;
					getfield_s_this 49;		// short des/IndexFile.recordSize
					if_scmpge L3;
				L2:	aload_2;
					sload_3;
					getfield_a_this 47;		// reference des/IndexFile.data
					sload_3;
					sload_1;
					getfield_s_this 49;		// short des/IndexFile.recordSize
					smul;
					sadd;
					baload;
					bastore;
					sinc 3 1;
					goto L1;
				L3:	aload_2;
					areturn;
		}

		.method public getPermissions()[B 13 {
			.stack 1;
			.locals 0;

				L0:	getfield_a_this 46;		// reference des/IndexFile.permissions
					areturn;
		}

		.method public getAccessRight(B)B 14 {
			.stack 3;
			.locals 0;

				L0:	getfield_a_this 46;		// reference des/IndexFile.permissions
					sconst_1;
					baload;
					bspush 15;
					sand;
					sload_1;
					if_scmpne L2;
				L1:	sconst_4;
					sreturn;
				L2:	getfield_a_this 46;		// reference des/IndexFile.permissions
					sconst_1;
					baload;
					bspush 15;
					sand;
					bspush 14;
					if_scmpne L4;
				L3:	sconst_4;
					sreturn;
				L4:	getfield_a_this 46;		// reference des/IndexFile.permissions
					sconst_1;
					baload;
					bspush -16;
					sand;
					sload_1;
					sconst_4;
					sshl;
					s2b;
					if_scmpne L6;
				L5:	sconst_3;
					sreturn;
				L6:	getfield_a_this 46;		// reference des/IndexFile.permissions
					sconst_1;
					baload;
					bspush -16;
					sand;
					bspush -32;
					if_scmpne L8;
				L7:	sconst_3;
					sreturn;
				L8:	getfield_a_this 46;		// reference des/IndexFile.permissions
					sconst_0;
					baload;
					bspush 15;
					sand;
					sload_1;
					if_scmpne L10;
				L9:	sconst_2;
					sreturn;
				L10:	getfield_a_this 46;		// reference des/IndexFile.permissions
					sconst_0;
					baload;
					bspush 15;
					sand;
					bspush 14;
					if_scmpne L12;
				L11:	sconst_2;
					sreturn;
				L12:	getfield_a_this 46;		// reference des/IndexFile.permissions
					sconst_0;
					baload;
					bspush -16;
					sand;
					sload_1;
					sconst_4;
					sshl;
					s2b;
					if_scmpne L14;
				L13:	sconst_1;
					sreturn;
				L14:	getfield_a_this 46;		// reference des/IndexFile.permissions
					sconst_0;
					baload;
					bspush -16;
					sand;
					bspush -32;
					if_scmpne L16;
				L15:	sconst_1;
					sreturn;
				L16:	sconst_0;
					sreturn;
		}

		.method public hasWriteAccess(B)Z 15 {
			.stack 3;
			.locals 0;

				L0:	getfield_a_this 46;		// reference des/IndexFile.permissions
					sconst_0;
					baload;
					bspush 15;
					sand;
					sload_1;
					if_scmpne L2;
				L1:	sconst_1;
					sreturn;
				L2:	getfield_a_this 46;		// reference des/IndexFile.permissions
					sconst_0;
					baload;
					bspush 15;
					sand;
					bspush 14;
					if_scmpne L4;
				L3:	sconst_1;
					sreturn;
				L4:	getfield_a_this 46;		// reference des/IndexFile.permissions
					sconst_1;
					baload;
					bspush -16;
					sand;
					sload_1;
					sconst_4;
					sshl;
					s2b;
					if_scmpne L6;
				L5:	sconst_1;
					sreturn;
				L6:	getfield_a_this 46;		// reference des/IndexFile.permissions
					sconst_1;
					baload;
					bspush -16;
					sand;
					bspush -32;
					if_scmpne L8;
				L7:	sconst_1;
					sreturn;
				L8:	sconst_0;
					sreturn;
		}

		.method public hasReadAccess(B)Z 16 {
			.stack 3;
			.locals 0;

				L0:	getfield_a_this 46;		// reference des/IndexFile.permissions
					sconst_0;
					baload;
					bspush -16;
					sand;
					sload_1;
					sconst_4;
					sshl;
					s2b;
					if_scmpne L2;
				L1:	sconst_1;
					sreturn;
				L2:	getfield_a_this 46;		// reference des/IndexFile.permissions
					sconst_0;
					baload;
					bspush -16;
					sand;
					bspush -32;
					if_scmpne L4;
				L3:	sconst_1;
					sreturn;
				L4:	getfield_a_this 46;		// reference des/IndexFile.permissions
					sconst_1;
					baload;
					bspush -16;
					sand;
					sload_1;
					sconst_4;
					sshl;
					s2b;
					if_scmpne L6;
				L5:	sconst_1;
					sreturn;
				L6:	getfield_a_this 46;		// reference des/IndexFile.permissions
					sconst_1;
					baload;
					bspush -16;
					sand;
					bspush -32;
					if_scmpne L8;
				L7:	sconst_1;
					sreturn;
				L8:	sconst_0;
					sreturn;
		}

	}

	.class public LinearRecord 5 extends File {

		.fields {
			private DirectoryFile parentFile 0;		// Ldes/DirectoryFile;
			private byte[] data 1;		// [B
			 byte[] uncommitedRecord 2;		// [B
			private byte[] permissions 3;		// [B
			 short size 4;		// S
			 short maxSize 5;		// S
			 short recordSize 6;		// S
			 boolean waitingToDeleteRecord 7;		// Z
		}

		.publicMethodTable 5 {
			equals(Ljava/lang/Object;)Z;
			getFileID()B;
			setActive(Z)V;
			getSize()B;
			setSize(B)V;
			getParent()Ldes/DirectoryFile;;
			getData()[B;
			getCurrentSize()S;
			getMaxSize()S;
			eraseData()V;
			deleteRecord()V;
			deleteRecords()V;
			writeRecord([B)V;
			writeRecord([BS)V;
			commitTransaction()V;
			abortTransaction()V;
			readValue()[B;
			readData(SSB)[B;
			getPermissions()[B;
			getAccessRight(B)B;
			hasWriteAccess(B)Z;
			hasReadAccess(B)Z;
		}

		.packageMethodTable 0 {
		}

		.method public <init>(BLdes/DirectoryFile;[BSS)V 0 {
			.stack 3;
			.locals 0;

				L0:	aload_0;
					sload_1;
					sconst_3;
					invokespecial 185;		// des/File.<init>(BB)V
					aload_0;
					aload_2;
					putfield_a 50;		// reference des/LinearRecord.parentFile
					aload_0;
					aload_3;
					putfield_a 51;		// reference des/LinearRecord.permissions
					aload_0;
					sload 5;
					sload 4;
					smul;
					newarray 11;
					putfield_a 52;		// reference des/LinearRecord.data
					aload_0;
					sconst_0;
					putfield_s 53;		// short des/LinearRecord.size
					aload_0;
					sload 4;
					putfield_s 22;		// short des/LinearRecord.recordSize
					aload_0;
					sload 5;
					putfield_s 54;		// short des/LinearRecord.maxSize
					aload_0;
					sload 4;
					newarray 11;
					putfield_a 55;		// reference des/LinearRecord.uncommitedRecord
					aload_0;
					sconst_0;
					putfield_b 56;		// boolean des/LinearRecord.waitingToDeleteRecord
					aload_2;
					aload_0;
					invokevirtual 193;		// des/DirectoryFile.addFile(Ldes/File;)V
					return;
		}

		.method public getParent()Ldes/DirectoryFile; 5 {
			.stack 1;
			.locals 0;

				L0:	getfield_a_this 50;		// reference des/LinearRecord.parentFile
					areturn;
		}

		.method public getData()[B 6 {
			.stack 2;
			.locals 0;

				L0:	getfield_b_this 0;		// boolean des/File.active
					sconst_1;
					if_scmpne L2;
				L1:	getfield_a_this 52;		// reference des/LinearRecord.data
					areturn;
				L2:	sspush 27010;
					invokestatic 177;		// javacard/framework/ISOException.throwIt(S)V
					aconst_null;
					areturn;
		}

		.method public getCurrentSize()S 7 {
			.stack 2;
			.locals 0;

				L0:	getfield_b_this 0;		// boolean des/File.active
					sconst_1;
					if_scmpne L2;
				L1:	getfield_s_this 53;		// short des/LinearRecord.size
					sreturn;
				L2:	sspush 27010;
					invokestatic 177;		// javacard/framework/ISOException.throwIt(S)V
					sconst_0;
					sreturn;
		}

		.method public getMaxSize()S 8 {
			.stack 1;
			.locals 0;

				L0:	getfield_a_this 52;		// reference des/LinearRecord.data
					arraylength;
					sreturn;
		}

		.method public eraseData()V 9 {
			.stack 3;
			.locals 1;

				L0:	sconst_0;
					sstore_1;
				L1:	sload_1;
					getfield_a_this 52;		// reference des/LinearRecord.data
					arraylength;
					if_scmpge L3;
				L2:	getfield_a_this 52;		// reference des/LinearRecord.data
					sload_1;
					sconst_0;
					bastore;
					sinc 1 1;
					goto L1;
				L3:	return;
		}

		.method public deleteRecord()V 10 {
			.stack 3;
			.locals 0;

				L0:	getfield_a_this 50;		// reference des/LinearRecord.parentFile
					getfield_a 24;		// reference des/DirectoryFile.waitingForTransaction
					aload_0;
					invokevirtual 75;		// des/File.getFileID()B
					sconst_1;
					bastore;
					aload_0;
					sconst_1;
					putfield_b 56;		// boolean des/LinearRecord.waitingToDeleteRecord
					return;
		}

		.method public deleteRecords()V 11 {
			.stack 2;
			.locals 0;

				L0:	aload_0;
					invokevirtual 207;		// des/LinearRecord.eraseData()V
					aload_0;
					sconst_0;
					putfield_s 53;		// short des/LinearRecord.size
					return;
		}

		.method public writeRecord([B)V 12 {
			.stack 4;
			.locals 1;

				L0:	getfield_s_this 53;		// short des/LinearRecord.size
					getfield_s_this 54;		// short des/LinearRecord.maxSize
					if_scmpne L2;
				L1:	sspush -28226;
					invokestatic 177;		// javacard/framework/ISOException.throwIt(S)V
				L2:	aload_1;
					arraylength;
					getfield_s_this 22;		// short des/LinearRecord.recordSize
					if_scmplt L4;
				L3:	sspush -28226;
					invokestatic 177;		// javacard/framework/ISOException.throwIt(S)V
				L4:	getfield_b_this 56;		// boolean des/LinearRecord.waitingToDeleteRecord
					sconst_1;
					if_scmpne L6;
				L5:	sspush -28404;
					invokestatic 177;		// javacard/framework/ISOException.throwIt(S)V
				L6:	getfield_a_this 50;		// reference des/LinearRecord.parentFile
					getfield_a 24;		// reference des/DirectoryFile.waitingForTransaction
					aload_0;
					invokevirtual 75;		// des/File.getFileID()B
					sconst_1;
					bastore;
					sconst_0;
					sstore_2;
				L7:	sload_2;
					getfield_s_this 22;		// short des/LinearRecord.recordSize
					if_scmpge L11;
				L8:	getfield_a_this 55;		// reference des/LinearRecord.uncommitedRecord
					sload_2;
					aload_1;
					sload_2;
					baload;
					bastore;
					sload_2;
					aload_1;
					arraylength;
					if_scmplt L10;
				L9:	getfield_a_this 55;		// reference des/LinearRecord.uncommitedRecord
					sload_2;
					sconst_0;
					bastore;
				L10:	sinc 2 1;
					goto L7;
				L11:	return;
		}

		.method public writeRecord([BS)V 13 {
			.stack 4;
			.locals 1;

				L0:	getfield_s_this 53;		// short des/LinearRecord.size
					getfield_s_this 54;		// short des/LinearRecord.maxSize
					if_scmpne L2;
				L1:	sspush -28226;
					invokestatic 177;		// javacard/framework/ISOException.throwIt(S)V
				L2:	aload_1;
					arraylength;
					sload_2;
					sadd;
					getfield_s_this 22;		// short des/LinearRecord.recordSize
					if_scmplt L4;
				L3:	sspush -28226;
					invokestatic 177;		// javacard/framework/ISOException.throwIt(S)V
				L4:	getfield_b_this 56;		// boolean des/LinearRecord.waitingToDeleteRecord
					sconst_1;
					if_scmpne L6;
				L5:	sspush -28404;
					invokestatic 177;		// javacard/framework/ISOException.throwIt(S)V
				L6:	getfield_a_this 50;		// reference des/LinearRecord.parentFile
					getfield_a 24;		// reference des/DirectoryFile.waitingForTransaction
					aload_0;
					invokevirtual 75;		// des/File.getFileID()B
					sconst_1;
					bastore;
					sconst_0;
					sstore_3;
				L7:	sload_3;
					getfield_s_this 22;		// short des/LinearRecord.recordSize
					if_scmpge L13;
				L8:	sload_3;
					sload_2;
					if_scmpge L10;
				L9:	getfield_a_this 55;		// reference des/LinearRecord.uncommitedRecord
					sload_3;
					sconst_0;
					bastore;
				L10:	getfield_a_this 55;		// reference des/LinearRecord.uncommitedRecord
					sload_3;
					aload_1;
					sload_3;
					baload;
					bastore;
					sload_3;
					aload_1;
					arraylength;
					if_scmplt L12;
				L11:	getfield_a_this 55;		// reference des/LinearRecord.uncommitedRecord
					sload_3;
					sconst_0;
					bastore;
				L12:	sinc 3 1;
					goto L7;
				L13:	return;
		}

		.method public commitTransaction()V 14 {
			.stack 4;
			.locals 1;

				L0:	getfield_a_this 50;		// reference des/LinearRecord.parentFile
					getfield_a 24;		// reference des/DirectoryFile.waitingForTransaction
					aload_0;
					invokevirtual 75;		// des/File.getFileID()B
					sconst_0;
					bastore;
					getfield_b_this 56;		// boolean des/LinearRecord.waitingToDeleteRecord
					sconst_1;
					if_scmpne L5;
				L1:	aload_0;
					sconst_0;
					putfield_b 56;		// boolean des/LinearRecord.waitingToDeleteRecord
					getfield_s_this 53;		// short des/LinearRecord.size
					getfield_s_this 22;		// short des/LinearRecord.recordSize
					smul;
					sstore_1;
				L2:	sload_1;
					getfield_s_this 53;		// short des/LinearRecord.size
					sconst_1;
					sadd;
					getfield_s_this 22;		// short des/LinearRecord.recordSize
					smul;
					if_scmpge L4;
				L3:	getfield_a_this 52;		// reference des/LinearRecord.data
					sload_1;
					sconst_0;
					bastore;
					sinc 1 1;
					goto L2;
				L4:	aload_0;
					dup;
					getfield_s 53;		// short des/LinearRecord.size
					sconst_1;
					ssub;
					putfield_s 53;		// short des/LinearRecord.size
					goto L9;
				L5:	getfield_s_this 53;		// short des/LinearRecord.size
					getfield_s_this 22;		// short des/LinearRecord.recordSize
					smul;
					sstore_1;
				L6:	sload_1;
					getfield_s_this 53;		// short des/LinearRecord.size
					sconst_1;
					sadd;
					getfield_s_this 22;		// short des/LinearRecord.recordSize
					smul;
					if_scmpge L8;
				L7:	getfield_a_this 52;		// reference des/LinearRecord.data
					sload_1;
					getfield_a_this 55;		// reference des/LinearRecord.uncommitedRecord
					sload_1;
					baload;
					bastore;
					sinc 1 1;
					goto L6;
				L8:	aload_0;
					dup;
					getfield_s 53;		// short des/LinearRecord.size
					sconst_1;
					sadd;
					putfield_s 53;		// short des/LinearRecord.size
				L9:	return;
		}

		.method public abortTransaction()V 15 {
			.stack 3;
			.locals 0;

				L0:	getfield_a_this 50;		// reference des/LinearRecord.parentFile
					getfield_a 24;		// reference des/DirectoryFile.waitingForTransaction
					aload_0;
					invokevirtual 75;		// des/File.getFileID()B
					sconst_0;
					bastore;
					aload_0;
					sconst_0;
					putfield_b 56;		// boolean des/LinearRecord.waitingToDeleteRecord
					return;
		}

		.method public readValue()[B 16 {
			.stack 6;
			.locals 2;

				L0:	getfield_s_this 22;		// short des/LinearRecord.recordSize
					newarray 11;
					astore_1;
					sconst_0;
					sstore_2;
				L1:	sload_2;
					getfield_s_this 22;		// short des/LinearRecord.recordSize
					if_scmpge L3;
				L2:	aload_1;
					sload_2;
					getfield_a_this 52;		// reference des/LinearRecord.data
					sload_2;
					getfield_s_this 53;		// short des/LinearRecord.size
					sconst_1;
					ssub;
					getfield_s_this 22;		// short des/LinearRecord.recordSize
					smul;
					sadd;
					baload;
					bastore;
					sinc 2 1;
					goto L1;
				L3:	aload_1;
					areturn;
		}

		.method public readData(SSB)[B 17 {
			.stack 5;
			.locals 2;

				L0:	sload_2;
					newarray 11;
					astore 4;
					sconst_0;
					sstore 5;
				L1:	sload 5;
					sload_2;
					if_scmpge L3;
				L2:	aload 4;
					sload_3;
					sload 5;
					sadd;
					getfield_a_this 52;		// reference des/LinearRecord.data
					sload_1;
					sload 5;
					sadd;
					baload;
					bastore;
					sinc 5 1;
					goto L1;
				L3:	aload 4;
					areturn;
		}

		.method public getPermissions()[B 18 {
			.stack 1;
			.locals 0;

				L0:	getfield_a_this 51;		// reference des/LinearRecord.permissions
					areturn;
		}

		.method public getAccessRight(B)B 19 {
			.stack 3;
			.locals 0;

				L0:	getfield_a_this 51;		// reference des/LinearRecord.permissions
					sconst_1;
					baload;
					bspush 15;
					sand;
					sload_1;
					if_scmpne L2;
				L1:	sconst_4;
					sreturn;
				L2:	getfield_a_this 51;		// reference des/LinearRecord.permissions
					sconst_1;
					baload;
					bspush 15;
					sand;
					bspush 14;
					if_scmpne L4;
				L3:	sconst_4;
					sreturn;
				L4:	getfield_a_this 51;		// reference des/LinearRecord.permissions
					sconst_1;
					baload;
					bspush -16;
					sand;
					sload_1;
					sconst_4;
					sshl;
					s2b;
					if_scmpne L6;
				L5:	sconst_3;
					sreturn;
				L6:	getfield_a_this 51;		// reference des/LinearRecord.permissions
					sconst_1;
					baload;
					bspush -16;
					sand;
					bspush -32;
					if_scmpne L8;
				L7:	sconst_3;
					sreturn;
				L8:	getfield_a_this 51;		// reference des/LinearRecord.permissions
					sconst_0;
					baload;
					bspush 15;
					sand;
					sload_1;
					if_scmpne L10;
				L9:	sconst_2;
					sreturn;
				L10:	getfield_a_this 51;		// reference des/LinearRecord.permissions
					sconst_0;
					baload;
					bspush 15;
					sand;
					bspush 14;
					if_scmpne L12;
				L11:	sconst_2;
					sreturn;
				L12:	getfield_a_this 51;		// reference des/LinearRecord.permissions
					sconst_0;
					baload;
					bspush -16;
					sand;
					sload_1;
					sconst_4;
					sshl;
					s2b;
					if_scmpne L14;
				L13:	sconst_1;
					sreturn;
				L14:	getfield_a_this 51;		// reference des/LinearRecord.permissions
					sconst_0;
					baload;
					bspush -16;
					sand;
					bspush -32;
					if_scmpne L16;
				L15:	sconst_1;
					sreturn;
				L16:	sconst_0;
					sreturn;
		}

		.method public hasWriteAccess(B)Z 20 {
			.stack 3;
			.locals 0;

				L0:	getfield_a_this 51;		// reference des/LinearRecord.permissions
					sconst_0;
					baload;
					bspush 15;
					sand;
					sload_1;
					if_scmpne L2;
				L1:	sconst_1;
					sreturn;
				L2:	getfield_a_this 51;		// reference des/LinearRecord.permissions
					sconst_0;
					baload;
					bspush 15;
					sand;
					bspush 14;
					if_scmpne L4;
				L3:	sconst_1;
					sreturn;
				L4:	getfield_a_this 51;		// reference des/LinearRecord.permissions
					sconst_1;
					baload;
					bspush -16;
					sand;
					sload_1;
					sconst_4;
					sshl;
					s2b;
					if_scmpne L6;
				L5:	sconst_1;
					sreturn;
				L6:	getfield_a_this 51;		// reference des/LinearRecord.permissions
					sconst_1;
					baload;
					bspush -16;
					sand;
					bspush -32;
					if_scmpne L8;
				L7:	sconst_1;
					sreturn;
				L8:	sconst_0;
					sreturn;
		}

		.method public hasReadAccess(B)Z 21 {
			.stack 3;
			.locals 0;

				L0:	getfield_a_this 51;		// reference des/LinearRecord.permissions
					sconst_0;
					baload;
					bspush -16;
					sand;
					sload_1;
					sconst_4;
					sshl;
					s2b;
					if_scmpne L2;
				L1:	sconst_1;
					sreturn;
				L2:	getfield_a_this 51;		// reference des/LinearRecord.permissions
					sconst_0;
					baload;
					bspush -16;
					sand;
					bspush -32;
					if_scmpne L4;
				L3:	sconst_1;
					sreturn;
				L4:	getfield_a_this 51;		// reference des/LinearRecord.permissions
					sconst_1;
					baload;
					bspush -16;
					sand;
					sload_1;
					sconst_4;
					sshl;
					s2b;
					if_scmpne L6;
				L5:	sconst_1;
					sreturn;
				L6:	getfield_a_this 51;		// reference des/LinearRecord.permissions
					sconst_1;
					baload;
					bspush -16;
					sand;
					bspush -32;
					if_scmpne L8;
				L7:	sconst_1;
					sreturn;
				L8:	sconst_0;
					sreturn;
		}

	}

	.class public MasterFile 6 extends DirectoryFile {

		.fields {
			 IndexFile indexDF 0;		// Ldes/IndexFile;
			 DirectoryFile[] arrayDF 1;		// [Ldes/DirectoryFile;
			private boolean formatEnabled 2;		// Z
			private boolean randomID 3;		// Z
			 byte numApp 4;		// B
			private static final byte MF_FID = 0;		// B
		}

		.publicMethodTable 22 {
			equals(Ljava/lang/Object;)Z;
			getFileID()B;
			setActive(Z)V;
			getSize()B;
			setSize(B)V;
			setAID([B)V;
			getNumberFiles()B;
			getFile(B)Ldes/File;;
			updateFile(Ldes/File;B)V;
			addFile(Ldes/File;)V;
			deleteFile(B)V;
			getKey(B)Ljavacard/security/Key;;
			getMasterKey()Ljavacard/security/Key;;
			changeKey(B[B)V;
			getMasterKeyType()B;
			hasChangeAccess(BB)Z;
			hasKeySettingsChangeAllowed(B)Z;
			changeKeySettings(B)V;
			hasGetRights(B)Z;
			hasManageRights(B)Z;
			getKeySettings()B;
			getKeyNumber()B;
			isMasterFile()Z;
			isValidKeyNumber(B)Z;
			addDF([B[B)B;
			deleteDF([B)V;
			searchAID([B)B;
			getAID(B)[B;
			getIndexDF()Ldes/IndexFile;;
			setConfiguration(B)V;
			isFormatEnabled()Z;
			isRandomID()Z;
			format()V;
		}

		.packageMethodTable 0 {
		}

		.method public <init>()V 0 {
			.stack 8;
			.locals 1;

				L0:	aload_0;
					sconst_0;
					invokespecial 208;		// des/DirectoryFile.<init>(B)V
					aload_0;
					sconst_1;
					putfield_b 57;		// boolean des/MasterFile.formatEnabled
					aload_0;
					sconst_0;
					putfield_b 58;		// boolean des/MasterFile.randomID
					aload_0;
					sconst_1;
					putfield_b 17;		// byte des/MasterFile.numApp
					aload_0;
					new 211;		// des/IndexFile
					dup;
					sconst_0;
					aload_0;
					getfield_a_this 26;		// reference des/DirectoryFile.permissions
					sconst_3;
					bspush 28;
					invokespecial 212;		// des/IndexFile.<init>(BLdes/DirectoryFile;[BSS)V
					putfield_a 59;		// reference des/MasterFile.indexDF
					sconst_3;
					newarray 11;
					dup;
					sconst_0;
					bspush -12;
					bastore;
					dup;
					sconst_1;
					sconst_1;
					bastore;
					dup;
					sconst_2;
					bspush 16;
					bastore;
					astore_1;
					getfield_a_this 59;		// reference des/MasterFile.indexDF
					sconst_0;
					aload_1;
					invokevirtual 214;		// des/IndexFile.writeRecord(S[B)V
					aload_0;
					bspush 28;
					anewarray 215;		// des/DirectoryFile
					putfield_a 16;		// reference des/MasterFile.arrayDF
					return;
		}

		.method public addDF([B[B)B 24 {
			.stack 6;
			.locals 0;

				L0:	aload_0;
					aload_1;
					invokevirtual 84;		// des/MasterFile.searchAID([B)B
					sconst_m1;
					if_scmpeq L2;
				L1:	sspush -28194;
					invokestatic 177;		// javacard/framework/ISOException.throwIt(S)V
				L2:	getfield_b_this 17;		// byte des/MasterFile.numApp
					bspush 27;
					if_scmpne L4;
				L3:	sspush -28210;
					invokestatic 177;		// javacard/framework/ISOException.throwIt(S)V
				L4:	getfield_a_this 59;		// reference des/MasterFile.indexDF
					getfield_b_this 17;		// byte des/MasterFile.numApp
					aload_1;
					invokevirtual 214;		// des/IndexFile.writeRecord(S[B)V
					getfield_a_this 16;		// reference des/MasterFile.arrayDF
					getfield_b_this 17;		// byte des/MasterFile.numApp
					new 215;		// des/DirectoryFile
					dup;
					getfield_b_this 17;		// byte des/MasterFile.numApp
					aload_2;
					invokespecial 216;		// des/DirectoryFile.<init>(B[B)V
					aastore;
					aload_0;
					dup;
					getfield_b 17;		// byte des/MasterFile.numApp
					sconst_1;
					sadd;
					s2b;
					putfield_b 17;		// byte des/MasterFile.numApp
					getfield_b_this 17;		// byte des/MasterFile.numApp
					sconst_1;
					ssub;
					s2b;
					sreturn;
		}

		.method public deleteDF([B)V 25 {
			.stack 3;
			.locals 1;

				L0:	aload_0;
					aload_1;
					invokevirtual 84;		// des/MasterFile.searchAID([B)B
					sstore_2;
					getfield_a_this 16;		// reference des/MasterFile.arrayDF
					sload_2;
					aconst_null;
					aastore;
					aload_0;
					dup;
					getfield_b 17;		// byte des/MasterFile.numApp
					sconst_1;
					ssub;
					s2b;
					putfield_b 17;		// byte des/MasterFile.numApp
					getfield_a_this 59;		// reference des/MasterFile.indexDF
					sload_2;
					invokevirtual 217;		// des/IndexFile.deleteRecord(S)V
					return;
		}

		.method public searchAID([B)B 26 {
			.stack 5;
			.locals 1;

				L0:	sconst_0;
					sstore_2;
				L1:	sload_2;
					getfield_a_this 59;		// reference des/MasterFile.indexDF
					getfield_s 48;		// short des/IndexFile.size
					if_scmpge L5;
				L2:	aload_1;
					sconst_0;
					getfield_a_this 59;		// reference des/MasterFile.indexDF
					sload_2;
					invokevirtual 218;		// des/IndexFile.readValue(S)[B
					sconst_0;
					sconst_3;
					invokestatic 238;		// javacard/framework/Util.arrayCompare([BS[BSS)B
					ifne L4;
				L3:	sload_2;
					sreturn;
				L4:	sload_2;
					sconst_1;
					sadd;
					s2b;
					sstore_2;
					goto L1;
				L5:	sconst_m1;
					sreturn;
		}

		.method public getAID(B)[B 27 {
			.stack 2;
			.locals 0;

				L0:	getfield_a_this 59;		// reference des/MasterFile.indexDF
					sload_1;
					invokevirtual 218;		// des/IndexFile.readValue(S)[B
					areturn;
		}

		.method public getIndexDF()Ldes/IndexFile; 28 {
			.stack 1;
			.locals 0;

				L0:	getfield_a_this 59;		// reference des/MasterFile.indexDF
					areturn;
		}

		.method public setConfiguration(B)V 29 {
			.stack 2;
			.locals 0;

				L0:	sload_1;
					sconst_1;
					sand;
					sconst_1;
					if_scmpne L2;
				L1:	aload_0;
					sconst_0;
					putfield_b 57;		// boolean des/MasterFile.formatEnabled
					goto L3;
				L2:	aload_0;
					sconst_1;
					putfield_b 57;		// boolean des/MasterFile.formatEnabled
				L3:	sload_1;
					sconst_2;
					sand;
					sconst_2;
					if_scmpne L5;
				L4:	aload_0;
					sconst_0;
					putfield_b 58;		// boolean des/MasterFile.randomID
					goto L6;
				L5:	aload_0;
					sconst_1;
					putfield_b 58;		// boolean des/MasterFile.randomID
				L6:	return;
		}

		.method public isValidKeyNumber(B)Z 23 {
			.stack 1;
			.locals 0;

				L0:	sload_1;
					ifne L2;
				L1:	sconst_1;
					sreturn;
				L2:	sconst_0;
					sreturn;
		}

		.method public isMasterFile()Z 22 {
			.stack 1;
			.locals 0;

				L0:	sconst_1;
					sreturn;
		}

		.method public isFormatEnabled()Z 30 {
			.stack 2;
			.locals 0;

				L0:	getfield_b_this 57;		// boolean des/MasterFile.formatEnabled
					sconst_1;
					if_scmpne L2;
				L1:	sconst_1;
					goto L3;
				L2:	sconst_0;
				L3:	sreturn;
		}

		.method public isRandomID()Z 31 {
			.stack 2;
			.locals 0;

				L0:	getfield_b_this 58;		// boolean des/MasterFile.randomID
					sconst_1;
					if_scmpne L2;
				L1:	sconst_1;
					goto L3;
				L2:	sconst_0;
				L3:	sreturn;
		}

		.method public format()V 32 {
			.stack 3;
			.locals 1;

				L0:	sconst_0;
					sstore_1;
				L1:	sload_1;
					getfield_a_this 16;		// reference des/MasterFile.arrayDF
					arraylength;
					if_scmpge L5;
				L2:	getfield_a_this 16;		// reference des/MasterFile.arrayDF
					sload_1;
					aaload;
					ifnull L4;
				L3:	aload_0;
					aload_0;
					sload_1;
					invokevirtual 88;		// des/MasterFile.getAID(B)[B
					invokevirtual 85;		// des/MasterFile.deleteDF([B)V
				L4:	sload_1;
					sconst_1;
					sadd;
					s2b;
					sstore_1;
					goto L1;
				L5:	return;
		}

	}

	.class public StandartFile 7 extends File {

		.fields {
			private DirectoryFile parentFile 0;		// Ldes/DirectoryFile;
			private byte[] data 1;		// [B
			private byte[] permissions 2;		// [B
		}

		.publicMethodTable 1 {
			equals(Ljava/lang/Object;)Z;
			getFileID()B;
			setActive(Z)V;
			getSize()B;
			setSize(B)V;
			getParent()Ldes/DirectoryFile;;
			getData()[B;
			getMaxSize()S;
			getPermissions()[B;
			readArray(SSB)[B;
			writeArray([BSS)V;
			getAccessRight(B)B;
			hasWriteAccess(B)Z;
			hasReadAccess(B)Z;
		}

		.packageMethodTable 0 {
		}

		.method public <init>(BLdes/DirectoryFile;[B[B)V 0 {
			.stack 3;
			.locals 0;

				L0:	aload_0;
					sload_1;
					sconst_0;
					invokespecial 185;		// des/File.<init>(BB)V
					aload_0;
					aload_2;
					putfield_a 60;		// reference des/StandartFile.parentFile
					aload_0;
					aload_3;
					putfield_a 61;		// reference des/StandartFile.permissions
					aload_0;
					aload 4;
					putfield_a 62;		// reference des/StandartFile.data
					aload_0;
					aload 4;
					arraylength;
					s2b;
					invokevirtual 222;		// des/File.setSize(B)V
					aload_2;
					aload_0;
					invokevirtual 193;		// des/DirectoryFile.addFile(Ldes/File;)V
					return;
		}

		.method public <init>(BLdes/DirectoryFile;[BS)V 1 {
			.stack 3;
			.locals 0;

				L0:	aload_0;
					sload_1;
					sconst_0;
					invokespecial 185;		// des/File.<init>(BB)V
					aload_0;
					aload_2;
					putfield_a 60;		// reference des/StandartFile.parentFile
					aload_0;
					aload_3;
					putfield_a 61;		// reference des/StandartFile.permissions
					aload_0;
					sload 4;
					newarray 11;
					putfield_a 62;		// reference des/StandartFile.data
					aload_0;
					sconst_0;
					invokevirtual 222;		// des/File.setSize(B)V
					aload_2;
					aload_0;
					invokevirtual 193;		// des/DirectoryFile.addFile(Ldes/File;)V
					return;
		}

		.method public getParent()Ldes/DirectoryFile; 5 {
			.stack 1;
			.locals 0;

				L0:	getfield_a_this 60;		// reference des/StandartFile.parentFile
					areturn;
		}

		.method public getFileID()B 1 {
			.stack 1;
			.locals 0;

				L0:	aload_0;
					invokespecial 223;		// des/StandartFile.getFileID()B
					sreturn;
		}

		.method public getData()[B 6 {
			.stack 2;
			.locals 0;

				L0:	getfield_b_this 0;		// boolean des/File.active
					sconst_1;
					if_scmpne L2;
				L1:	getfield_a_this 62;		// reference des/StandartFile.data
					areturn;
				L2:	sspush 27010;
					invokestatic 177;		// javacard/framework/ISOException.throwIt(S)V
					aconst_null;
					areturn;
		}

		.method public getMaxSize()S 7 {
			.stack 1;
			.locals 0;

				L0:	getfield_a_this 62;		// reference des/StandartFile.data
					arraylength;
					sreturn;
		}

		.method public getPermissions()[B 8 {
			.stack 1;
			.locals 0;

				L0:	getfield_a_this 61;		// reference des/StandartFile.permissions
					areturn;
		}

		.method public readArray(SSB)[B 9 {
			.stack 5;
			.locals 2;

				L0:	sload_2;
					newarray 11;
					astore 4;
					sconst_0;
					sstore 5;
				L1:	sload 5;
					sload_2;
					if_scmpge L3;
				L2:	aload 4;
					sload_3;
					sload 5;
					sadd;
					getfield_a_this 62;		// reference des/StandartFile.data
					sload_1;
					sload 5;
					sadd;
					baload;
					bastore;
					sinc 5 1;
					goto L1;
				L3:	aload 4;
					areturn;
		}

		.method public writeArray([BSS)V 10 {
			.stack 4;
			.locals 1;

				L0:	sconst_0;
					sstore 4;
				L1:	sload 4;
					sload_3;
					if_scmpge L3;
				L2:	getfield_a_this 62;		// reference des/StandartFile.data
					sload_2;
					sload 4;
					sadd;
					aload_1;
					sload 4;
					baload;
					bastore;
					sinc 4 1;
					goto L1;
				L3:	aload_0;
					aload_0;
					invokevirtual 117;		// des/File.getSize()B
					sload_2;
					sload_3;
					sadd;
					invokestatic 224;		// des/Util.max(SS)S
					s2b;
					invokevirtual 222;		// des/File.setSize(B)V
					return;
		}

		.method public getAccessRight(B)B 11 {
			.stack 3;
			.locals 0;

				L0:	getfield_a_this 61;		// reference des/StandartFile.permissions
					sconst_1;
					baload;
					bspush 15;
					sand;
					sload_1;
					if_scmpne L2;
				L1:	sconst_4;
					sreturn;
				L2:	getfield_a_this 61;		// reference des/StandartFile.permissions
					sconst_1;
					baload;
					bspush 15;
					sand;
					bspush 14;
					if_scmpne L4;
				L3:	sconst_4;
					sreturn;
				L4:	getfield_a_this 61;		// reference des/StandartFile.permissions
					sconst_1;
					baload;
					bspush -16;
					sand;
					sload_1;
					sconst_4;
					sshl;
					s2b;
					if_scmpne L6;
				L5:	sconst_3;
					sreturn;
				L6:	getfield_a_this 61;		// reference des/StandartFile.permissions
					sconst_1;
					baload;
					bspush -16;
					sand;
					bspush -32;
					if_scmpne L8;
				L7:	sconst_3;
					sreturn;
				L8:	getfield_a_this 61;		// reference des/StandartFile.permissions
					sconst_0;
					baload;
					bspush 15;
					sand;
					sload_1;
					if_scmpne L10;
				L9:	sconst_2;
					sreturn;
				L10:	getfield_a_this 61;		// reference des/StandartFile.permissions
					sconst_0;
					baload;
					bspush 15;
					sand;
					bspush 14;
					if_scmpne L12;
				L11:	sconst_2;
					sreturn;
				L12:	getfield_a_this 61;		// reference des/StandartFile.permissions
					sconst_0;
					baload;
					bspush -16;
					sand;
					sload_1;
					sconst_4;
					sshl;
					s2b;
					if_scmpne L14;
				L13:	sconst_1;
					sreturn;
				L14:	getfield_a_this 61;		// reference des/StandartFile.permissions
					sconst_0;
					baload;
					bspush -16;
					sand;
					bspush -32;
					if_scmpne L16;
				L15:	sconst_1;
					sreturn;
				L16:	sconst_0;
					sreturn;
		}

		.method public hasWriteAccess(B)Z 12 {
			.stack 3;
			.locals 0;

				L0:	getfield_a_this 61;		// reference des/StandartFile.permissions
					sconst_0;
					baload;
					bspush 15;
					sand;
					sload_1;
					if_scmpne L2;
				L1:	sconst_1;
					sreturn;
				L2:	getfield_a_this 61;		// reference des/StandartFile.permissions
					sconst_0;
					baload;
					bspush 15;
					sand;
					bspush 14;
					if_scmpne L4;
				L3:	sconst_1;
					sreturn;
				L4:	getfield_a_this 61;		// reference des/StandartFile.permissions
					sconst_1;
					baload;
					bspush -16;
					sand;
					sload_1;
					sconst_4;
					sshl;
					s2b;
					if_scmpne L6;
				L5:	sconst_1;
					sreturn;
				L6:	getfield_a_this 61;		// reference des/StandartFile.permissions
					sconst_1;
					baload;
					bspush -16;
					sand;
					bspush -32;
					if_scmpne L8;
				L7:	sconst_1;
					sreturn;
				L8:	sconst_0;
					sreturn;
		}

		.method public hasReadAccess(B)Z 13 {
			.stack 3;
			.locals 0;

				L0:	getfield_a_this 61;		// reference des/StandartFile.permissions
					sconst_0;
					baload;
					bspush -16;
					sand;
					sload_1;
					sconst_4;
					sshl;
					s2b;
					if_scmpne L2;
				L1:	sconst_1;
					sreturn;
				L2:	getfield_a_this 61;		// reference des/StandartFile.permissions
					sconst_0;
					baload;
					bspush -16;
					sand;
					bspush -32;
					if_scmpne L4;
				L3:	sconst_1;
					sreturn;
				L4:	getfield_a_this 61;		// reference des/StandartFile.permissions
					sconst_1;
					baload;
					bspush -16;
					sand;
					sload_1;
					sconst_4;
					sshl;
					s2b;
					if_scmpne L6;
				L5:	sconst_1;
					sreturn;
				L6:	getfield_a_this 61;		// reference des/StandartFile.permissions
					sconst_1;
					baload;
					bspush -16;
					sand;
					bspush -32;
					if_scmpne L8;
				L7:	sconst_1;
					sreturn;
				L8:	sconst_0;
					sreturn;
		}

	}

	.class public Util 8 extends 0.0 {		// extends java/lang/Object

		.fields {
			public static final byte AUTHENTICATE = 10;		// B
			public static final byte AUTHENTICATE_ISO = 26;		// B
			public static final byte AUTHENTICATE_AES = -86;		// B
			public static final byte CHANGE_KEY_SETTINGS = 84;		// B
			public static final byte SET_CONFIGURATION = 92;		// B
			public static final byte CHANGE_KEY = -60;		// B
			public static final byte GET_KEY_VERSION = 100;		// B
			public static final byte CREATE_APPLICATION = -54;		// B
			public static final byte DELETE_APPLICATION = -38;		// B
			public static final byte GET_APPLICATION_IDS = 106;		// B
			public static final byte FREE_MEMORY = 110;		// B
			public static final byte GET_DF_NAMES = 109;		// B
			public static final byte GET_KEY_SETTINGS = 69;		// B
			public static final byte SELECT_APPLICATION = 90;		// B
			public static final byte FORMAT_PICC = -4;		// B
			public static final byte GET_VERSION = 96;		// B
			public static final byte GET_CARD_UID = 81;		// B
			public static final byte GET_FILE_IDS = 111;		// B
			public static final byte GET_FILE_SETTINGS = -11;		// B
			public static final byte CHANGE_FILE_SETTINGS = 95;		// B
			public static final byte CREATE_STDDATAFILE = -51;		// B
			public static final byte CREATE_VALUE_FILE = -52;		// B
			public static final byte CREATE_LINEAR_RECORD_FILE = -63;		// B
			public static final byte CREATE_CYCLIC_RECORD_FILE = -64;		// B
			public static final byte DELETE_FILE = -33;		// B
			public static final byte GET_ISO_FILE_IDS = 97;		// B
			public static final byte READ_DATA = -115;		// B
			public static final byte WRITE_DATA = 61;		// B
			public static final byte GET_VALUE = 108;		// B
			public static final byte CREDIT = 12;		// B
			public static final byte DEBIT = -36;		// B
			public static final byte LIMITED_CREDIT = 28;		// B
			public static final byte WRITE_RECORD = 59;		// B
			public static final byte READ_RECORDS = -69;		// B
			public static final byte CLEAR_RECORD_FILE = -21;		// B
			public static final byte COMMIT_TRANSACTION = -57;		// B
			public static final byte ABORT_TRANSACTION = -89;		// B
			public static final byte CONTINUE = -81;		// B
			public static final byte NO_COMMAND_TO_CONTINUE = 0;		// B
			public static final byte NO_KEY_AUTHENTICATED = -1;		// B
			public static final short OPERATION_OK = -28416;		// S
			public static final short NO_CHANGES = -28404;		// S
			public static final short OUT_OF_EEPROM_ERROR = -28402;		// S
			public static final short ILLEGAL_COMMAND_CODE = -28388;		// S
			public static final short INTEGRITY_ERROR = -28386;		// S
			public static final short NO_SUCH_KEY = -28352;		// S
			public static final short LENGTH_ERROR = -28290;		// S
			public static final short PERMISSION_DENIED = -28259;		// S
			public static final short PARAMETER_ERROR = -28258;		// S
			public static final short APPLICATION_NOT_FOUND = -28256;		// S
			public static final short APPL_INTEGRITY_ERROR = -28255;		// S
			public static final short AUTHENTICATION_ERROR = -28242;		// S
			public static final short ADDITIONAL_FRAME = -28241;		// S
			public static final short BOUNDARY_ERROR = -28226;		// S
			public static final short PICC_INTEGRITY_ERROR = -28223;		// S
			public static final short COMMAND_ABORTED = -28214;		// S
			public static final short PICC_DISABLED_ERROR = -28211;		// S
			public static final short COUNT_ERROR = -28210;		// S
			public static final short DUPLICATE_ERROR = -28194;		// S
			public static final short EEPROM_ERROR = -28178;		// S
			public static final short FILE_NOT_FOUND = -28176;		// S
			public static final short FILE_INTEGRITY_ERROR = -28175;		// S
			public static final short WRONG_VALUE_ERROR = -28306;		// S
			public static final byte[] masterFileAID 0 = {0,0,0};		// [B
			public static final byte[] DEFAULT_MASTER_KEY 1 = {0,0,0,0,0,0,0,0,0,0,0,0,0,0,0,0};		// [B
			public static final byte[] RANDOM_A 2 = {-69,-52,-69,-52,-69,-52,-69,-52};		// [B
			public static final byte[] CHECKSUM_IV 3 = {0,0,0,0};		// [B
			static final byte TDES = 0;		// B
			static final byte TKTDES = 1;		// B
			static final byte AES = 2;		// B
			static final byte STANDARD_DATA_FILE = 0;		// B
			static final byte BACKUP_DATA_FILE = 1;		// B
			static final byte VALUE_FILE = 2;		// B
			static final byte LINEAR_RECORD_FILE = 3;		// B
			static final byte CYCLIC_RECORD_FILE = 4;		// B
			static final byte PLAIN_COMMUNICATION = 0;		// B
			static final byte PLAIN_COMMUNICATION_MAC = 1;		// B
			static final byte FULLY_ENCRYPTED = 2;		// B
		}

		.publicMethodTable 1 {
			equals(Ljava/lang/Object;)Z;
		}

		.packageMethodTable 0 {
		}

		.method public static final shortToByteArray(S)[B 0 {
			.stack 5;
			.locals 0;

				L0:	sconst_2;
					newarray 11;
					dup;
					sconst_0;
					sload_0;
					bspush 8;
					sushr;
					s2b;
					bastore;
					dup;
					sconst_1;
					sload_0;
					s2b;
					bastore;
					areturn;
		}

		.method public static final byteArrayToShort([B)S 1 {
			.stack 3;
			.locals 0;

				L0:	aload_0;
					sconst_0;
					baload;
					sspush 255;
					sand;
					bspush 8;
					sshl;
					aload_0;
					sconst_1;
					baload;
					sspush 255;
					sand;
					sadd;
					sreturn;
		}

		.method public static final valueByteArrayToShort([B)S 2 {
			.stack 3;
			.locals 0;

				L0:	aload_0;
					sconst_2;
					baload;
					sspush 255;
					sand;
					bspush 8;
					sshl;
					aload_0;
					sconst_3;
					baload;
					sspush 255;
					sand;
					sadd;
					sreturn;
		}

		.method public static final concatByteArray([B[B)[B 3 {
			.stack 4;
			.locals 2;

				L0:	aload_0;
					arraylength;
					aload_1;
					arraylength;
					sadd;
					newarray 11;
					astore_2;
					sconst_0;
					sstore_3;
				L1:	sload_3;
					aload_0;
					arraylength;
					if_scmpge L3;
				L2:	aload_2;
					sload_3;
					aload_0;
					sload_3;
					baload;
					bastore;
					sinc 3 1;
					goto L1;
				L3:	sconst_0;
					sstore_3;
				L4:	sload_3;
					aload_1;
					arraylength;
					if_scmpge L6;
				L5:	aload_2;
					sload_3;
					aload_0;
					arraylength;
					sadd;
					aload_1;
					sload_3;
					baload;
					bastore;
					sinc 3 1;
					goto L4;
				L6:	aload_2;
					areturn;
		}

		.method public <init>()V 4 {
			.stack 1;
			.locals 0;

				L0:	aload_0;
					invokespecial 86;		// java/lang/Object.<init>()V
					return;
		}

		.method public static rotateLeft([B)[B 5 {
			.stack 4;
			.locals 2;

				L0:	aload_0;
					arraylength;
					newarray 11;
					astore_1;
					aload_1;
					aload_0;
					arraylength;
					sconst_1;
					ssub;
					s2b;
					aload_0;
					sconst_0;
					baload;
					bastore;
					sconst_1;
					sstore_2;
				L1:	sload_2;
					aload_1;
					arraylength;
					if_scmpge L3;
				L2:	aload_1;
					sload_2;
					sconst_1;
					ssub;
					s2b;
					aload_0;
					sload_2;
					baload;
					bastore;
					sload_2;
					sconst_1;
					sadd;
					s2b;
					sstore_2;
					goto L1;
				L3:	aload_1;
					areturn;
		}

		.method public static rotateRight([B)[B 6 {
			.stack 5;
			.locals 2;

				L0:	aload_0;
					arraylength;
					newarray 11;
					astore_1;
					aload_1;
					sconst_0;
					aload_0;
					aload_0;
					arraylength;
					sconst_1;
					ssub;
					s2b;
					baload;
					bastore;
					sconst_1;
					sstore_2;
				L1:	sload_2;
					aload_1;
					arraylength;
					if_scmpge L3;
				L2:	aload_1;
					sload_2;
					aload_0;
					sload_2;
					sconst_1;
					ssub;
					s2b;
					baload;
					bastore;
					sload_2;
					sconst_1;
					sadd;
					s2b;
					sstore_2;
					goto L1;
				L3:	aload_1;
					areturn;
		}

		.method public static preparePaddedByteArray([B)[B 7 {
			.stack 4;
			.locals 2;

				L0:	aload_0;
					arraylength;
					bspush 8;
					srem;
					ifeq L5;
				L1:	aload_0;
					arraylength;
					bspush 8;
					aload_0;
					arraylength;
					bspush 8;
					srem;
					ssub;
					sadd;
					newarray 11;
					astore_1;
					sconst_0;
					sstore_2;
				L2:	sload_2;
					aload_0;
					arraylength;
					if_scmpge L4;
				L3:	aload_1;
					sload_2;
					aload_0;
					sload_2;
					baload;
					bastore;
					sinc 2 1;
					goto L2;
				L4:	aload_1;
					aload_0;
					arraylength;
					bspush -128;
					bastore;
					aload_1;
					areturn;
				L5:	aload_0;
					areturn;
		}

		.method public static removePadding([B)[B 8 {
			.stack 4;
			.locals 2;

				L0:	sconst_0;
					sstore_1;
					aload_0;
					arraylength;
					s2b;
					sstore_2;
				L1:	sload_1;
					ifne L3;
				L2:	sload_2;
					sconst_1;
					ssub;
					s2b;
					sstore_2;
					aload_0;
					sload_2;
					baload;
					sstore_1;
					goto L1;
				L3:	aload_0;
					sload_2;
					baload;
					bspush -128;
					if_scmpeq L5;
				L4:	aload_0;
					areturn;
				L5:	aload_0;
					sconst_0;
					sload_2;
					sconst_1;
					ssub;
					s2b;
					invokestatic 236;		// des/Util.subByteArray([BBB)[B
					areturn;
		}

		.method public static copyByteArray([BSS[BS)[B 9 {
			.stack 5;
			.locals 1;

				L0:	sload 4;
					sstore 5;
				L1:	sload 5;
					sload_2;
					sload 4;
					sadd;
					if_scmpge L3;
				L2:	aload_3;
					sload 5;
					aload_0;
					sload 5;
					sload_1;
					sadd;
					sload 4;
					ssub;
					baload;
					bastore;
					sinc 5 1;
					goto L1;
				L3:	aload_3;
					areturn;
		}

		.method public static create3DESSessionKey([B[B)[B 10 {
			.stack 4;
			.locals 1;

				L0:	bspush 16;
					newarray 11;
					astore_2;
					aload_2;
					sconst_0;
					aload_0;
					sconst_0;
					baload;
					bastore;
					aload_2;
					sconst_1;
					aload_0;
					sconst_1;
					baload;
					bastore;
					aload_2;
					sconst_2;
					aload_0;
					sconst_2;
					baload;
					bastore;
					aload_2;
					sconst_3;
					aload_0;
					sconst_3;
					baload;
					bastore;
					aload_2;
					sconst_4;
					aload_1;
					sconst_0;
					baload;
					bastore;
					aload_2;
					sconst_5;
					aload_1;
					sconst_1;
					baload;
					bastore;
					aload_2;
					bspush 6;
					aload_1;
					sconst_2;
					baload;
					bastore;
					aload_2;
					bspush 7;
					aload_1;
					sconst_3;
					baload;
					bastore;
					aload_2;
					bspush 8;
					aload_0;
					sconst_4;
					baload;
					bastore;
					aload_2;
					bspush 9;
					aload_0;
					sconst_5;
					baload;
					bastore;
					aload_2;
					bspush 10;
					aload_0;
					bspush 6;
					baload;
					bastore;
					aload_2;
					bspush 11;
					aload_0;
					bspush 7;
					baload;
					bastore;
					aload_2;
					bspush 12;
					aload_1;
					sconst_4;
					baload;
					bastore;
					aload_2;
					bspush 13;
					aload_1;
					sconst_5;
					baload;
					bastore;
					aload_2;
					bspush 14;
					aload_1;
					bspush 6;
					baload;
					bastore;
					aload_2;
					bspush 15;
					aload_1;
					bspush 7;
					baload;
					bastore;
					aload_2;
					areturn;
		}

		.method public static switchBytes([B)[B 11 {
			.stack 5;
			.locals 2;

				L0:	aload_0;
					arraylength;
					newarray 11;
					astore_1;
					sconst_0;
					sstore_2;
				L1:	sload_2;
					aload_1;
					arraylength;
					if_scmpge L3;
				L2:	aload_1;
					sload_2;
					aload_0;
					aload_1;
					arraylength;
					sload_2;
					ssub;
					sconst_1;
					ssub;
					s2b;
					baload;
					bastore;
					sload_2;
					sconst_1;
					sadd;
					s2b;
					sstore_2;
					goto L1;
				L3:	aload_1;
					areturn;
		}

		.method public static subByteArray([BBB)[B 12 {
			.stack 4;
			.locals 2;

				L0:	sload_2;
					sload_1;
					ssub;
					sconst_1;
					sadd;
					s2b;
					newarray 11;
					astore_3;
					sload_1;
					sstore 4;
				L1:	sload 4;
					sload_2;
					if_scmpgt L3;
				L2:	aload_3;
					sload 4;
					sload_1;
					ssub;
					s2b;
					aload_0;
					sload 4;
					baload;
					bastore;
					sload 4;
					sconst_1;
					sadd;
					s2b;
					sstore 4;
					goto L1;
				L3:	aload_3;
					areturn;
		}

		.method public static max(SS)S 13 {
			.stack 2;
			.locals 0;

				L0:	sload_0;
					sload_1;
					if_scmple L2;
				L1:	sload_0;
					sreturn;
				L2:	sload_0;
					sload_1;
					if_scmpge L4;
				L3:	sload_1;
					sreturn;
				L4:	sload_0;
					sreturn;
		}

		.method public static crc16([B)[B 14 {
			.stack 5;
			.locals 3;

				L0:	sconst_0;
					sstore_1;
					sspush 256;
					newarray 12;
					dup;
					sconst_0;
					sconst_0;
					sastore;
					dup;
					sconst_1;
					sspush -16191;
					sastore;
					dup;
					sconst_2;
					sspush -15999;
					sastore;
					dup;
					sconst_3;
					sspush 320;
					sastore;
					dup;
					sconst_4;
					sspush -15615;
					sastore;
					dup;
					sconst_5;
					sspush 960;
					sastore;
					dup;
					bspush 6;
					sspush 640;
					sastore;
					dup;
					bspush 7;
					sspush -15807;
					sastore;
					dup;
					bspush 8;
					sspush -14847;
					sastore;
					dup;
					bspush 9;
					sspush 1728;
					sastore;
					dup;
					bspush 10;
					sspush 1920;
					sastore;
					dup;
					bspush 11;
					sspush -14527;
					sastore;
					dup;
					bspush 12;
					sspush 1280;
					sastore;
					dup;
					bspush 13;
					sspush -14911;
					sastore;
					dup;
					bspush 14;
					sspush -15231;
					sastore;
					dup;
					bspush 15;
					sspush 1088;
					sastore;
					dup;
					bspush 16;
					sspush -13311;
					sastore;
					dup;
					bspush 17;
					sspush 3264;
					sastore;
					dup;
					bspush 18;
					sspush 3456;
					sastore;
					dup;
					bspush 19;
					sspush -12991;
					sastore;
					dup;
					bspush 20;
					sspush 3840;
					sastore;
					dup;
					bspush 21;
					sspush -12351;
					sastore;
					dup;
					bspush 22;
					sspush -12671;
					sastore;
					dup;
					bspush 23;
					sspush 3648;
					sastore;
					dup;
					bspush 24;
					sspush 2560;
					sastore;
					dup;
					bspush 25;
					sspush -13631;
					sastore;
					dup;
					bspush 26;
					sspush -13439;
					sastore;
					dup;
					bspush 27;
					sspush 2880;
					sastore;
					dup;
					bspush 28;
					sspush -14079;
					sastore;
					dup;
					bspush 29;
					sspush 2496;
					sastore;
					dup;
					bspush 30;
					sspush 2176;
					sastore;
					dup;
					bspush 31;
					sspush -14271;
					sastore;
					dup;
					bspush 32;
					sspush -10239;
					sastore;
					dup;
					bspush 33;
					sspush 6336;
					sastore;
					dup;
					bspush 34;
					sspush 6528;
					sastore;
					dup;
					bspush 35;
					sspush -9919;
					sastore;
					dup;
					bspush 36;
					sspush 6912;
					sastore;
					dup;
					bspush 37;
					sspush -9279;
					sastore;
					dup;
					bspush 38;
					sspush -9599;
					sastore;
					dup;
					bspush 39;
					sspush 6720;
					sastore;
					dup;
					bspush 40;
					sspush 7680;
					sastore;
					dup;
					bspush 41;
					sspush -8511;
					sastore;
					dup;
					bspush 42;
					sspush -8319;
					sastore;
					dup;
					bspush 43;
					sspush 8000;
					sastore;
					dup;
					bspush 44;
					sspush -8959;
					sastore;
					dup;
					bspush 45;
					sspush 7616;
					sastore;
					dup;
					bspush 46;
					sspush 7296;
					sastore;
					dup;
					bspush 47;
					sspush -9151;
					sastore;
					dup;
					bspush 48;
					sspush 5120;
					sastore;
					dup;
					bspush 49;
					sspush -11071;
					sastore;
					dup;
					bspush 50;
					sspush -10879;
					sastore;
					dup;
					bspush 51;
					sspush 5440;
					sastore;
					dup;
					bspush 52;
					sspush -10495;
					sastore;
					dup;
					bspush 53;
					sspush 6080;
					sastore;
					dup;
					bspush 54;
					sspush 5760;
					sastore;
					dup;
					bspush 55;
					sspush -10687;
					sastore;
					dup;
					bspush 56;
					sspush -11775;
					sastore;
					dup;
					bspush 57;
					sspush 4800;
					sastore;
					dup;
					bspush 58;
					sspush 4992;
					sastore;
					dup;
					bspush 59;
					sspush -11455;
					sastore;
					dup;
					bspush 60;
					sspush 4352;
					sastore;
					dup;
					bspush 61;
					sspush -11839;
					sastore;
					dup;
					bspush 62;
					sspush -12159;
					sastore;
					dup;
					bspush 63;
					sspush 4160;
					sastore;
					dup;
					bspush 64;
					sspush -4095;
					sastore;
					dup;
					bspush 65;
					sspush 12480;
					sastore;
					dup;
					bspush 66;
					sspush 12672;
					sastore;
					dup;
					bspush 67;
					sspush -3775;
					sastore;
					dup;
					bspush 68;
					sspush 13056;
					sastore;
					dup;
					bspush 69;
					sspush -3135;
					sastore;
					dup;
					bspush 70;
					sspush -3455;
					sastore;
					dup;
					bspush 71;
					sspush 12864;
					sastore;
					dup;
					bspush 72;
					sspush 13824;
					sastore;
					dup;
					bspush 73;
					sspush -2367;
					sastore;
					dup;
					bspush 74;
					sspush -2175;
					sastore;
					dup;
					bspush 75;
					sspush 14144;
					sastore;
					dup;
					bspush 76;
					sspush -2815;
					sastore;
					dup;
					bspush 77;
					sspush 13760;
					sastore;
					dup;
					bspush 78;
					sspush 13440;
					sastore;
					dup;
					bspush 79;
					sspush -3007;
					sastore;
					dup;
					bspush 80;
					sspush 15360;
					sastore;
					dup;
					bspush 81;
					sspush -831;
					sastore;
					dup;
					bspush 82;
					sspush -639;
					sastore;
					dup;
					bspush 83;
					sspush 15680;
					sastore;
					dup;
					bspush 84;
					sspush -255;
					sastore;
					dup;
					bspush 85;
					sspush 16320;
					sastore;
					dup;
					bspush 86;
					sspush 16000;
					sastore;
					dup;
					bspush 87;
					sspush -447;
					sastore;
					dup;
					bspush 88;
					sspush -1535;
					sastore;
					dup;
					bspush 89;
					sspush 15040;
					sastore;
					dup;
					bspush 90;
					sspush 15232;
					sastore;
					dup;
					bspush 91;
					sspush -1215;
					sastore;
					dup;
					bspush 92;
					sspush 14592;
					sastore;
					dup;
					bspush 93;
					sspush -1599;
					sastore;
					dup;
					bspush 94;
					sspush -1919;
					sastore;
					dup;
					bspush 95;
					sspush 14400;
					sastore;
					dup;
					bspush 96;
					sspush 10240;
					sastore;
					dup;
					bspush 97;
					sspush -5951;
					sastore;
					dup;
					bspush 98;
					sspush -5759;
					sastore;
					dup;
					bspush 99;
					sspush 10560;
					sastore;
					dup;
					bspush 100;
					sspush -5375;
					sastore;
					dup;
					bspush 101;
					sspush 11200;
					sastore;
					dup;
					bspush 102;
					sspush 10880;
					sastore;
					dup;
					bspush 103;
					sspush -5567;
					sastore;
					dup;
					bspush 104;
					sspush -4607;
					sastore;
					dup;
					bspush 105;
					sspush 11968;
					sastore;
					dup;
					bspush 106;
					sspush 12160;
					sastore;
					dup;
					bspush 107;
					sspush -4287;
					sastore;
					dup;
					bspush 108;
					sspush 11520;
					sastore;
					dup;
					bspush 109;
					sspush -4671;
					sastore;
					dup;
					bspush 110;
					sspush -4991;
					sastore;
					dup;
					bspush 111;
					sspush 11328;
					sastore;
					dup;
					bspush 112;
					sspush -7167;
					sastore;
					dup;
					bspush 113;
					sspush 9408;
					sastore;
					dup;
					bspush 114;
					sspush 9600;
					sastore;
					dup;
					bspush 115;
					sspush -6847;
					sastore;
					dup;
					bspush 116;
					sspush 9984;
					sastore;
					dup;
					bspush 117;
					sspush -6207;
					sastore;
					dup;
					bspush 118;
					sspush -6527;
					sastore;
					dup;
					bspush 119;
					sspush 9792;
					sastore;
					dup;
					bspush 120;
					sspush 8704;
					sastore;
					dup;
					bspush 121;
					sspush -7487;
					sastore;
					dup;
					bspush 122;
					sspush -7295;
					sastore;
					dup;
					bspush 123;
					sspush 9024;
					sastore;
					dup;
					bspush 124;
					sspush -7935;
					sastore;
					dup;
					bspush 125;
					sspush 8640;
					sastore;
					dup;
					bspush 126;
					sspush 8320;
					sastore;
					dup;
					bspush 127;
					sspush -8127;
					sastore;
					dup;
					sspush 128;
					sspush -24575;
					sastore;
					dup;
					sspush 129;
					sspush 24768;
					sastore;
					dup;
					sspush 130;
					sspush 24960;
					sastore;
					dup;
					sspush 131;
					sspush -24255;
					sastore;
					dup;
					sspush 132;
					sspush 25344;
					sastore;
					dup;
					sspush 133;
					sspush -23615;
					sastore;
					dup;
					sspush 134;
					sspush -23935;
					sastore;
					dup;
					sspush 135;
					sspush 25152;
					sastore;
					dup;
					sspush 136;
					sspush 26112;
					sastore;
					dup;
					sspush 137;
					sspush -22847;
					sastore;
					dup;
					sspush 138;
					sspush -22655;
					sastore;
					dup;
					sspush 139;
					sspush 26432;
					sastore;
					dup;
					sspush 140;
					sspush -23295;
					sastore;
					dup;
					sspush 141;
					sspush 26048;
					sastore;
					dup;
					sspush 142;
					sspush 25728;
					sastore;
					dup;
					sspush 143;
					sspush -23487;
					sastore;
					dup;
					sspush 144;
					sspush 27648;
					sastore;
					dup;
					sspush 145;
					sspush -21311;
					sastore;
					dup;
					sspush 146;
					sspush -21119;
					sastore;
					dup;
					sspush 147;
					sspush 27968;
					sastore;
					dup;
					sspush 148;
					sspush -20735;
					sastore;
					dup;
					sspush 149;
					sspush 28608;
					sastore;
					dup;
					sspush 150;
					sspush 28288;
					sastore;
					dup;
					sspush 151;
					sspush -20927;
					sastore;
					dup;
					sspush 152;
					sspush -22015;
					sastore;
					dup;
					sspush 153;
					sspush 27328;
					sastore;
					dup;
					sspush 154;
					sspush 27520;
					sastore;
					dup;
					sspush 155;
					sspush -21695;
					sastore;
					dup;
					sspush 156;
					sspush 26880;
					sastore;
					dup;
					sspush 157;
					sspush -22079;
					sastore;
					dup;
					sspush 158;
					sspush -22399;
					sastore;
					dup;
					sspush 159;
					sspush 26688;
					sastore;
					dup;
					sspush 160;
					sspush 30720;
					sastore;
					dup;
					sspush 161;
					sspush -18239;
					sastore;
					dup;
					sspush 162;
					sspush -18047;
					sastore;
					dup;
					sspush 163;
					sspush 31040;
					sastore;
					dup;
					sspush 164;
					sspush -17663;
					sastore;
					dup;
					sspush 165;
					sspush 31680;
					sastore;
					dup;
					sspush 166;
					sspush 31360;
					sastore;
					dup;
					sspush 167;
					sspush -17855;
					sastore;
					dup;
					sspush 168;
					sspush -16895;
					sastore;
					dup;
					sspush 169;
					sspush 32448;
					sastore;
					dup;
					sspush 170;
					sspush 32640;
					sastore;
					dup;
					sspush 171;
					sspush -16575;
					sastore;
					dup;
					sspush 172;
					sspush 32000;
					sastore;
					dup;
					sspush 173;
					sspush -16959;
					sastore;
					dup;
					sspush 174;
					sspush -17279;
					sastore;
					dup;
					sspush 175;
					sspush 31808;
					sastore;
					dup;
					sspush 176;
					sspush -19455;
					sastore;
					dup;
					sspush 177;
					sspush 29888;
					sastore;
					dup;
					sspush 178;
					sspush 30080;
					sastore;
					dup;
					sspush 179;
					sspush -19135;
					sastore;
					dup;
					sspush 180;
					sspush 30464;
					sastore;
					dup;
					sspush 181;
					sspush -18495;
					sastore;
					dup;
					sspush 182;
					sspush -18815;
					sastore;
					dup;
					sspush 183;
					sspush 30272;
					sastore;
					dup;
					sspush 184;
					sspush 29184;
					sastore;
					dup;
					sspush 185;
					sspush -19775;
					sastore;
					dup;
					sspush 186;
					sspush -19583;
					sastore;
					dup;
					sspush 187;
					sspush 29504;
					sastore;
					dup;
					sspush 188;
					sspush -20223;
					sastore;
					dup;
					sspush 189;
					sspush 29120;
					sastore;
					dup;
					sspush 190;
					sspush 28800;
					sastore;
					dup;
					sspush 191;
					sspush -20415;
					sastore;
					dup;
					sspush 192;
					sspush 20480;
					sastore;
					dup;
					sspush 193;
					sspush -28479;
					sastore;
					dup;
					sspush 194;
					sspush -28287;
					sastore;
					dup;
					sspush 195;
					sspush 20800;
					sastore;
					dup;
					sspush 196;
					sspush -27903;
					sastore;
					dup;
					sspush 197;
					sspush 21440;
					sastore;
					dup;
					sspush 198;
					sspush 21120;
					sastore;
					dup;
					sspush 199;
					sspush -28095;
					sastore;
					dup;
					sspush 200;
					sspush -27135;
					sastore;
					dup;
					sspush 201;
					sspush 22208;
					sastore;
					dup;
					sspush 202;
					sspush 22400;
					sastore;
					dup;
					sspush 203;
					sspush -26815;
					sastore;
					dup;
					sspush 204;
					sspush 21760;
					sastore;
					dup;
					sspush 205;
					sspush -27199;
					sastore;
					dup;
					sspush 206;
					sspush -27519;
					sastore;
					dup;
					sspush 207;
					sspush 21568;
					sastore;
					dup;
					sspush 208;
					sspush -25599;
					sastore;
					dup;
					sspush 209;
					sspush 23744;
					sastore;
					dup;
					sspush 210;
					sspush 23936;
					sastore;
					dup;
					sspush 211;
					sspush -25279;
					sastore;
					dup;
					sspush 212;
					sspush 24320;
					sastore;
					dup;
					sspush 213;
					sspush -24639;
					sastore;
					dup;
					sspush 214;
					sspush -24959;
					sastore;
					dup;
					sspush 215;
					sspush 24128;
					sastore;
					dup;
					sspush 216;
					sspush 23040;
					sastore;
					dup;
					sspush 217;
					sspush -25919;
					sastore;
					dup;
					sspush 218;
					sspush -25727;
					sastore;
					dup;
					sspush 219;
					sspush 23360;
					sastore;
					dup;
					sspush 220;
					sspush -26367;
					sastore;
					dup;
					sspush 221;
					sspush 22976;
					sastore;
					dup;
					sspush 222;
					sspush 22656;
					sastore;
					dup;
					sspush 223;
					sspush -26559;
					sastore;
					dup;
					sspush 224;
					sspush -30719;
					sastore;
					dup;
					sspush 225;
					sspush 18624;
					sastore;
					dup;
					sspush 226;
					sspush 18816;
					sastore;
					dup;
					sspush 227;
					sspush -30399;
					sastore;
					dup;
					sspush 228;
					sspush 19200;
					sastore;
					dup;
					sspush 229;
					sspush -29759;
					sastore;
					dup;
					sspush 230;
					sspush -30079;
					sastore;
					dup;
					sspush 231;
					sspush 19008;
					sastore;
					dup;
					sspush 232;
					sspush 19968;
					sastore;
					dup;
					sspush 233;
					sspush -28991;
					sastore;
					dup;
					sspush 234;
					sspush -28799;
					sastore;
					dup;
					sspush 235;
					sspush 20288;
					sastore;
					dup;
					sspush 236;
					sspush -29439;
					sastore;
					dup;
					sspush 237;
					sspush 19904;
					sastore;
					dup;
					sspush 238;
					sspush 19584;
					sastore;
					dup;
					sspush 239;
					sspush -29631;
					sastore;
					dup;
					sspush 240;
					sspush 17408;
					sastore;
					dup;
					sspush 241;
					sspush -31551;
					sastore;
					dup;
					sspush 242;
					sspush -31359;
					sastore;
					dup;
					sspush 243;
					sspush 17728;
					sastore;
					dup;
					sspush 244;
					sspush -30975;
					sastore;
					dup;
					sspush 245;
					sspush 18368;
					sastore;
					dup;
					sspush 246;
					sspush 18048;
					sastore;
					dup;
					sspush 247;
					sspush -31167;
					sastore;
					dup;
					sspush 248;
					sspush -32255;
					sastore;
					dup;
					sspush 249;
					sspush 17088;
					sastore;
					dup;
					sspush 250;
					sspush 17280;
					sastore;
					dup;
					sspush 251;
					sspush -31935;
					sastore;
					dup;
					sspush 252;
					sspush 16640;
					sastore;
					dup;
					sspush 253;
					sspush -32319;
					sastore;
					dup;
					sspush 254;
					sspush -32639;
					sastore;
					dup;
					sspush 255;
					sspush 16448;
					sastore;
					astore_2;
					sconst_0;
					sstore_3;
				L1:	sload_3;
					aload_0;
					arraylength;
					if_scmpge L3;
				L2:	sload_1;
					bspush 8;
					sushr;
					aload_2;
					sload_1;
					aload_0;
					sload_3;
					baload;
					sxor;
					sspush 255;
					sand;
					saload;
					sxor;
					sstore_1;
					sinc 3 1;
					goto L1;
				L3:	sload_1;
					invokestatic 225;		// des/Util.shortToByteArray(S)[B
					areturn;
		}

		.method public static byteArrayCompare([B[B)Z 15 {
			.stack 3;
			.locals 1;

				L0:	aload_0;
					arraylength;
					aload_1;
					arraylength;
					if_scmpeq L2;
				L1:	sconst_0;
					sreturn;
				L2:	sconst_0;
					sstore_2;
				L3:	sload_2;
					aload_0;
					arraylength;
					if_scmpge L7;
				L4:	aload_0;
					sload_2;
					baload;
					aload_1;
					sload_2;
					baload;
					if_scmpeq L6;
				L5:	sconst_0;
					sreturn;
				L6:	sload_2;
					sconst_1;
					sadd;
					s2b;
					sstore_2;
					goto L3;
				L7:	sconst_1;
					sreturn;
		}

	}

	.class public Value 9 extends 0.0 {		// extends java/lang/Object

		.fields {
			private byte[] value 0;		// [B
		}

		.publicMethodTable 1 {
			equals(Ljava/lang/Object;)Z;
			getValue()[B;
			compareTo(Ldes/Value;)B;
			compareAbsoluteValueTo(Ldes/Value;)B;
			addValue(Ldes/Value;)Z;
			subtractValue(Ldes/Value;)Z;
			hasOverflowSum(BBB)Z;
		}

		.packageMethodTable 0 {
		}

		.method public <init>([B)V 0 {
			.stack 2;
			.locals 0;

				L0:	aload_0;
					invokespecial 86;		// java/lang/Object.<init>()V
					aload_1;
					arraylength;
					sconst_4;
					if_scmpeq L2;
				L1:	sspush -28306;
					invokestatic 177;		// javacard/framework/ISOException.throwIt(S)V
				L2:	aload_0;
					aload_1;
					putfield_a 63;		// reference des/Value.value
					return;
		}

		.method public getValue()[B 1 {
			.stack 1;
			.locals 0;

				L0:	getfield_a_this 63;		// reference des/Value.value
					areturn;
		}

		.method public compareTo(Ldes/Value;)B 2 {
			.stack 2;
			.locals 0;

				L0:	aload_0;
					aload_0;
					invokevirtual 123;		// des/Value.getValue()[B
					invokespecial 227;		// des/Value.isPositive([B)Z
					ifeq L4;
				L1:	aload_0;
					aload_1;
					invokevirtual 123;		// des/Value.getValue()[B
					invokespecial 227;		// des/Value.isPositive([B)Z
					ifne L3;
				L2:	sconst_1;
					sreturn;
				L3:	aload_0;
					aload_1;
					invokevirtual 228;		// des/Value.compareAbsoluteValueTo(Ldes/Value;)B
					sreturn;
				L4:	aload_0;
					aload_1;
					invokevirtual 123;		// des/Value.getValue()[B
					invokespecial 227;		// des/Value.isPositive([B)Z
					ifeq L6;
				L5:	sconst_2;
					sreturn;
				L6:	aload_0;
					aload_1;
					invokevirtual 228;		// des/Value.compareAbsoluteValueTo(Ldes/Value;)B
					sreturn;
		}

		.method public compareAbsoluteValueTo(Ldes/Value;)B 3 {
			.stack 2;
			.locals 3;

				L0:	sconst_0;
					sstore 4;
				L1:	sload 4;
					sconst_4;
					if_scmpge L7;
				L2:	aload_0;
					invokevirtual 123;		// des/Value.getValue()[B
					sload 4;
					baload;
					sstore_2;
					aload_1;
					invokevirtual 123;		// des/Value.getValue()[B
					sload 4;
					baload;
					sstore_3;
					sload_2;
					sload_3;
					if_scmple L4;
				L3:	sconst_1;
					sreturn;
				L4:	sload_2;
					sload_3;
					if_scmpge L6;
				L5:	sconst_2;
					sreturn;
				L6:	sload 4;
					sconst_1;
					sadd;
					s2b;
					sstore 4;
					goto L1;
				L7:	sconst_0;
					sreturn;
		}

		.method public addValue(Ldes/Value;)Z 4 {
			.stack 4;
			.locals 3;

				L0:	sconst_0;
					sstore_3;
					sconst_3;
					sstore 4;
				L1:	sload 4;
					iflt L6;
				L2:	aload_0;
					invokevirtual 123;		// des/Value.getValue()[B
					sload 4;
					baload;
					aload_1;
					invokevirtual 123;		// des/Value.getValue()[B
					sload 4;
					baload;
					sadd;
					s2b;
					sstore_2;
					sload_3;
					sconst_1;
					if_scmpne L4;
				L3:	aload_0;
					aload_0;
					invokevirtual 123;		// des/Value.getValue()[B
					sload 4;
					baload;
					aload_1;
					invokevirtual 123;		// des/Value.getValue()[B
					sload 4;
					baload;
					sload_2;
					invokevirtual 229;		// des/Value.hasOverflowSum(BBB)Z
					sstore_3;
					sload_2;
					sconst_1;
					sadd;
					s2b;
					sstore_2;
					getfield_a_this 63;		// reference des/Value.value
					sload 4;
					sload_2;
					bastore;
					goto L5;
				L4:	aload_0;
					aload_0;
					invokevirtual 123;		// des/Value.getValue()[B
					sload 4;
					baload;
					aload_1;
					invokevirtual 123;		// des/Value.getValue()[B
					sload 4;
					baload;
					sload_2;
					invokevirtual 229;		// des/Value.hasOverflowSum(BBB)Z
					sstore_3;
					getfield_a_this 63;		// reference des/Value.value
					sload 4;
					sload_2;
					bastore;
				L5:	sload 4;
					sconst_1;
					ssub;
					s2b;
					sstore 4;
					goto L1;
				L6:	sload_3;
					ifne L8;
				L7:	sconst_1;
					goto L9;
				L8:	sconst_0;
				L9:	sreturn;
		}

		.method public subtractValue(Ldes/Value;)Z 5 {
			.stack 7;
			.locals 2;

				L0:	sconst_4;
					newarray 11;
					astore_2;
					sconst_0;
					sstore_3;
				L1:	sload_3;
					sconst_4;
					if_scmpge L3;
				L2:	aload_2;
					sload_3;
					aload_1;
					invokevirtual 123;		// des/Value.getValue()[B
					sload_3;
					baload;
					sconst_m1;
					sxor;
					bastore;
					sload_3;
					sconst_1;
					sadd;
					s2b;
					sstore_3;
					goto L1;
				L3:	new 106;		// des/Value
					dup;
					aload_2;
					invokespecial 107;		// des/Value.<init>([B)V
					astore_3;
					aload_3;
					new 106;		// des/Value
					dup;
					sconst_4;
					newarray 11;
					dup;
					sconst_0;
					sconst_0;
					bastore;
					dup;
					sconst_1;
					sconst_0;
					bastore;
					dup;
					sconst_2;
					sconst_0;
					bastore;
					dup;
					sconst_3;
					sconst_1;
					bastore;
					invokespecial 107;		// des/Value.<init>([B)V
					invokevirtual 230;		// des/Value.addValue(Ldes/Value;)Z
					pop;
					aload_0;
					aload_3;
					invokevirtual 230;		// des/Value.addValue(Ldes/Value;)Z
					ifne L5;
				L4:	sconst_1;
					goto L6;
				L5:	sconst_0;
				L6:	sreturn;
		}

		.method public hasOverflowSum(BBB)Z 6 {
			.stack 2;
			.locals 0;

				L0:	aload_0;
					sload_1;
					invokespecial 231;		// des/Value.isPositive(B)Z
					ifeq L5;
				L1:	aload_0;
					sload_2;
					invokespecial 231;		// des/Value.isPositive(B)Z
					ifeq L5;
				L2:	aload_0;
					sload_3;
					invokespecial 231;		// des/Value.isPositive(B)Z
					ifeq L4;
				L3:	sconst_0;
					sreturn;
				L4:	sconst_1;
					sreturn;
				L5:	aload_0;
					sload_1;
					invokespecial 231;		// des/Value.isPositive(B)Z
					ifne L10;
				L6:	aload_0;
					sload_2;
					invokespecial 231;		// des/Value.isPositive(B)Z
					ifne L10;
				L7:	aload_0;
					sload_3;
					invokespecial 231;		// des/Value.isPositive(B)Z
					ifne L9;
				L8:	sconst_0;
					sreturn;
				L9:	sconst_1;
					sreturn;
				L10:	sconst_0;
					sreturn;
		}

		.method private isPositive([B)Z {
			.stack 2;
			.locals 0;

				L0:	aload_1;
					sconst_0;
					baload;
					bspush -128;
					sand;
					ifne L2;
				L1:	sconst_1;
					goto L3;
				L2:	sconst_0;
				L3:	sreturn;
		}

		.method private isPositive(B)Z {
			.stack 2;
			.locals 0;

				L0:	sload_1;
					bspush -128;
					sand;
					ifne L2;
				L1:	sconst_1;
					goto L3;
				L2:	sconst_0;
				L3:	sreturn;
		}

	}

	.class public ValueRecord 10 extends File {

		.fields {
			private DirectoryFile parentFile 0;		// Ldes/DirectoryFile;
			private Value value 1;		// Ldes/Value;
			private Value upperLimit 2;		// Ldes/Value;
			private Value lowerLimit 3;		// Ldes/Value;
			private byte[] permissions 4;		// [B
			 Value uncommitedValue 5;		// Ldes/Value;
			 boolean limitedCreditEnabled 6;		// Z
			 boolean freeGetValueEnabled 7;		// Z
		}

		.publicMethodTable 5 {
			equals(Ljava/lang/Object;)Z;
			getFileID()B;
			setActive(Z)V;
			getSize()B;
			setSize(B)V;
			getParent()Ldes/DirectoryFile;;
			getCurrentSize()S;
			getValue()Ldes/Value;;
			getLowerLimit()Ldes/Value;;
			getUpperLimit()Ldes/Value;;
			getPermissions()[B;
			valueOutBounds(Ldes/Value;)Z;
			addCredit(Ldes/Value;)V;
			decDebit(Ldes/Value;)V;
			commitTransaction()V;
			abortTransaction()V;
			getAccessRight(B)B;
			hasWriteAccess(B)Z;
			hasReadAccess(B)Z;
		}

		.packageMethodTable 0 {
		}

		.method public <init>(BLdes/DirectoryFile;[BLdes/Value;Ldes/Value;Ldes/Value;B)V 0 {
			.stack 3;
			.locals 0;

				L0:	aload_0;
					sload_1;
					sconst_2;
					invokespecial 185;		// des/File.<init>(BB)V
					aload_0;
					aload_2;
					putfield_a 64;		// reference des/ValueRecord.parentFile
					aload_0;
					aload_3;
					putfield_a 65;		// reference des/ValueRecord.permissions
					aload_0;
					aload 5;
					putfield_a 66;		// reference des/ValueRecord.upperLimit
					aload_0;
					aload 4;
					putfield_a 67;		// reference des/ValueRecord.lowerLimit
					aload_0;
					aload 6;
					putfield_a 68;		// reference des/ValueRecord.value
					sload 7;
					sconst_1;
					sand;
					sconst_1;
					if_scmpne L2;
				L1:	aload_0;
					sconst_1;
					putfield_b 69;		// boolean des/ValueRecord.limitedCreditEnabled
					goto L3;
				L2:	aload_0;
					sconst_0;
					putfield_b 69;		// boolean des/ValueRecord.limitedCreditEnabled
				L3:	sload 7;
					sconst_2;
					sand;
					sconst_2;
					if_scmpne L5;
				L4:	aload_0;
					sconst_1;
					putfield_b 70;		// boolean des/ValueRecord.freeGetValueEnabled
					goto L6;
				L5:	aload_0;
					sconst_0;
					putfield_b 70;		// boolean des/ValueRecord.freeGetValueEnabled
				L6:	aload_0;
					getfield_a_this 68;		// reference des/ValueRecord.value
					putfield_a 71;		// reference des/ValueRecord.uncommitedValue
					aload_2;
					aload_0;
					invokevirtual 193;		// des/DirectoryFile.addFile(Ldes/File;)V
					return;
		}

		.method public getParent()Ldes/DirectoryFile; 5 {
			.stack 1;
			.locals 0;

				L0:	getfield_a_this 64;		// reference des/ValueRecord.parentFile
					areturn;
		}

		.method public getCurrentSize()S 6 {
			.stack 2;
			.locals 0;

				L0:	getfield_b_this 0;		// boolean des/File.active
					sconst_1;
					if_scmpne L2;
				L1:	sconst_4;
					sreturn;
				L2:	sspush 27010;
					invokestatic 177;		// javacard/framework/ISOException.throwIt(S)V
					sconst_0;
					sreturn;
		}

		.method public getValue()Ldes/Value; 7 {
			.stack 2;
			.locals 0;

				L0:	getfield_b_this 0;		// boolean des/File.active
					sconst_1;
					if_scmpne L2;
				L1:	getfield_a_this 68;		// reference des/ValueRecord.value
					areturn;
				L2:	sspush 27010;
					invokestatic 177;		// javacard/framework/ISOException.throwIt(S)V
					aconst_null;
					areturn;
		}

		.method public getLowerLimit()Ldes/Value; 8 {
			.stack 1;
			.locals 0;

				L0:	getfield_a_this 67;		// reference des/ValueRecord.lowerLimit
					areturn;
		}

		.method public getUpperLimit()Ldes/Value; 9 {
			.stack 1;
			.locals 0;

				L0:	getfield_a_this 66;		// reference des/ValueRecord.upperLimit
					areturn;
		}

		.method public getPermissions()[B 10 {
			.stack 1;
			.locals 0;

				L0:	getfield_a_this 65;		// reference des/ValueRecord.permissions
					areturn;
		}

		.method public valueOutBounds(Ldes/Value;)Z 11 {
			.stack 2;
			.locals 0;

				L0:	aload_1;
					getfield_a_this 67;		// reference des/ValueRecord.lowerLimit
					invokevirtual 108;		// des/Value.compareTo(Ldes/Value;)B
					sconst_2;
					if_scmpne L2;
				L1:	sconst_1;
					sreturn;
				L2:	aload_1;
					getfield_a_this 66;		// reference des/ValueRecord.upperLimit
					invokevirtual 108;		// des/Value.compareTo(Ldes/Value;)B
					sconst_1;
					if_scmpne L4;
				L3:	sconst_1;
					sreturn;
				L4:	sconst_0;
					sreturn;
		}

		.method public addCredit(Ldes/Value;)V 12 {
			.stack 3;
			.locals 1;

				L0:	getfield_a_this 71;		// reference des/ValueRecord.uncommitedValue
					astore_2;
					aload_2;
					aload_1;
					invokevirtual 230;		// des/Value.addValue(Ldes/Value;)Z
					ifne L2;
				L1:	sspush -28226;
					invokestatic 177;		// javacard/framework/ISOException.throwIt(S)V
				L2:	aload_0;
					aload_2;
					invokevirtual 240;		// des/ValueRecord.valueOutBounds(Ldes/Value;)Z
					sconst_1;
					if_scmpne L4;
				L3:	sspush -28258;
					invokestatic 177;		// javacard/framework/ISOException.throwIt(S)V
				L4:	aload_0;
					aload_2;
					putfield_a 71;		// reference des/ValueRecord.uncommitedValue
					getfield_a_this 64;		// reference des/ValueRecord.parentFile
					getfield_a 24;		// reference des/DirectoryFile.waitingForTransaction
					aload_0;
					invokevirtual 75;		// des/File.getFileID()B
					sconst_1;
					bastore;
					return;
		}

		.method public decDebit(Ldes/Value;)V 13 {
			.stack 3;
			.locals 1;

				L0:	getfield_a_this 71;		// reference des/ValueRecord.uncommitedValue
					astore_2;
					aload_2;
					aload_1;
					invokevirtual 241;		// des/Value.subtractValue(Ldes/Value;)Z
					ifne L2;
				L1:	sspush -28258;
					invokestatic 177;		// javacard/framework/ISOException.throwIt(S)V
				L2:	aload_0;
					aload_2;
					invokevirtual 240;		// des/ValueRecord.valueOutBounds(Ldes/Value;)Z
					sconst_1;
					if_scmpne L4;
				L3:	sspush -28258;
					invokestatic 177;		// javacard/framework/ISOException.throwIt(S)V
				L4:	aload_0;
					aload_2;
					putfield_a 71;		// reference des/ValueRecord.uncommitedValue
					getfield_a_this 64;		// reference des/ValueRecord.parentFile
					getfield_a 24;		// reference des/DirectoryFile.waitingForTransaction
					aload_0;
					invokevirtual 75;		// des/File.getFileID()B
					sconst_1;
					bastore;
					return;
		}

		.method public commitTransaction()V 14 {
			.stack 3;
			.locals 0;

				L0:	getfield_a_this 64;		// reference des/ValueRecord.parentFile
					getfield_a 24;		// reference des/DirectoryFile.waitingForTransaction
					aload_0;
					invokevirtual 75;		// des/File.getFileID()B
					sconst_0;
					bastore;
					aload_0;
					getfield_a_this 71;		// reference des/ValueRecord.uncommitedValue
					putfield_a 68;		// reference des/ValueRecord.value
					return;
		}

		.method public abortTransaction()V 15 {
			.stack 3;
			.locals 0;

				L0:	getfield_a_this 64;		// reference des/ValueRecord.parentFile
					getfield_a 24;		// reference des/DirectoryFile.waitingForTransaction
					aload_0;
					invokevirtual 75;		// des/File.getFileID()B
					sconst_0;
					bastore;
					return;
		}

		.method public getAccessRight(B)B 16 {
			.stack 3;
			.locals 0;

				L0:	getfield_a_this 65;		// reference des/ValueRecord.permissions
					sconst_1;
					baload;
					bspush 15;
					sand;
					sload_1;
					if_scmpne L2;
				L1:	sconst_4;
					sreturn;
				L2:	getfield_a_this 65;		// reference des/ValueRecord.permissions
					sconst_1;
					baload;
					bspush 15;
					sand;
					bspush 14;
					if_scmpne L4;
				L3:	sconst_4;
					sreturn;
				L4:	getfield_a_this 65;		// reference des/ValueRecord.permissions
					sconst_1;
					baload;
					bspush -16;
					sand;
					sload_1;
					sconst_4;
					sshl;
					s2b;
					if_scmpne L6;
				L5:	sconst_3;
					sreturn;
				L6:	getfield_a_this 65;		// reference des/ValueRecord.permissions
					sconst_1;
					baload;
					bspush -16;
					sand;
					bspush -32;
					if_scmpne L8;
				L7:	sconst_3;
					sreturn;
				L8:	getfield_a_this 65;		// reference des/ValueRecord.permissions
					sconst_0;
					baload;
					bspush 15;
					sand;
					sload_1;
					if_scmpne L10;
				L9:	sconst_2;
					sreturn;
				L10:	getfield_a_this 65;		// reference des/ValueRecord.permissions
					sconst_0;
					baload;
					bspush 15;
					sand;
					bspush 14;
					if_scmpne L12;
				L11:	sconst_2;
					sreturn;
				L12:	getfield_a_this 65;		// reference des/ValueRecord.permissions
					sconst_0;
					baload;
					bspush -16;
					sand;
					sload_1;
					sconst_4;
					sshl;
					s2b;
					if_scmpne L14;
				L13:	sconst_1;
					sreturn;
				L14:	getfield_a_this 65;		// reference des/ValueRecord.permissions
					sconst_0;
					baload;
					bspush -16;
					sand;
					bspush -32;
					if_scmpne L16;
				L15:	sconst_1;
					sreturn;
				L16:	sconst_0;
					sreturn;
		}

		.method public hasWriteAccess(B)Z 17 {
			.stack 3;
			.locals 0;

				L0:	getfield_a_this 65;		// reference des/ValueRecord.permissions
					sconst_0;
					baload;
					bspush 15;
					sand;
					sload_1;
					if_scmpne L2;
				L1:	sconst_1;
					sreturn;
				L2:	getfield_a_this 65;		// reference des/ValueRecord.permissions
					sconst_0;
					baload;
					bspush 15;
					sand;
					bspush 14;
					if_scmpne L4;
				L3:	sconst_1;
					sreturn;
				L4:	getfield_a_this 65;		// reference des/ValueRecord.permissions
					sconst_1;
					baload;
					bspush -16;
					sand;
					sload_1;
					sconst_4;
					sshl;
					s2b;
					if_scmpne L6;
				L5:	sconst_1;
					sreturn;
				L6:	getfield_a_this 65;		// reference des/ValueRecord.permissions
					sconst_1;
					baload;
					bspush -16;
					sand;
					bspush -32;
					if_scmpne L8;
				L7:	sconst_1;
					sreturn;
				L8:	sconst_0;
					sreturn;
		}

		.method public hasReadAccess(B)Z 18 {
			.stack 3;
			.locals 0;

				L0:	getfield_a_this 65;		// reference des/ValueRecord.permissions
					sconst_0;
					baload;
					bspush -16;
					sand;
					sload_1;
					sconst_4;
					sshl;
					s2b;
					if_scmpne L2;
				L1:	sconst_1;
					sreturn;
				L2:	getfield_a_this 65;		// reference des/ValueRecord.permissions
					sconst_0;
					baload;
					bspush -16;
					sand;
					bspush -32;
					if_scmpne L4;
				L3:	sconst_1;
					sreturn;
				L4:	getfield_a_this 65;		// reference des/ValueRecord.permissions
					sconst_1;
					baload;
					bspush -16;
					sand;
					sload_1;
					sconst_4;
					sshl;
					s2b;
					if_scmpne L6;
				L5:	sconst_1;
					sreturn;
				L6:	getfield_a_this 65;		// reference des/ValueRecord.permissions
					sconst_1;
					baload;
					bspush -16;
					sand;
					bspush -32;
					if_scmpne L8;
				L7:	sconst_1;
					sreturn;
				L8:	sconst_0;
					sreturn;
		}

	}

}
